Workbook
Name Afirmativa: OFFSET('[1]Listas (Hide)'!$B$13,1,MATCH('[1]General Information'!$F$4,'[1]Listas (Hide)'!$B$13:$D$13,0)-1,2)
Name Afirmativa: OFFSET('[2]Listas (Hide)'!$B$13,1,MATCH('[2]General Information'!$F$4,'[2]Listas (Hide)'!$B$13:$D$13,0)-1,2)
Name Afirmativa: OFFSET('Listas (Hide)'!$B$16,1,MATCH(Proposal!#REF!,'Listas (Hide)'!$B$16:$D$16,0)-1,2)
Name Afirmativa: OFFSET('Listas (Hide)'!$B$16,1,MATCH('General Information'!$C$6,'Listas (Hide)'!$B$16:$D$16,0)-1,2)
Name Assistencial: OFFSET('[1]Listas (Hide)'!$B$72,1,MATCH('[1]General Information'!$F$4,'[1]Listas (Hide)'!$B$72:$D$72,0)-1,3)
Name Assistencial: OFFSET('[2]Listas (Hide)'!$B$72,1,MATCH('[2]General Information'!$F$4,'[2]Listas (Hide)'!$B$72:$D$72,0)-1,3)
Name Assistencial: OFFSET('Listas (Hide)'!$B$75,1,MATCH('General Information'!$C$6,'Listas (Hide)'!$B$75:$D$75,0)-1,3)
Name Banco_sangue: OFFSET('[1]Listas (Hide)'!$B$17,1,MATCH('[1]General Information'!$F$4,'[1]Listas (Hide)'!$B$17:$D$17,0)-1,2)
Name Banco_sangue: OFFSET('[2]Listas (Hide)'!$B$17,1,MATCH('[2]General Information'!$F$4,'[2]Listas (Hide)'!$B$17:$D$17,0)-1,2)
Name Banco_sangue: OFFSET('Listas (Hide)'!$B$20,1,MATCH('General Information'!$C$6,'Listas (Hide)'!$B$20:$D$20,0)-1,2)
Name Cloud: OFFSET('[1]Listas (Hide)'!$B$116,1,MATCH('[1]General Information'!$F$4,'[1]Listas (Hide)'!$B$116:$D$116,0)-1,4)
Name Cloud: OFFSET('[2]Listas (Hide)'!$B$115,1,MATCH('[2]General Information'!$F$4,'[2]Listas (Hide)'!$B$115:$D$115,0)-1,4)
Name Cloud: OFFSET('Listas (Hide)'!$B$119,1,MATCH('General Information'!$C$6,'Listas (Hide)'!$B$119:$D$119,0)-1,4)
Name Deslocamento: OFFSET('[1]Listas (Hide)'!$B$80,1,MATCH('[1]General Information'!$F$4,'[1]Listas (Hide)'!$B$80:$D$80,0)-1,5)
Name Deslocamento: OFFSET('[2]Listas (Hide)'!$B$79,1,MATCH('[2]General Information'!$F$4,'[2]Listas (Hide)'!$B$79:$D$79,0)-1,5)
Name Deslocamento: OFFSET('Listas (Hide)'!$B$83,1,MATCH('General Information'!$C$6,'Listas (Hide)'!$B$83:$D$83,0)-1,5)
Name Mercados: OFFSET('[1]Listas (Hide)'!$B$98,1,MATCH('[1]General Information'!$F$4,'[1]Listas (Hide)'!$B$98:$D$98,0)-1,12)
Name Mercados: OFFSET('[2]Listas (Hide)'!$B$97,1,MATCH('[2]General Information'!$F$4,'[2]Listas (Hide)'!$B$97:$D$97,0)-1,12)
Name Mercados: OFFSET('Listas (Hide)'!$B$101,1,MATCH('General Information'!$C$6,'Listas (Hide)'!$B$101:$D$101,0)-1,12)
Name Onda_Implantacao: OFFSET('[1]Listas (Hide)'!$B$65,1,MATCH('[1]General Information'!$F$4,'[1]Listas (Hide)'!$B$65:$D$65,0)-1,2)
Name Onda_Implantacao: OFFSET('[2]Listas (Hide)'!$B$65,1,MATCH('[2]General Information'!$F$4,'[2]Listas (Hide)'!$B$65:$D$65,0)-1,2)
Name Onda_Implantacao: OFFSET('Listas (Hide)'!$B$68,1,MATCH('General Information'!$C$6,'Listas (Hide)'!$B$68:$D$68,0)-1,2)
Name Periodicidade: OFFSET('[1]Listas (Hide)'!$B$56,1,MATCH('[1]General Information'!$F$4,'[1]Listas (Hide)'!$B$56:$D$56,0)-1,4)
Name Periodicidade: OFFSET('[2]Listas (Hide)'!$B$56,1,MATCH('[2]General Information'!$F$4,'[2]Listas (Hide)'!$B$56:$D$56,0)-1,4)
Name Periodicidade: OFFSET('Listas (Hide)'!$B$59,1,MATCH('General Information'!$C$6,'Listas (Hide)'!$B$59:$D$59,0)-1,4)
Name Porte: OFFSET('[1]Listas (Hide)'!XFA1048568,1,MATCH('[1]General Information'!A1048568,'[1]Listas (Hide)'!XFA1048568:XFC1048568,0)-1,4)
Name Porte: OFFSET('[2]Listas (Hide)'!XFA1048568,1,MATCH('[2]General Information'!A1048568,'[2]Listas (Hide)'!XFA1048568:XFC1048568,0)-1,4)
Name Porte: OFFSET('Listas (Hide)'!XFA1048568,1,MATCH(Proposal!A1048568,'Listas (Hide)'!XFA1048568:XFC1048568,0)-1,4)
Name Porte: OFFSET('Listas (Hide)'!XFA1048568,1,MATCH('General Information'!A1048568,'Listas (Hide)'!XFA1048568:XFC1048568,0)-1,4)
Name Porte_Cliente: OFFSET('[1]Listas (Hide)'!$B$4,1,MATCH('[1]General Information'!$F$4,'[1]Listas (Hide)'!$B$4:$D$4,0)-1,6)
Name Porte_Cliente: OFFSET('[2]Listas (Hide)'!$B$4,1,MATCH('[2]General Information'!$F$4,'[2]Listas (Hide)'!$B$4:$D$4,0)-1,6)
Name Porte_Cliente: OFFSET('Listas (Hide)'!$B$4,1,MATCH('General Information'!$C$6,'Listas (Hide)'!$B$4:$D$4,0)-1,6)
Name Porte_v2: 'Listas (Hide)'!$A$5:$D$10
Name Porte_v3: 'Listas (Hide)'!$B$5:$B$10
Name Tipo_proposta: OFFSET('[1]Listas (Hide)'!$B$43,1,MATCH('[1]General Information'!$F$4,'[1]Listas (Hide)'!$B$43:$D$43,0)-1,3)
Name Tipo_proposta: OFFSET('[2]Listas (Hide)'!$B$43,1,MATCH('[2]General Information'!$F$4,'[2]Listas (Hide)'!$B$43:$D$43,0)-1,3)
Name Tipo_proposta: OFFSET('Listas (Hide)'!$B$46,1,MATCH('General Information'!$C$6,'Listas (Hide)'!$B$46:$D$46,0)-1,3)
Name Tipo_usuario: OFFSET('[1]Listas (Hide)'!$B$50,1,MATCH('[1]General Information'!$F$4,'[1]Listas (Hide)'!$B$50:$D$50,0)-1,2)
Name Tipo_usuario: OFFSET('[2]Listas (Hide)'!$B$50,1,MATCH('[2]General Information'!$F$4,'[2]Listas (Hide)'!$B$50:$D$50,0)-1,2)
Name Tipo_usuario: OFFSET('Listas (Hide)'!$B$53,1,MATCH('General Information'!$C$6,'Listas (Hide)'!$B$53:$D$53,0)-1,2)
Name TWS: OFFSET('[1]Listas (Hide)'!$B$89,1,MATCH('[1]General Information'!$F$4,'[1]Listas (Hide)'!$B$89:$D$89,0)-1,4)
Name TWS: OFFSET('[2]Listas (Hide)'!$B$88,1,MATCH('[2]General Information'!$F$4,'[2]Listas (Hide)'!$B$88:$D$88,0)-1,4)
Name TWS: OFFSET('Listas (Hide)'!$B$92,1,MATCH('General Information'!$C$6,'Listas (Hide)'!$B$92:$D$92,0)-1,4)

Sheet Version Control (Old-Delete)
A1: 2 | B1: =HLOOKUP('General Information'!$C$6,'IDIOMA (hide)'!$A$1:$D$5016,A1,0) -> LTEP - Levantamento Técnico de Estimativa de Projeto TASY EMR Código do documento: 0060 - Rev 024
B3: Version Control
B5: Version | C5: Date | D5: Date | E5: Description | F5: Responsible
B6: 12 | C6: 01/Apr/2019 | D6: 43535 | E6: Atualizada horas de implantação, alterada algumas perguntas, criado indicador de plataforma | F6: José Dallabrida
D7: 43538 | E7: Funções com horas 0 foram removidas de todos os escopos | F7: Diogo Benigo
D8: 43539 | E8: Excluido modulo ITEM PRONTUÁRIO, funções criadas PALM | F8: Diogo Benigo
D9: 43545 | E9: Criado planilha SP- Proposta | F9: Diogo Benigo
D10: 43546 | E10: Ajustes nos módulos, funções e perguntas | F10: Diogo Benigo
D11: 43550 | E11: Adicionada a aba de Integrações | F11: Anderson R. Tridapalli
D12: 43551 | E12: 1) Ajuste do Módulo Suporte a Decisão Clínica para ser incluído no caso de Hospital de Pequeno porte; 2) Inclusão de pergunta sobre Oftalmologia para inclusão de 40 horas no Prontuário Eletrônico Paciente; 3) Ajuste do número de horas do item do PEP Oftalmologia para 40 horas. Não há reflexo, mas, é importante manter atualizado. | F12: Anderson R. Tridapalli
D13: 43552 | E13: 1) Todas as funções com horas alteramos para "Sim" a coluna pequeno, médio e grande. 2) Ajustamos a pergunta "Data Privacy", adicionado um código de função ao processo. 3) Ajustamos as horas de teste piloto, processo de virada e acompanhamento pós virada. | F13: José Dallabrida
D14: 43553 | E14: 1) Ajustes do idioma das perguntas 2) Mais expressões por idioma 3) Inclusão de mais perguntas para geração da estimativa | F14: Anderson R. Tridapalli
D15: 01/Apr/2019 | E15: 1) Melhoria nas traduções 2) Incluída a pergunta de Hemodiálise Externa 3) Incluída a pergunta/orientação Protocolo de Manchester | F15: Jade Kraft
B16: 13 | C16: 09/Apr/2019 | D16: 09/Apr/2019 | E16: 1) Inclusão Digifull 2) Sugestões do Treinamentos: 2.1) Multisite - Adicionar combo box 2.2) Classificar perguntas por areas 2.3) Sepses-nova mensagem 2.4) mensagem de observação (parte de integrações) 2.5) limitação de % de gerenciamento (20% mínimo – Full 100% máximo) 2.6) limitação de número de horas referente ao projeto, conforme conversamos em reunião 2.7) validação da instalação (nao instalação do produto) 2.8) campo "fase" 1ª onda, 2ª onda em detalhe de horas 3) Inclusão NPI – Processo padrão NPI; 4) Melhorias em geral: 4.1) Corrigir idioma das respostas (Sim, Não) 4.2) Melhorar a forma de definição do Porte do Cliente e incluir opção de “Todas as funções por módulo” 4.2.1) Alterar descrição para “Porte do Cliente” 4.2.2) Adicionar a opção “Todas as funções dos módulos” 4.2.3) Adicionar coluna “Todas as funções dos módulos” na aba Base de Funções, marcando todas funções com mais de 0 horas para Sim 4.2.4) Atualizar a última versão para habilitar os portes e incluir sim ou não nas colunas dos portes na aba Base de Funções 5) Ordenar perguntas para fazerem sentido numa sequência lógica 6) Melhorar a pergunta da GQA sobre os indicadores de Sepse, Protocolo Manchester e Data Privacy 7) Indicador de alteração do Detalhe de Horas (informação diferente da planilha original com cor diferente e legenda) 8) Organizar os módulos por sequencia logica do sistema. | F16: Anderson R. Tridapalli, Diogo Benigo, José Dallabrida, Jade Kraft
B17: 14 | C17: 23/Apr/2019 | D17: 23/Apr/2019 | E17: 1) Tratado respostas em idiomas diferentes na planilha Perguntas. 2) Criada validação para respostas numéricas na planilha Perguntas. 3) Alterado a descrição das fases do projeto. 4) Melhorias em traduções 5) Inclusão do canal de vendas Philips Vendas Direta na planilha SP-PROPOSTA. 6) Alterada descrição do Deslocamento na planilha SP-PROPOSTA. 7) Alterado a descrição do campo B5 na planilha SP-PROPOSTA. | F17: Diogo Benigo
B18: 15 | C18: 43634 | D18: 43634 | E18: 1) Inclusão de horas de implantação para Gestão Populacional. 2) Inclusão de horas para clinicas pequenas e grandes. 3) Inclusão do módulo PEP/ CPOE / ADEP na Planilha Perguntas. 4) Melhorias em traduções. 5) Inclusão da Pergunta para implantação de Certificação Digital na Planilha Perguntas e acrescimo de 120h para implantação da opção. 6) Inclusão da Opção Consultório Médico (Ambulatório) na planilha Módulos. 7)Exclusão do Módulos - Call Center e funções vinculadas. Planejamento Estratégico e funções vinculadas. 8) Módulo PEP - Cadastro de Protocolos e Cadastros PEP - alterarado para 1 hora em ambos. 9) Inclusão da Pergunta "A função Gestão dos Planos Terapêuticos será utilizada em qual setor?" e opções - se "Enfermagem e Farmácia" adição (+100% de horas) 10) Alterado para 20% de acrescimo HTML5 11) Alterado Função “Laudo de Anatomia patológica” 12) Inclusa Tarja Vermelha na aba resumo: "Após preenchimento das informações prévias, atualizar o resumo com o botão direito sob a tabela da estimativa". 13) Inclusão da pasta de premissas: "Sugestões de Premissas" 14) Inclusão de Opção para aquisição de Cloud "Informações Gerais" | F18: Diogo Benigo, Anderson R. Tridapalli, Gaspar I. Borges, Fernanda Maciel, Everson Luis Faita, Antonio Peixer
B19: 16 | C19: 43643 | D19: 43634 | E19: 1) Alteração na aba Módulos - item "Prontuário Eletrônico" sai da área 'Core do sistema' e passa a pertencer ao área 'Assistencial'. 2) Alteração na aba Detalhe de Horas - Organização linear sequencial seguindo o mesmo padrão da aba Módulos. | F19: Gaspar I. Borges
B20: 17 | C20: 43656 | D20: 43634 | E20: 1) Inclusão da coluna "Observações" na aba Resumo. 2) Inclusão da coluna "Horas de Consultoria" na aba Integrações e automatização de cálculo para inclusão das horas no resumo. 3) Ajuste nas funções (REP - REP-PT - CPOE - Atendimento da Prescrição - Atendimento do lote) alteração de sugestão de inclusão em escopo por tamanho de cliente. 4) Melhorias em traduções. | F20: Gaspar I. Borges, Evandro Polastri, Anderson R. Tridapalli
B21: 18 | C21: 43692 | D21: 43634 | E21: 1) Inclusão da Pergunta "TWS -Tasy Web Suite"; 2) Inclusão de lista suspensa na aba "SP - Proposta" itém "Deslocamento" com opções; 3) Ajuste nas funções (orçamento contabil, infecção hospitalar, nutrição) alteração de sugestão de inclusão em escopo por tamanho de cliente; 4) Inclusão de Mensagens de alerta para a aplicação "TWS - Tasy Web Suite" nas abas "Módulos" e "Perguntas"; 5) Melhorias em traduções. | F21: Gaspar I. Borges
B22: 19 | C22: 43732 | D22: 43634 | E22: 1) Tradução dos Nomes das Abas para o idioma "Inglês" 2) Alteração e padronização da aba "Integrations" 3) Alteração da Pergunta "TWS" para aba "Proposal" 4) Inclusão dos campos "Modalidade" e "Valor" Cloud na aba "Proposal" 5) Inclusão da aba "TWS" 6) Inclusão do desclaimer "Em caso de oferta Java, HTML5 ou Cloud HTML5 não há possibilidade de integrações via banco de dados." na aba "Intagrations". 7) Inclusão do desclaimer "Sugestões de Premissas para serem inclusas em contrato." na aba "Assumptions Suggestion". 8) Melhorias em traduções. | F22: Gaspar I. Borges
B23: 20 | C23: 43756 | E23: 1) Retirado o aviso de aprovação necessária para projetos em HTML5; 2) Inclusa a SC - Solicitação de Contrato e informações solicitadas pelo KLAS; 3) Inseridos cálculos automáticos da proposta e do OIT; 4) Adicionado racional para inclusão de 110% nas horas caso o projeto seja Grande ou caso tenha integração/customização e/ou migração de dados. | F23: Rafael dos Santos Pellens, Gaspar l. Borges, Anderson R. Tridapalli
B24: 21 | C24: 43909 | E24: 1) Incluso aba para sugestão de horas e justificativas para Vendas e PMO na aba "Summary"; 2) Incluso campo para descrever a estratégia de implantação na aba "Summary"; 3) Incluso camos somatórios para cada sugestão (vendas e PMO) na aba "Summary"; 4) Inclusão de somatória das horas e valor hora na aba "Summary"; | F24: Rafael dos Santos Pellens
E25: Nota: Alterações relacionadas a revisões anteriores do documento não foram capturadas como parte da tabela de histórico de revisão acima e as alterações relacionadas à revisão são destacadas no próprio documento.

Sheet Version Control 
A1: 2 | B1: =HLOOKUP('General Information'!$C$6,'IDIOMA (hide)'!$A$1:$D$5016,A1,0) -> LTEP - Levantamento Técnico de Estimativa de Projeto TASY EMR Código do documento: 0060 - Rev 024
B7: Version | C7: Date | D7: Date | E7: Description | F7: Responsible
B8: 12 | C8: 01/Apr/2019 | D8: 43535 | E8: Atualizada horas de implantação, alterada algumas perguntas, criado indicador de plataforma | F8: José Dallabrida
D9: 43538 | E9: Funções com horas 0 foram removidas de todos os escopos | F9: Diogo Benigo
D10: 43539 | E10: Excluido modulo ITEM PRONTUÁRIO, funções criadas PALM | F10: Diogo Benigo
D11: 43545 | E11: Criado planilha SP- Proposta | F11: Diogo Benigo
D12: 43546 | E12: Ajustes nos módulos, funções e perguntas | F12: Diogo Benigo
D13: 43550 | E13: Adicionada a aba de Integrações | F13: Anderson R. Tridapalli
D14: 43551 | E14: 1) Ajuste do Módulo Suporte a Decisão Clínica para ser incluído no caso de Hospital de Pequeno porte; 2) Inclusão de pergunta sobre Oftalmologia para inclusão de 40 horas no Prontuário Eletrônico Paciente; 3) Ajuste do número de horas do item do PEP Oftalmologia para 40 horas. Não há reflexo, mas, é importante manter atualizado. | F14: Anderson R. Tridapalli
D15: 43552 | E15: 1) Todas as funções com horas alteramos para "Sim" a coluna pequeno, médio e grande. 2) Ajustamos a pergunta "Data Privacy", adicionado um código de função ao processo. 3) Ajustamos as horas de teste piloto, processo de virada e acompanhamento pós virada. | F15: José Dallabrida
D16: 43553 | E16: 1) Ajustes do idioma das perguntas 2) Mais expressões por idioma 3) Inclusão de mais perguntas para geração da estimativa | F16: Anderson R. Tridapalli
D17: 01/Apr/2019 | E17: 1) Melhoria nas traduções 2) Incluída a pergunta de Hemodiálise Externa 3) Incluída a pergunta/orientação Protocolo de Manchester | F17: Jade Kraft
B18: 13 | C18: 09/Apr/2019 | D18: 09/Apr/2019 | E18: 1) Inclusão Digifull 2) Sugestões do Treinamentos: 2.1) Multisite - Adicionar combo box 2.2) Classificar perguntas por areas 2.3) Sepses-nova mensagem 2.4) mensagem de observação (parte de integrações) 2.5) limitação de % de gerenciamento (20% mínimo – Full 100% máximo) 2.6) limitação de número de horas referente ao projeto, conforme conversamos em reunião 2.7) validação da instalação (nao instalação do produto) 2.8) campo "fase" 1ª onda, 2ª onda em detalhe de horas 3) Inclusão NPI – Processo padrão NPI; 4) Melhorias em geral: 4.1) Corrigir idioma das respostas (Sim, Não) 4.2) Melhorar a forma de definição do Porte do Cliente e incluir opção de “Todas as funções por módulo” 4.2.1) Alterar descrição para “Porte do Cliente” 4.2.2) Adicionar a opção “Todas as funções dos módulos” 4.2.3) Adicionar coluna “Todas as funções dos módulos” na aba Base de Funções, marcando todas funções com mais de 0 horas para Sim 4.2.4) Atualizar a última versão para habilitar os portes e incluir sim ou não nas colunas dos portes na aba Base de Funções 5) Ordenar perguntas para fazerem sentido numa sequência lógica 6) Melhorar a pergunta da GQA sobre os indicadores de Sepse, Protocolo Manchester e Data Privacy 7) Indicador de alteração do Detalhe de Horas (informação diferente da planilha original com cor diferente e legenda) 8) Organizar os módulos por sequencia logica do sistema. | F18: Anderson R. Tridapalli, Diogo Benigo, José Dallabrida, Jade Kraft
B19: 14 | C19: 23/Apr/2019 | D19: 23/Apr/2019 | E19: 1) Tratado respostas em idiomas diferentes na planilha Perguntas. 2) Criada validação para respostas numéricas na planilha Perguntas. 3) Alterado a descrição das fases do projeto. 4) Melhorias em traduções 5) Inclusão do canal de vendas Philips Vendas Direta na planilha SP-PROPOSTA. 6) Alterada descrição do Deslocamento na planilha SP-PROPOSTA. 7) Alterado a descrição do campo B5 na planilha SP-PROPOSTA. | F19: Diogo Benigo
B20: 15 | C20: 43634 | D20: 43634 | E20: 1) Inclusão de horas de implantação para Gestão Populacional. 2) Inclusão de horas para clinicas pequenas e grandes. 3) Inclusão do módulo PEP/ CPOE / ADEP na Planilha Perguntas. 4) Melhorias em traduções. 5) Inclusão da Pergunta para implantação de Certificação Digital na Planilha Perguntas e acrescimo de 120h para implantação da opção. 6) Inclusão da Opção Consultório Médico (Ambulatório) na planilha Módulos. 7)Exclusão do Módulos - Call Center e funções vinculadas. Planejamento Estratégico e funções vinculadas. 8) Módulo PEP - Cadastro de Protocolos e Cadastros PEP - alterarado para 1 hora em ambos. 9) Inclusão da Pergunta "A função Gestão dos Planos Terapêuticos será utilizada em qual setor?" e opções - se "Enfermagem e Farmácia" adição (+100% de horas) 10) Alterado para 20% de acrescimo HTML5 11) Alterado Função “Laudo de Anatomia patológica” 12) Inclusa Tarja Vermelha na aba resumo: "Após preenchimento das informações prévias, atualizar o resumo com o botão direito sob a tabela da estimativa". 13) Inclusão da pasta de premissas: "Sugestões de Premissas" 14) Inclusão de Opção para aquisição de Cloud "Informações Gerais" | F20: Diogo Benigo, Anderson R. Tridapalli, Gaspar I. Borges, Fernanda Maciel, Everson Luis Faita, Antonio Peixer
B21: 16 | C21: 43643 | D21: 43634 | E21: 1) Alteração na aba Módulos - item "Prontuário Eletrônico" sai da área 'Core do sistema' e passa a pertencer ao área 'Assistencial'. 2) Alteração na aba Detalhe de Horas - Organização linear sequencial seguindo o mesmo padrão da aba Módulos. | F21: Gaspar I. Borges
B22: 17 | C22: 43656 | D22: 43634 | E22: 1) Inclusão da coluna "Observações" na aba Resumo. 2) Inclusão da coluna "Horas de Consultoria" na aba Integrações e automatização de cálculo para inclusão das horas no resumo. 3) Ajuste nas funções (REP - REP-PT - CPOE - Atendimento da Prescrição - Atendimento do lote) alteração de sugestão de inclusão em escopo por tamanho de cliente. 4) Melhorias em traduções. | F22: Gaspar I. Borges, Evandro Polastri, Anderson R. Tridapalli
B23: 18 | C23: 43692 | D23: 43634 | E23: 1) Inclusão da Pergunta "TWS -Tasy Web Suite"; 2) Inclusão de lista suspensa na aba "SP - Proposta" itém "Deslocamento" com opções; 3) Ajuste nas funções (orçamento contabil, infecção hospitalar, nutrição) alteração de sugestão de inclusão em escopo por tamanho de cliente; 4) Inclusão de Mensagens de alerta para a aplicação "TWS - Tasy Web Suite" nas abas "Módulos" e "Perguntas"; 5) Melhorias em traduções. | F23: Gaspar I. Borges
B24: 19 | C24: 43732 | D24: 43634 | E24: 1) Tradução dos Nomes das Abas para o idioma "Inglês" 2) Alteração e padronização da aba "Integrations" 3) Alteração da Pergunta "TWS" para aba "Proposal" 4) Inclusão dos campos "Modalidade" e "Valor" Cloud na aba "Proposal" 5) Inclusão da aba "TWS" 6) Inclusão do desclaimer "Em caso de oferta Java, HTML5 ou Cloud HTML5 não há possibilidade de integrações via banco de dados." na aba "Intagrations". 7) Inclusão do desclaimer "Sugestões de Premissas para serem inclusas em contrato." na aba "Assumptions Suggestion". 8) Melhorias em traduções. | F24: Gaspar I. Borges
B25: 20 | C25: 43756 | E25: 1) Retirado o aviso de aprovação necessária para projetos em HTML5; 2) Inclusa a SC - Solicitação de Contrato e informações solicitadas pelo KLAS; 3) Inseridos cálculos automáticos da proposta e do OIT; 4) Adicionado racional para inclusão de 110% nas horas caso o projeto seja Grande ou caso tenha integração/customização e/ou migração de dados. | F25: Rafael dos Santos Pellens, Gaspar l. Borges, Anderson R. Tridapalli
B26: 21 | C26: 43909 | E26: 1) Incluso aba para sugestão de horas e justificativas para Vendas e PMO na aba "Summary"; 2) Incluso campo para descrever a estratégia de implantação na aba "Summary"; 3) Incluso camos somatórios para cada sugestão (vendas e PMO) na aba "Summary"; 4) Inclusão de somatória das horas e valor hora na aba "Summary"; | F26: Rafael dos Santos Pellens
B27: 22 | C27: 43955 | E27: 1) Inclusão das NPIs: CarePlan, Patient Journey, Tele Consulta, Contabilidade Online, Mapa Ocupação Quimioterapia, TNM, Neo Center,PEPA na aba "Questions" e "Base Funções" quando aplicável. 2) Inclusão da opção de escolha da "Moeda" em General Information; 3) Inclusão de uma quantidade de horas exclusiva para o México na aba "Base Funções"; 4) Redução dos 20% da consultoria em "Base Funções"; 5) Pequenos outros ajustes de traduções e etc. | F27: Rafael dos Santos Pellens
B28: 23 | C28: 43993 | E28: 1) Ajuste em "Modules", correções de fórmulas; 2) Ajuste em "Questions", perguntas que são específicas para um mercado, ficam como "Não Aplicáveis" para os outros idiomas; 3) Retirado o adicional de 10% para hospitais de porte grande na aba "Hours Detail"; 4) Ajustes pequenos em traduções gerais; 5) Ajuste nas fórmulas de OIT da aba "Proposal"; 6) Inclusão do valor hora de RnD na aba "Proposal". 7) Ajustes no porte da instituição em "BASE_FUNÇÕES". Antes, alguns módulos não apareciam mesmo selecionando sim em "Modules" porque não estavam previstos na aba "BASE_FUNÇÕES", agora isso foi solucionado. | F28: Rafael dos Santos Pellens
B29: 24 | E29: 1) Inclusão do produto OPS. 2) Inclusão da aba "OIT Saas" que serve para calcular automaticamente o OIT do SaaS, levando em consideração o escalonamento. 3) Inclusão da aba "Rollout" que tenta automatizar projetos que utilizarão a metodologia Rollout. 4) Inclusão da aba "Backoffice" que copia e cola informações gerais da LTEP para automatizar o preenchimento da proposta. 5) Exclusão de diversas funções que já não são mais utilizadas na aba "BASE_FUNÇÕES" 6) Revisão na aba "Questions", de forma geral, para diversas perguntas, só temos horas adicionais quando temos uma resposta acima de 1 (porque em teoria, se a resposta for 1, já temos as horas da funções previstas". Além disso, foram retiradas perguntas consideradas desnecessárias. 7) Inclusão dos NPIs: Planejamento Orçamentário, Launch Dashboard, Auditoria Concorrente 8) Revisão na aba proposal, melhorando a parte de SAAS e demais cenários. Revisão também na parte do cálculo de OIT. 10) Inclusão das modalides de Operadora; 11) Deletada a parte de integrações antiga e incluída a aba de integrações nova, com as integrações previstas; 12) Inclusão do RnD (integrações) no escopo da LTEP; 13) Revisão na aba "Questions" para que a quantiade de consultores seja gerada de acordo com o tempo de projeto desejado. 14) Adicionada a parte de escopo negativo, porém, ainda não será liberada até que tenhamos a descrição de todos os módulos em PT. | F29: Rafael dos Santos Pellens
E30: Nota: Alterações relacionadas a revisões anteriores do documento não foram capturadas como parte da tabela de histórico de revisão acima e as alterações relacionadas à revisão são destacadas no próprio documento.

Sheet Pendências
A1: Solicitante | B1: Solicitação | C1: Status | D1: Situação
A2: Fernanda | B2: Para revisão, o LTEP – 23 não está puxando o módulo de Rouparia, mesmo com o módulo selecionado no “Sim”, somente quando seleciona a opção “Todas as funções”. | C2: OK
A3: NPI | B3: 13820 Planejamento Orçamentário. | C3: OK | D3: Validar com Dallabrida quais são as funções necessárias para usar o orçamento contábil. | E3: Plano de ImplementaçãoConhecendo a função e entendendo o vínculo desta função com o Orçamento Contábil, entendemos que a função Orçamento Contábil deverá ser vendida em conjunto com esta função, assim, considerando as 40 horas do orçamento, só precisaremos manter 4 horas com esta função - em 1 semana podemos implementar ambos.
A4: NPI | B4: Processo de Launch Dashboard | C4: OK
A5: NPI | B5: Auditoria Concorrente | C5: OK | D5: Temos as horas mas não tivemos product news, não foi lançado. | E5: 2081937 | F5: 2081938
A6: NPI | B6: Portal do Beneficiário | C6: Falta código e traduções. | D6: Inserir na parte de proposta e na parte de horas. | E6: Plano de ImplementaçãoPara implementação do novo processo do Portal do Beneficiário são necessárias 32 horas. Contudo,será necessário a revisão da estimativa de OPS, retirando as funções antigas que eram usadas no Delphi e acrescendo esta nova.Para a migração de OPS (clientes da base instalada), este novo processo pode ser executado pelo cliente, sem a necessidade de alocação de um consultor, considerando-se 16 horas, pois aproveita-se o que o cliente já utilizar na plataforma em Delphi.Observações: Em ambos os casos, seja uma implantação inicial ou uma migração, o consultor somente poderá ser alocado após a conclusãoda infraestrutura necessária para rodar o portal. Relembrando que a instalação da infraestrutura para o Portal do Beneficiário rodar fica a cargo do cliente ou de um parceiro homologado Philips, e não faz parte do escopo de implantação do time de serviços(consultoria), ou seja, as horas acima não comportam o trabalho de infraestrutura.
A7: NPI | B7: Panorama Clínico | C7: OK | D7: OK. Colocamos 20 horas na nova função (painel) e não colocamos as 3 horas de ADM e 1 de cadastros gerais. | E7: Plano de implantação: Cronogramas de implantação revisados –24 horas para implementação, sendo:ADM TASY -3horasCadastros Gerais -1 horaNova função "Painel do Panorama Clínico" -20 horasInformações comerciais: Base de demonstração do Pré Vendas atualizada e disponível para demonstrações. LTEP de Vendas e Pós Vendas atualizado. Nenhuma alteração na Política e Proposta Comercial.
A8: OPS | B8: Colocar módulos e funções padrões no OPS | C8: OK | E8: Validar módulos e validar horas
A9: Fernanda | B9: • Gestão das Prescrições pela Enfermagem • Gestão das Prescrições pela Farmácia Clínica • SAE – Sistematização da Assistência de Enfermagem • Laudo Paciente | C9: Pendente | E9: As duas últimas OK, as 2 primeiras validar com RnD.
A10: OPS | B10: 1 – Haverá acompanhamento do monitoramento ANS? (acrescer 40 horas), normalmente o envio do primeiro monitoramento ocorre 2 meses após a virada. | C10: OK
A11: OPS | B11: 2 – Haverá acompanhamento para o SIP? (acrescer 40 horas), normalmente o envio do primeiro SIP ocorre 4 meses após a virada. | C11: OK
A12: OPS | B12: 3 – Haverá acompanhamento para o DIOPS e geração livros auxiliares para auditoria? (acrescer 80 horas), normalmente o envio do primeiro DIOPS ocorre 4 meses após a virada. | C12: OK
A13: OPS | B13: 5 – Quantidade de beneficiários? (aumentar 20% das horas do projeto a cada 80.000) | C13: Pendente
A14: OPS | B14: HDM? | C14: OK
A15: OPS | B15: Funções exclusivas Unimed | C15: OK | D15: Todas as funções que são exclusivas Unimed tem que estrar como No na autogestão e med grupo
A16: Fernanda | B16: 4Test (Função só p/ Java) Schematic4Test (Função só p/ HTML5) | C16: Pendente | D16: Confirmado com Dallabrida, colocar dessa forma nas horas.

Sheet General Information
A1: 2 | B1: =HLOOKUP($C$6,'IDIOMA (hide)'!$A$1:$D$5016,A1,0) -> LTEP - Levantamento Técnico de Estimativa de Projeto TASY EMR Código do documento: 0060 - Rev 024
A2: 3 | B2: =HLOOKUP($C$6,'IDIOMA (hide)'!$A$1:$D$5016,A2,0) -> General Information | D2: OCULTAR
A4: 5 | B4: =HLOOKUP($C$6,'IDIOMA (hide)'!$A$1:$D$5016,A4,0) -> País | G4: =IF(C$4="Brasil","Guia de Segmentação (Para Brasil)","")
B5: =IF(OR(C4="Outro",C4="Other",C4="Otro")=TRUE,HLOOKUP($C$6,'IDIOMA (hide)'!$A$1:$D$5016,A5,0),HLOOKUP($C$6,'IDIOMA (hide)'!$A$1:$D$5016,A7,0)) -> Não Preencher | G5: =IF($C$4="Brasil","Hospitais","")
A6: 40 | B6: =HLOOKUP($C$6,'IDIOMA (hide)'!$A$1:$D$5016,A6,0) -> Idioma | C6: Português | G6: =IF($C$4="Brasil","Pequeno","") | H6: =IF($C$4="Brasil","Até 100 Leitos","")
A7: 361 | B7: =HLOOKUP($C$6,'IDIOMA (hide)'!$A$1:$D$5016,E8,0) -> Moeda | G7: =IF($C$4="Brasil","Médio","") | H7: =IF($C$4="Brasil","De 101 até 300 Leitos","")
E8: 480 | G8: =IF($C$4="Brasil","Grande","") | H8: =IF($C$4="Brasil","De 301 até 500 Leitos","")
A9: 6 | B9: =HLOOKUP($C$6,'IDIOMA (hide)'!$A$1:$D$5016,A9,0) -> Informações do Cliente | C9: =HLOOKUP($C$6,'IDIOMA (hide)'!$A$1:$D$5016,B9,0) -> #REF! | G9: =IF($C$4="Brasil","Gigante","") | H9: =IF($C$4="Brasil","Acima de 500 Leitos","")
A10: 7 | B10: =HLOOKUP($C$6,'IDIOMA (hide)'!$A$1:$D$5016,A10,0) -> ID Oportunidade | G10: =IF($C$4="Brasil","OPS - Operadoras de Saúde","")
A11: 8 | B11: =HLOOKUP($C$6,'IDIOMA (hide)'!$A$1:$D$5016,A11,0) -> Nome do Cliente | G11: =IF($C$4="Brasil","Pequeno","") | H11: =IF($C$4="Brasil","Menos de 20 mil vidas","")
A12: 9 | B12: =HLOOKUP($C$6,'IDIOMA (hide)'!$A$1:$D$5016,A12,0) -> Contato | G12: =IF($C$4="Brasil","Médio","") | H12: =IF($C$4="Brasil","De 20 a 100 mil vidas","")
A13: 13 | B13: =HLOOKUP($C$6,'IDIOMA (hide)'!$A$1:$D$5016,A13,0) -> Número de Leitos | G13: =IF($C$4="Brasil","Grande","") | H13: =IF($C$4="Brasil","Acima de 100 mil vidas","")
A14: 409 | B14: =HLOOKUP($C$6,'IDIOMA (hide)'!$A$1:$D$5016,A14,0) -> Sistema anterior (a ser substituído) | G14: =IF($C$4="Brasil","Clínicas","")
A15: 504 | B15: =HLOOKUP($C$6,'IDIOMA (hide)'!$A$1:$D$5016,A15,0) -> Será uma proposta no Modelo Trade In? | E15: 200 | G15: =IF($C$4="Brasil","Pequena","") | H15: =IF($C$4="Brasil","Até 2 Unidades / Faturamento até 5 M/Ano","")
A16: 76 | B16: =HLOOKUP($C$6,'IDIOMA (hide)'!$A$1:$D$5016,A16,0) -> Funções sugeridas pelo porte do cliente | D16: =IF(OR(C16='Listas (Hide)'!D5,C16='Listas (Hide)'!B5,C16='Listas (Hide)'!C5)=TRUE,1,IF(OR(C16='Listas (Hide)'!D6,C16='Listas (Hide)'!B6,C16='Listas (Hide)'!C6)=TRUE,2,IF(OR(C16='Listas (Hide)'!D7,C16='Listas (Hide)'!B7,C16='Listas (Hide)'!C7)=TRUE,3,IF(OR(C16='Listas (Hide)'!D8,C16='Listas (Hide)'!B8,C16='Listas (Hide)'!C8)=TRUE,4,IF(OR(C16='Listas (Hide)'!D9,C16='Listas (Hide)'!B9,C16='Listas (Hide)'!C9)=TRUE,5,IF(OR(C16='Listas (Hide)'!D10,C16='Listas (Hide)'!B10,C16='Listas (Hide)'!C10)=TRUE,6,IF(C16='Listas (Hide)'!B11,7,IF(C16='Listas (Hide)'!B12,8,IF(C16='Listas (Hide)'!B13,9,"Erro"))))))))) -> Erro | E16: =HLOOKUP($C$6,'IDIOMA (hide)'!$A$1:$D$5016,E15,0) -> *Campo Obrigatório para gerar estimativa | G16: =IF($C$4="Brasil","Médio","") | H16: =IF($C$4="Brasil","De 3 a 6 Unidades / Faturamento de 5 a 20 M/Ano","")
A17: 505 | B17: =HLOOKUP($C$6,'IDIOMA (hide)'!$A$1:$D$5016,A17,0) -> Funções Sugeridas pela modalidade (OPS) | D17: =IF(OR(C17='Listas (Hide)'!D5,C17='Listas (Hide)'!B5,C17='Listas (Hide)'!C5)=TRUE,1,IF(OR(C17='Listas (Hide)'!D6,C17='Listas (Hide)'!B6,C17='Listas (Hide)'!C6)=TRUE,2,IF(OR(C17='Listas (Hide)'!D7,C17='Listas (Hide)'!B7,C17='Listas (Hide)'!C7)=TRUE,3,IF(OR(C17='Listas (Hide)'!D8,C17='Listas (Hide)'!B8,C17='Listas (Hide)'!C8)=TRUE,4,IF(OR(C17='Listas (Hide)'!D9,C17='Listas (Hide)'!B9,C17='Listas (Hide)'!C9)=TRUE,5,IF(OR(C17='Listas (Hide)'!D10,C17='Listas (Hide)'!B10,C17='Listas (Hide)'!C10)=TRUE,6,IF(C17='Listas (Hide)'!B11,7,IF(C17='Listas (Hide)'!B12,8,IF(C17='Listas (Hide)'!B13,9,"Erro"))))))))) -> Erro | E17: =HLOOKUP($C$6,'IDIOMA (hide)'!$A$1:$D$5016,E15,0) -> *Campo Obrigatório para gerar estimativa
A18: 506 | B18: =HLOOKUP($C$6,'IDIOMA (hide)'!$A$1:$D$5016,A18,0) -> Produto | G18: =IF($C$4="Brasil","Grande","") | H18: =IF($C$4="Brasil","Acima de 7 Unidades / Faturamento acima de 20 M/Ano","")
A19: 199 | B19: =HLOOKUP($C$6,'IDIOMA (hide)'!$A$1:$D$5016,A19,0) -> Plataforma
A20: 345 | B20: =HLOOKUP($C$6,'IDIOMA (hide)'!$A$1:$D$5016,A20,0) -> Oferta Cloud / SaaS / Nuvem

Sheet Proposal
A1: 2 | B1: =HLOOKUP('General Information'!$C$6,'IDIOMA (hide)'!$A$1:$D$5016,A1,0) -> LTEP - Levantamento Técnico de Estimativa de Projeto TASY EMR Código do documento: 0060 - Rev 024
A3: 198 | B3: =HLOOKUP('General Information'!$C$6,'IDIOMA (hide)'!$A$1:$D$5016,A3,0) -> SP - Solicitação de Proposta
A4: 160 | B4: =HLOOKUP('General Information'!$C$6,'IDIOMA (hide)'!$A$1:$D$5016,A4,0) -> Informações Gerais
A7: 141 | B7: =HLOOKUP('General Information'!$C$6,'IDIOMA (hide)'!$A$1:$D$5016,A7,0) -> Informações sobre o Cliente
A8: 77 | B8: =HLOOKUP('General Information'!$C$6,'IDIOMA (hide)'!$A$1:$D$5016,A8,0) -> CNPJ
A9: 79 | B9: =HLOOKUP('General Information'!$C$6,'IDIOMA (hide)'!$A$1:$D$5016,A9,0) -> Razão Social
A10: 80 | B10: =HLOOKUP('General Information'!$C$6,'IDIOMA (hide)'!$A$1:$D$5016,A10,0) -> Nome Fantasia
A11: 81 | B11: =HLOOKUP('General Information'!$C$6,'IDIOMA (hide)'!$A$1:$D$5016,A11,0) -> Tipo de Proposta
A12: 82 | B12: =HLOOKUP('General Information'!$C$6,'IDIOMA (hide)'!$A$1:$D$5016,A12,0) -> Forma de Licenciamento
A13: 83 | B13: =HLOOKUP('General Information'!$C$6,'IDIOMA (hide)'!$A$1:$D$5016,A13,0) -> Número de Licenças
A14: 471 | B14: =HLOOKUP('General Information'!$C$6,'IDIOMA (hide)'!$A$1:$D$5016,A14,0) -> Qual template de proposta deseja receber?
A15: 161 | B15: =HLOOKUP('General Information'!$C$6,'IDIOMA (hide)'!$A$1:$D$5016,A15,0) -> Dados Comerciais
B18: Informações Gerais e Condições de Pgto | E18: Cálculo OIT
A19: 427 | B19: =HLOOKUP('General Information'!$C$6,'IDIOMA (hide)'!$A$1:$D$5016,A19,0) -> Vigência do Contrato | D19: 419 | E19: =HLOOKUP('General Information'!$C$6,'IDIOMA (hide)'!$A$1:$D$5016,D19,0) -> Tipo de Venda | F19: Philips
A20: 428 | B20: =HLOOKUP('General Information'!$C$6,'IDIOMA (hide)'!$A$1:$D$5016,A20,0) -> Carência na Manutenção (em meses) | D20: 420 | E20: =HLOOKUP('General Information'!$C$6,'IDIOMA (hide)'!$A$1:$D$5016,D20,0) -> Licença | F20: =IF(C11="CDU/SaaP",C23*C13,IF(C11="LUT/SAAS","0",IF(OR(C11="CDU+LUT",OR(C11="CDU+LUT+Cloud"),OR(C11="CDU+Cloud")),C23*C13,0))) -> 0
A21: 90 | B21: =HLOOKUP('General Information'!$C$6,'IDIOMA (hide)'!$A$1:$D$5016,A21,0) -> Os impostos estão inclusos no valor hora? | E21: =HLOOKUP('General Information'!$C$6,'IDIOMA (hide)'!$A$1:$D$5016,D23,0) -> Consultoria | F21: =Rollout!AE18*Proposal!C32 -> 0
A22: 492 | B22: =HLOOKUP('General Information'!$C$6,'IDIOMA (hide)'!$A$1:$D$5016,A22,0) -> Proposta - CDU | E22: =HLOOKUP('General Information'!$C$6,'IDIOMA (hide)'!$A$1:$D$5016,D24,0) -> Gerenciamento de Projeto | F22: =Rollout!AE19*Proposal!C33 -> 0
A23: 86 | B23: =HLOOKUP('General Information'!$C$6,'IDIOMA (hide)'!$A$1:$D$5016,A23,0) -> Valor CDU | D23: 422 | E23: =HLOOKUP('General Information'!$C$6,'IDIOMA (hide)'!$A$1:$D$5016,D25,0) -> R&D | F23: =IF(C34="",0,(Rollout!AE20*C34)) -> 0
A24: 87 | B24: =HLOOKUP('General Information'!$C$6,'IDIOMA (hide)'!$A$1:$D$5016,A24,0) -> Valor da Manutenção | D24: 423 | E24: =HLOOKUP('General Information'!$C$6,'IDIOMA (hide)'!$A$1:$D$5016,D26,0) -> Manutenção | F24: =IF(C11="CDU/SaaP",C24*C13*(C19-C20),IF(C11="LUT/SaaS",(C13*C30*C19),IF(C11="LUT+Cloud",C29*C19,IF(C11="SaaS (Cloud)",'OIT SaaS'!#REF!,IF(OR(C11="CDU+LUT",OR(C11="CDU+LUT+Cloud"),OR(C11="CDU+Cloud")),(C24*C13)*(C19-C20),0))))) -> 0
A25: 417 | B25: =HLOOKUP('General Information'!$C$6,'IDIOMA (hide)'!$A$1:$D$5016,A25,0) -> Valor Total Manutenção CDU (Mensal) | C25: =C24*C13 -> 0 | D25: 424 | E25: =HLOOKUP('General Information'!$C$6,'IDIOMA (hide)'!$A$1:$D$5016,D28,0) -> OIT | F25: =IF(F19="Channel",F20+F24+F23,IF(F19="Philips",F20+F24+F21+F22+F23,"")) -> 0
A26: 91 | B26: =HLOOKUP('General Information'!$C$6,'IDIOMA (hide)'!$A$1:$D$5016,A26,0) -> Parcelas? (Quantidade) | D26: 421 | E26: =HLOOKUP('General Information'!$C$6,'IDIOMA (hide)'!$A$1:$D$5016,D29,0) -> Taxa | F26: =F25-'Listas (Hide)'!B129 -> 0
A27: 533 | B27: =HLOOKUP('General Information'!$C$6,'IDIOMA (hide)'!$A$1:$D$5016,A27,0) -> Valor por Parcela | C27: =IFERROR((C23*C13)/C26,0) -> 0
A28: 493 | B28: =HLOOKUP('General Information'!$C$6,'IDIOMA (hide)'!$A$1:$D$5016,A28,0) -> Proposta - LUT | D28: 425
A29: 85 | B29: =HLOOKUP('General Information'!$C$6,'IDIOMA (hide)'!$A$1:$D$5016,A29,0) -> Valor da LUT | D29: 426
A30: 418 | B30: =HLOOKUP('General Information'!$C$6,'IDIOMA (hide)'!$A$1:$D$5016,A30,0) -> Valor Total da Manutenção LUT (Mensal) | C30: =C29*C13 -> 0
A31: 494 | B31: =HLOOKUP('General Information'!$C$6,'IDIOMA (hide)'!$A$1:$D$5016,A31,0) -> Proposta - Serviços
A32: 88 | B32: =HLOOKUP('General Information'!$C$6,'IDIOMA (hide)'!$A$1:$D$5016,A32,0) -> Valor da Hora da Consultoria
A33: 89 | B33: =HLOOKUP('General Information'!$C$6,'IDIOMA (hide)'!$A$1:$D$5016,A33,0) -> Valor Hora de Gerenciamento De Projetos
A34: 490 | B34: =HLOOKUP('General Information'!$C$6,'IDIOMA (hide)'!$A$1:$D$5016,A34,0) -> Valor Hora RnD
A35: 495 | B35: =HLOOKUP('General Information'!$C$6,'IDIOMA (hide)'!$A$1:$D$5016,A35,0) -> Proposta - SaaS (Cloud)
A36: 497 | B36: =HLOOKUP('General Information'!$C$6,'IDIOMA (hide)'!$A$1:$D$5016,A36,0) -> Valor Base SaaS (Pacote 20 Usuários) | D36: 363
A37: 498 | B37: =HLOOKUP('General Information'!$C$6,'IDIOMA (hide)'!$A$1:$D$5016,A37,0) -> Valor das Licenças Adicionais (Por Licença)
A38: 499 | B38: =HLOOKUP('General Information'!$C$6,'IDIOMA (hide)'!$A$1:$D$5016,A38,0) -> Valor Mensal Total SaaS (Cloud) | C38: =IF(C13<101,(C36+((C13-20)*C37)),C37*C13) -> 0
A39: 507 | B39: =HLOOKUP('General Information'!$C$6,'IDIOMA (hide)'!$A$1:$D$5016,A39,0) -> Propostas Adicionais
A40: 508 | B40: =HLOOKUP('General Information'!$C$6,'IDIOMA (hide)'!$A$1:$D$5016,A40,0) -> TWS - Portal do Paciente
A41: 509 | B41: =HLOOKUP('General Information'!$C$6,'IDIOMA (hide)'!$A$1:$D$5016,A41,0) -> Incluir TWS nesta proposta?
A42: 510 | B42: =HLOOKUP('General Information'!$C$6,'IDIOMA (hide)'!$A$1:$D$5016,A42,0) -> Porte | D42: 354
A43: 511 | B43: =HLOOKUP('General Information'!$C$6,'IDIOMA (hide)'!$A$1:$D$5016,A43,0) -> Valor do TWS
A44: 357 | B44: =HLOOKUP('General Information'!$C$6,'IDIOMA (hide)'!$A$1:$D$5016,A44,0) -> Horas de Consultoria | C44: =IF(C41="Yes",80,0) -> 0
B45: Protocolo de Manchester
A46: 83 | B46: =HLOOKUP('General Information'!$C$6,'IDIOMA (hide)'!$A$1:$D$5016,A46,0) -> Número de Licenças
A47: 86 | B47: =HLOOKUP('General Information'!$C$6,'IDIOMA (hide)'!$A$1:$D$5016,A47,0) -> Valor CDU
A48: 357 | B48: =HLOOKUP('General Information'!$C$6,'IDIOMA (hide)'!$A$1:$D$5016,A48,0) -> Horas de Consultoria
A49: 87 | B49: =HLOOKUP('General Information'!$C$6,'IDIOMA (hide)'!$A$1:$D$5016,A49,0) -> Valor da Manutenção
A50: 273 | B50: =HLOOKUP('General Information'!$C$6,'IDIOMA (hide)'!$A$1:$D$5016,A50,0) -> Deslocamento
A51: 93 | B51: =HLOOKUP('General Information'!$C$6,'IDIOMA (hide)'!$A$1:$D$5016,A51,0) -> Forma de Deslocamento | D51: 202
A52: 512 | B52: =HLOOKUP('General Information'!$C$6,'IDIOMA (hide)'!$A$1:$D$5016,A52,0) -> Cidade de Origem
A53: 513 | B53: =HLOOKUP('General Information'!$C$6,'IDIOMA (hide)'!$A$1:$D$5016,A53,0) -> Cidade de Destino
A54: 95 | B54: =HLOOKUP('General Information'!$C$6,'IDIOMA (hide)'!$A$1:$D$5016,A54,0) -> Periodicidade
A56: 163 | B56: =HLOOKUP('General Information'!$C$6,'IDIOMA (hide)'!$A$1:$D$5016,A56,0) -> Informações Adicionais

Sheet OIT SaaS
A1: 2 | C1: =HLOOKUP('General Information'!$C$6,'IDIOMA (hide)'!$A$1:$D$5016,A1,0) -> LTEP - Levantamento Técnico de Estimativa de Projeto TASY EMR Código do documento: 0060 - Rev 024
A3: 198 | C3: =HLOOKUP('General Information'!$C$6,'IDIOMA (hide)'!$A$1:$D$5016,A3,0) -> SP - Solicitação de Proposta
A4: 160 | B4: =HLOOKUP('General Information'!$C$6,'IDIOMA (hide)'!$A$1:$D$5016,A4,0) -> Informações Gerais
A5: 357 | B5: =HLOOKUP('General Information'!$C$6,'IDIOMA (hide)'!$A$1:$D$5016,A5,0) -> Horas de Consultoria | C5: =GETPIVOTDATA("TOTAL HOURS (STANDARD HOURS + ADDITIONAL HOURS)",Summary!$B$13) -> 232 | D5: =HLOOKUP('General Information'!$C$6,'IDIOMA (hide)'!$A$1:$D$5016,A6,0) -> Qtd Consultores | E5: =Proposal!B38 -> Valor Mensal Total SaaS (Cloud) | H5: Month | I5: Hours | J5: Price | K5: Months
A6: 514 | D6: =Questions!D145 -> 1 | H6: 1 | I6: =IF(H6<>"",IF(H6<$K$6,($C$5/$K$6)*H6,IF(H6=$K$6,($C$5+0),IF(H6>$K$6,($C$5+0),""))),"") -> 160 | J6: =IF(H6<>"",IF(I6<$K$10,E$7*30%,IF(AND(I6>$K$8,I6<$K$12),$E$7*60%,IF(I6>=$K$12,$E$7*100%,""))),"") -> 0 | K6: =D7 -> 1.45 | L6: <- Qtd de meses considerando a qtd de consultores informados (1 trabalha 160)
D7: =C5/(160*D6) -> 1.45 | E7: =Proposal!C38 -> 0 | H7: 2 | I7: =IF(H7<>"",IF(H7<$K$6,($C$5/$K$6)*H7,IF(H7=$K$6,($C$5+0),IF(H7>$K$6,($C$5+0),""))),"") -> 232 | J7: =IF(H7<>"",IF(I7<$K$10,E$7*30%,IF(AND(I7>$K$8,I7<$K$12),$E$7*60%,IF(I7>=$K$12,$E$7*100%,""))),"") -> 0 | K7: Parametrization (30%)
H8: 3 | I8: =IF(H8<>"",IF(H8<$K$6,($C$5/$K$6)*H8,IF(H8=$K$6,($C$5+0),IF(H8>$K$6,($C$5+0),""))),"") -> 232 | J8: =IF(H8<>"",IF(I8<$K$10,E$7*30%,IF(AND(I8>$K$8,I8<$K$12),$E$7*60%,IF(I8>=$K$12,$E$7*100%,""))),"") -> 0 | K8: =C5*30% -> 69.6 | L8: <- Quantidade de horas correspondente a 30% do total da implantação
H9: 4 | I9: =IF(H9<>"",IF(H9<$K$6,($C$5/$K$6)*H9,IF(H9=$K$6,($C$5+0),IF(H9>$K$6,($C$5+0),""))),"") -> 232 | J9: =IF(H9<>"",IF(I9<$K$10,E$7*30%,IF(AND(I9>$K$8,I9<$K$12),$E$7*60%,IF(I9>=$K$12,$E$7*100%,""))),"") -> 0 | K9: Pilot Test (60%)
H10: 5 | I10: =IF(H10<>"",IF(H10<$K$6,($C$5/$K$6)*H10,IF(H10=$K$6,($C$5+0),IF(H10>$K$6,($C$5+0),""))),"") -> 232 | J10: =IF(H10<>"",IF(I10<$K$10,E$7*30%,IF(AND(I10>$K$8,I10<$K$12),$E$7*60%,IF(I10>=$K$12,$E$7*100%,""))),"") -> 0 | K10: =C5*60% -> 139.2 | L10: <- Quantidade de horas correspondente a 60% do total da implantação
D11: =H66 -> Total | E11: =J66 -> 0 | H11: 6 | I11: =IF(H11<>"",IF(H11<$K$6,($C$5/$K$6)*H11,IF(H11=$K$6,($C$5+0),IF(H11>$K$6,($C$5+0),""))),"") -> 232 | J11: =IF(H11<>"",IF(I11<$K$10,E$7*30%,IF(AND(I11>$K$8,I11<$K$12),$E$7*60%,IF(I11>=$K$12,$E$7*100%,""))),"") -> 0 | K11: Go-Live (100%)
H12: 7 | I12: =IF(H12<>"",IF(H12<$K$6,($C$5/$K$6)*H12,IF(H12=$K$6,($C$5+0),IF(H12>$K$6,($C$5+0),""))),"") -> 232 | J12: =IF(H12<>"",IF(I12<$K$10,E$7*30%,IF(AND(I12>$K$8,I12<$K$12),$E$7*60%,IF(I12>=$K$12,$E$7*100%,""))),"") -> 0 | K12: =C5*100% -> 232 | L12: <- Quantidade de horas correspondente a 100% do total da implantação
H13: 8 | I13: =IF(H13<>"",IF(H13<$K$6,($C$5/$K$6)*H13,IF(H13=$K$6,($C$5+0),IF(H13>$K$6,($C$5+0),""))),"") -> 232 | J13: =IF(H13<>"",IF(I13<$K$10,E$7*30%,IF(AND(I13>$K$8,I13<$K$12),$E$7*60%,IF(I13>=$K$12,$E$7*100%,""))),"") -> 0
H14: 9 | I14: =IF(H14<>"",IF(H14<$K$6,($C$5/$K$6)*H14,IF(H14=$K$6,($C$5+0),IF(H14>$K$6,($C$5+0),""))),"") -> 232 | J14: =IF(H14<>"",IF(I14<$K$10,E$7*30%,IF(AND(I14>$K$8,I14<$K$12),$E$7*60%,IF(I14>=$K$12,$E$7*100%,""))),"") -> 0 | K14: OIT
H15: 10 | I15: =IF(H15<>"",IF(H15<$K$6,($C$5/$K$6)*H15,IF(H15=$K$6,($C$5+0),IF(H15>$K$6,($C$5+0),""))),"") -> 232 | J15: =IF(H15<>"",IF(I15<$K$10,E$7*30%,IF(AND(I15>$K$8,I15<$K$12),$E$7*60%,IF(I15>=$K$12,$E$7*100%,""))),"") -> 0 | K15: =SUM(J6:J65) -> 0
H16: 11 | I16: =IF(H16<>"",IF(H16<$K$6,($C$5/$K$6)*H16,IF(H16=$K$6,($C$5+0),IF(H16>$K$6,($C$5+0),""))),"") -> 232 | J16: =IF(H16<>"",IF(I16<$K$10,E$7*30%,IF(AND(I16>$K$8,I16<$K$12),$E$7*60%,IF(I16>=$K$12,$E$7*100%,""))),"") -> 0
H17: 12 | I17: =IF(H17<>"",IF(H17<$K$6,($C$5/$K$6)*H17,IF(H17=$K$6,($C$5+0),IF(H17>$K$6,($C$5+0),""))),"") -> 232 | J17: =IF(H17<>"",IF(I17<$K$10,E$7*30%,IF(AND(I17>$K$8,I17<$K$12),$E$7*60%,IF(I17>=$K$12,$E$7*100%,""))),"") -> 0
H18: =IF(Proposal!$C$19>12,'OIT SaaS'!H17+1,"") | I18: =IF(H18<>"",IF(H18<$K$6,($C$5/$K$6)*H18,IF(H18=$K$6,($C$5+0),IF(H18>$K$6,($C$5+0),""))),"") | J18: =IF(H18<>"",IF(I18<$K$10,E$7*30%,IF(AND(I18>$K$8,I18<$K$12),$E$7*60%,IF(I18>=$K$12,$E$7*100%,""))),"")
H19: =IF(Proposal!$C$19>12,'OIT SaaS'!H18+1,"") | I19: =IF(H19<>"",IF(H19<$K$6,($C$5/$K$6)*H19,IF(H19=$K$6,($C$5+0),IF(H19>$K$6,($C$5+0),""))),"") | J19: =IF(H19<>"",IF(I19<$K$10,E$7*30%,IF(AND(I19>$K$8,I19<$K$12),$E$7*60%,IF(I19>=$K$12,$E$7*100%,""))),"")
H20: =IF(Proposal!$C$19>12,'OIT SaaS'!H19+1,"") | I20: =IF(H20<>"",IF(H20<$K$6,($C$5/$K$6)*H20,IF(H20=$K$6,($C$5+0),IF(H20>$K$6,($C$5+0),""))),"") | J20: =IF(H20<>"",IF(I20<$K$10,E$7*30%,IF(AND(I20>$K$8,I20<$K$12),$E$7*60%,IF(I20>=$K$12,$E$7*100%,""))),"")
H21: =IF(Proposal!$C$19>12,'OIT SaaS'!H20+1,"") | I21: =IF(H21<>"",IF(H21<$K$6,($C$5/$K$6)*H21,IF(H21=$K$6,($C$5+0),IF(H21>$K$6,($C$5+0),""))),"") | J21: =IF(H21<>"",IF(I21<$K$10,E$7*30%,IF(AND(I21>$K$8,I21<$K$12),$E$7*60%,IF(I21>=$K$12,$E$7*100%,""))),"")
H22: =IF(Proposal!$C$19>12,'OIT SaaS'!H21+1,"") | I22: =IF(H22<>"",IF(H22<$K$6,($C$5/$K$6)*H22,IF(H22=$K$6,($C$5+0),IF(H22>$K$6,($C$5+0),""))),"") | J22: =IF(H22<>"",IF(I22<$K$10,E$7*30%,IF(AND(I22>$K$8,I22<$K$12),$E$7*60%,IF(I22>=$K$12,$E$7*100%,""))),"")
H23: =IF(Proposal!$C$19>12,'OIT SaaS'!H22+1,"") | I23: =IF(H23<>"",IF(H23<$K$6,($C$5/$K$6)*H23,IF(H23=$K$6,($C$5+0),IF(H23>$K$6,($C$5+0),""))),"") | J23: =IF(H23<>"",IF(I23<$K$10,E$7*30%,IF(AND(I23>$K$8,I23<$K$12),$E$7*60%,IF(I23>=$K$12,$E$7*100%,""))),"")
H24: =IF(Proposal!$C$19>12,'OIT SaaS'!H23+1,"") | I24: =IF(H24<>"",IF(H24<$K$6,($C$5/$K$6)*H24,IF(H24=$K$6,($C$5+0),IF(H24>$K$6,($C$5+0),""))),"") | J24: =IF(H24<>"",IF(I24<$K$10,E$7*30%,IF(AND(I24>$K$8,I24<$K$12),$E$7*60%,IF(I24>=$K$12,$E$7*100%,""))),"")
H25: =IF(Proposal!$C$19>12,'OIT SaaS'!H24+1,"") | I25: =IF(H25<>"",IF(H25<$K$6,($C$5/$K$6)*H25,IF(H25=$K$6,($C$5+0),IF(H25>$K$6,($C$5+0),""))),"") | J25: =IF(H25<>"",IF(I25<$K$10,E$7*30%,IF(AND(I25>$K$8,I25<$K$12),$E$7*60%,IF(I25>=$K$12,$E$7*100%,""))),"")
H26: =IF(Proposal!$C$19>12,'OIT SaaS'!H25+1,"") | I26: =IF(H26<>"",IF(H26<$K$6,($C$5/$K$6)*H26,IF(H26=$K$6,($C$5+0),IF(H26>$K$6,($C$5+0),""))),"") | J26: =IF(H26<>"",IF(I26<$K$10,E$7*30%,IF(AND(I26>$K$8,I26<$K$12),$E$7*60%,IF(I26>=$K$12,$E$7*100%,""))),"")
H27: =IF(Proposal!$C$19>12,'OIT SaaS'!H26+1,"") | I27: =IF(H27<>"",IF(H27<$K$6,($C$5/$K$6)*H27,IF(H27=$K$6,($C$5+0),IF(H27>$K$6,($C$5+0),""))),"") | J27: =IF(H27<>"",IF(I27<$K$10,E$7*30%,IF(AND(I27>$K$8,I27<$K$12),$E$7*60%,IF(I27>=$K$12,$E$7*100%,""))),"")
H28: =IF(Proposal!$C$19>12,'OIT SaaS'!H27+1,"") | I28: =IF(H28<>"",IF(H28<$K$6,($C$5/$K$6)*H28,IF(H28=$K$6,($C$5+0),IF(H28>$K$6,($C$5+0),""))),"") | J28: =IF(H28<>"",IF(I28<$K$10,E$7*30%,IF(AND(I28>$K$8,I28<$K$12),$E$7*60%,IF(I28>=$K$12,$E$7*100%,""))),"")
H29: =IF(Proposal!$C$19>12,'OIT SaaS'!H28+1,"") | I29: =IF(H29<>"",IF(H29<$K$6,($C$5/$K$6)*H29,IF(H29=$K$6,($C$5+0),IF(H29>$K$6,($C$5+0),""))),"") | J29: =IF(H29<>"",IF(I29<$K$10,E$7*30%,IF(AND(I29>$K$8,I29<$K$12),$E$7*60%,IF(I29>=$K$12,$E$7*100%,""))),"")
H30: =IF(Proposal!$C$19>24,'OIT SaaS'!H29+1,"") | I30: =IF(H30<>"",IF(H30<$K$6,($C$5/$K$6)*H30,IF(H30=$K$6,($C$5+0),IF(H30>$K$6,($C$5+0),""))),"") | J30: =IF(H30<>"",IF(I30<$K$10,E$7*30%,IF(AND(I30>$K$8,I30<$K$12),$E$7*60%,IF(I30>=$K$12,$E$7*100%,""))),"")
H31: =IF(Proposal!$C$19>24,'OIT SaaS'!H30+1,"") | I31: =IF(H31<>"",IF(H31<$K$6,($C$5/$K$6)*H31,IF(H31=$K$6,($C$5+0),IF(H31>$K$6,($C$5+0),""))),"") | J31: =IF(H31<>"",IF(I31<$K$10,E$7*30%,IF(AND(I31>$K$8,I31<$K$12),$E$7*60%,IF(I31>=$K$12,$E$7*100%,""))),"")
H32: =IF(Proposal!$C$19>24,'OIT SaaS'!H31+1,"") | I32: =IF(H32<>"",IF(H32<$K$6,($C$5/$K$6)*H32,IF(H32=$K$6,($C$5+0),IF(H32>$K$6,($C$5+0),""))),"") | J32: =IF(H32<>"",IF(I32<$K$10,E$7*30%,IF(AND(I32>$K$8,I32<$K$12),$E$7*60%,IF(I32>=$K$12,$E$7*100%,""))),"")
H33: =IF(Proposal!$C$19>24,'OIT SaaS'!H32+1,"") | I33: =IF(H33<>"",IF(H33<$K$6,($C$5/$K$6)*H33,IF(H33=$K$6,($C$5+0),IF(H33>$K$6,($C$5+0),""))),"") | J33: =IF(H33<>"",IF(I33<$K$10,E$7*30%,IF(AND(I33>$K$8,I33<$K$12),$E$7*60%,IF(I33>=$K$12,$E$7*100%,""))),"")
H34: =IF(Proposal!$C$19>24,'OIT SaaS'!H33+1,"") | I34: =IF(H34<>"",IF(H34<$K$6,($C$5/$K$6)*H34,IF(H34=$K$6,($C$5+0),IF(H34>$K$6,($C$5+0),""))),"") | J34: =IF(H34<>"",IF(I34<$K$10,E$7*30%,IF(AND(I34>$K$8,I34<$K$12),$E$7*60%,IF(I34>=$K$12,$E$7*100%,""))),"")
H35: =IF(Proposal!$C$19>24,'OIT SaaS'!H34+1,"") | I35: =IF(H35<>"",IF(H35<$K$6,($C$5/$K$6)*H35,IF(H35=$K$6,($C$5+0),IF(H35>$K$6,($C$5+0),""))),"") | J35: =IF(H35<>"",IF(I35<$K$10,E$7*30%,IF(AND(I35>$K$8,I35<$K$12),$E$7*60%,IF(I35>=$K$12,$E$7*100%,""))),"")
H36: =IF(Proposal!$C$19>24,'OIT SaaS'!H35+1,"") | I36: =IF(H36<>"",IF(H36<$K$6,($C$5/$K$6)*H36,IF(H36=$K$6,($C$5+0),IF(H36>$K$6,($C$5+0),""))),"") | J36: =IF(H36<>"",IF(I36<$K$10,E$7*30%,IF(AND(I36>$K$8,I36<$K$12),$E$7*60%,IF(I36>=$K$12,$E$7*100%,""))),"")
H37: =IF(Proposal!$C$19>24,'OIT SaaS'!H36+1,"") | I37: =IF(H37<>"",IF(H37<$K$6,($C$5/$K$6)*H37,IF(H37=$K$6,($C$5+0),IF(H37>$K$6,($C$5+0),""))),"") | J37: =IF(H37<>"",IF(I37<$K$10,E$7*30%,IF(AND(I37>$K$8,I37<$K$12),$E$7*60%,IF(I37>=$K$12,$E$7*100%,""))),"")
H38: =IF(Proposal!$C$19>24,'OIT SaaS'!H37+1,"") | I38: =IF(H38<>"",IF(H38<$K$6,($C$5/$K$6)*H38,IF(H38=$K$6,($C$5+0),IF(H38>$K$6,($C$5+0),""))),"") | J38: =IF(H38<>"",IF(I38<$K$10,E$7*30%,IF(AND(I38>$K$8,I38<$K$12),$E$7*60%,IF(I38>=$K$12,$E$7*100%,""))),"")
H39: =IF(Proposal!$C$19>24,'OIT SaaS'!H38+1,"") | I39: =IF(H39<>"",IF(H39<$K$6,($C$5/$K$6)*H39,IF(H39=$K$6,($C$5+0),IF(H39>$K$6,($C$5+0),""))),"") | J39: =IF(H39<>"",IF(I39<$K$10,E$7*30%,IF(AND(I39>$K$8,I39<$K$12),$E$7*60%,IF(I39>=$K$12,$E$7*100%,""))),"")
H40: =IF(Proposal!$C$19>24,'OIT SaaS'!H39+1,"") | I40: =IF(H40<>"",IF(H40<$K$6,($C$5/$K$6)*H40,IF(H40=$K$6,($C$5+0),IF(H40>$K$6,($C$5+0),""))),"") | J40: =IF(H40<>"",IF(I40<$K$10,E$7*30%,IF(AND(I40>$K$8,I40<$K$12),$E$7*60%,IF(I40>=$K$12,$E$7*100%,""))),"")
H41: =IF(Proposal!$C$19>24,'OIT SaaS'!H40+1,"") | I41: =IF(H41<>"",IF(H41<$K$6,($C$5/$K$6)*H41,IF(H41=$K$6,($C$5+0),IF(H41>$K$6,($C$5+0),""))),"") | J41: =IF(H41<>"",IF(I41<$K$10,E$7*30%,IF(AND(I41>$K$8,I41<$K$12),$E$7*60%,IF(I41>=$K$12,$E$7*100%,""))),"")
H42: =IF(Proposal!$C$19>36,'OIT SaaS'!H41+1,"") | I42: =IF(H42<>"",IF(H42<$K$6,($C$5/$K$6)*H42,IF(H42=$K$6,($C$5+0),IF(H42>$K$6,($C$5+0),""))),"") | J42: =IF(H42<>"",IF(I42<$K$10,E$7*30%,IF(AND(I42>$K$8,I42<$K$12),$E$7*60%,IF(I42>=$K$12,$E$7*100%,""))),"")
H43: =IF(Proposal!$C$19>36,'OIT SaaS'!H42+1,"") | I43: =IF(H43<>"",IF(H43<$K$6,($C$5/$K$6)*H43,IF(H43=$K$6,($C$5+0),IF(H43>$K$6,($C$5+0),""))),"") | J43: =IF(H43<>"",IF(I43<$K$10,E$7*30%,IF(AND(I43>$K$8,I43<$K$12),$E$7*60%,IF(I43>=$K$12,$E$7*100%,""))),"")
H44: =IF(Proposal!$C$19>36,'OIT SaaS'!H43+1,"") | I44: =IF(H44<>"",IF(H44<$K$6,($C$5/$K$6)*H44,IF(H44=$K$6,($C$5+0),IF(H44>$K$6,($C$5+0),""))),"") | J44: =IF(H44<>"",IF(I44<$K$10,E$7*30%,IF(AND(I44>$K$8,I44<$K$12),$E$7*60%,IF(I44>=$K$12,$E$7*100%,""))),"")
H45: =IF(Proposal!$C$19>36,'OIT SaaS'!H44+1,"") | I45: =IF(H45<>"",IF(H45<$K$6,($C$5/$K$6)*H45,IF(H45=$K$6,($C$5+0),IF(H45>$K$6,($C$5+0),""))),"") | J45: =IF(H45<>"",IF(I45<$K$10,E$7*30%,IF(AND(I45>$K$8,I45<$K$12),$E$7*60%,IF(I45>=$K$12,$E$7*100%,""))),"")
H46: =IF(Proposal!$C$19>36,'OIT SaaS'!H45+1,"") | I46: =IF(H46<>"",IF(H46<$K$6,($C$5/$K$6)*H46,IF(H46=$K$6,($C$5+0),IF(H46>$K$6,($C$5+0),""))),"") | J46: =IF(H46<>"",IF(I46<$K$10,E$7*30%,IF(AND(I46>$K$8,I46<$K$12),$E$7*60%,IF(I46>=$K$12,$E$7*100%,""))),"")
H47: =IF(Proposal!$C$19>36,'OIT SaaS'!H46+1,"") | I47: =IF(H47<>"",IF(H47<$K$6,($C$5/$K$6)*H47,IF(H47=$K$6,($C$5+0),IF(H47>$K$6,($C$5+0),""))),"") | J47: =IF(H47<>"",IF(I47<$K$10,E$7*30%,IF(AND(I47>$K$8,I47<$K$12),$E$7*60%,IF(I47>=$K$12,$E$7*100%,""))),"")
H48: =IF(Proposal!$C$19>36,'OIT SaaS'!H47+1,"") | I48: =IF(H48<>"",IF(H48<$K$6,($C$5/$K$6)*H48,IF(H48=$K$6,($C$5+0),IF(H48>$K$6,($C$5+0),""))),"") | J48: =IF(H48<>"",IF(I48<$K$10,E$7*30%,IF(AND(I48>$K$8,I48<$K$12),$E$7*60%,IF(I48>=$K$12,$E$7*100%,""))),"")
H49: =IF(Proposal!$C$19>36,'OIT SaaS'!H48+1,"") | I49: =IF(H49<>"",IF(H49<$K$6,($C$5/$K$6)*H49,IF(H49=$K$6,($C$5+0),IF(H49>$K$6,($C$5+0),""))),"") | J49: =IF(H49<>"",IF(I49<$K$10,E$7*30%,IF(AND(I49>$K$8,I49<$K$12),$E$7*60%,IF(I49>=$K$12,$E$7*100%,""))),"")
H50: =IF(Proposal!$C$19>36,'OIT SaaS'!H49+1,"") | I50: =IF(H50<>"",IF(H50<$K$6,($C$5/$K$6)*H50,IF(H50=$K$6,($C$5+0),IF(H50>$K$6,($C$5+0),""))),"") | J50: =IF(H50<>"",IF(I50<$K$10,E$7*30%,IF(AND(I50>$K$8,I50<$K$12),$E$7*60%,IF(I50>=$K$12,$E$7*100%,""))),"")
H51: =IF(Proposal!$C$19>36,'OIT SaaS'!H50+1,"") | I51: =IF(H51<>"",IF(H51<$K$6,($C$5/$K$6)*H51,IF(H51=$K$6,($C$5+0),IF(H51>$K$6,($C$5+0),""))),"") | J51: =IF(H51<>"",IF(I51<$K$10,E$7*30%,IF(AND(I51>$K$8,I51<$K$12),$E$7*60%,IF(I51>=$K$12,$E$7*100%,""))),"")
H52: =IF(Proposal!$C$19>36,'OIT SaaS'!H51+1,"") | I52: =IF(H52<>"",IF(H52<$K$6,($C$5/$K$6)*H52,IF(H52=$K$6,($C$5+0),IF(H52>$K$6,($C$5+0),""))),"") | J52: =IF(H52<>"",IF(I52<$K$10,E$7*30%,IF(AND(I52>$K$8,I52<$K$12),$E$7*60%,IF(I52>=$K$12,$E$7*100%,""))),"")
H53: =IF(Proposal!$C$19>36,'OIT SaaS'!H52+1,"") | I53: =IF(H53<>"",IF(H53<$K$6,($C$5/$K$6)*H53,IF(H53=$K$6,($C$5+0),IF(H53>$K$6,($C$5+0),""))),"") | J53: =IF(H53<>"",IF(I53<$K$10,E$7*30%,IF(AND(I53>$K$8,I53<$K$12),$E$7*60%,IF(I53>=$K$12,$E$7*100%,""))),"")
H54: =IF(Proposal!$C$19>48,'OIT SaaS'!H53+1,"") | I54: =IF(H54<>"",IF(H54<$K$6,($C$5/$K$6)*H54,IF(H54=$K$6,($C$5+0),IF(H54>$K$6,($C$5+0),""))),"") | J54: =IF(H54<>"",IF(I54<$K$10,E$7*30%,IF(AND(I54>$K$8,I54<$K$12),$E$7*60%,IF(I54>=$K$12,$E$7*100%,""))),"")
H55: =IF(Proposal!$C$19>48,'OIT SaaS'!H54+1,"") | I55: =IF(H55<>"",IF(H55<$K$6,($C$5/$K$6)*H55,IF(H55=$K$6,($C$5+0),IF(H55>$K$6,($C$5+0),""))),"") | J55: =IF(H55<>"",IF(I55<$K$10,E$7*30%,IF(AND(I55>$K$8,I55<$K$12),$E$7*60%,IF(I55>=$K$12,$E$7*100%,""))),"")
H56: =IF(Proposal!$C$19>48,'OIT SaaS'!H55+1,"") | I56: =IF(H56<>"",IF(H56<$K$6,($C$5/$K$6)*H56,IF(H56=$K$6,($C$5+0),IF(H56>$K$6,($C$5+0),""))),"") | J56: =IF(H56<>"",IF(I56<$K$10,E$7*30%,IF(AND(I56>$K$8,I56<$K$12),$E$7*60%,IF(I56>=$K$12,$E$7*100%,""))),"")
H57: =IF(Proposal!$C$19>48,'OIT SaaS'!H56+1,"") | I57: =IF(H57<>"",IF(H57<$K$6,($C$5/$K$6)*H57,IF(H57=$K$6,($C$5+0),IF(H57>$K$6,($C$5+0),""))),"") | J57: =IF(H57<>"",IF(I57<$K$10,E$7*30%,IF(AND(I57>$K$8,I57<$K$12),$E$7*60%,IF(I57>=$K$12,$E$7*100%,""))),"")
H58: =IF(Proposal!$C$19>48,'OIT SaaS'!H57+1,"") | I58: =IF(H58<>"",IF(H58<$K$6,($C$5/$K$6)*H58,IF(H58=$K$6,($C$5+0),IF(H58>$K$6,($C$5+0),""))),"") | J58: =IF(H58<>"",IF(I58<$K$10,E$7*30%,IF(AND(I58>$K$8,I58<$K$12),$E$7*60%,IF(I58>=$K$12,$E$7*100%,""))),"")
H59: =IF(Proposal!$C$19>48,'OIT SaaS'!H58+1,"") | I59: =IF(H59<>"",IF(H59<$K$6,($C$5/$K$6)*H59,IF(H59=$K$6,($C$5+0),IF(H59>$K$6,($C$5+0),""))),"") | J59: =IF(H59<>"",IF(I59<$K$10,E$7*30%,IF(AND(I59>$K$8,I59<$K$12),$E$7*60%,IF(I59>=$K$12,$E$7*100%,""))),"")
H60: =IF(Proposal!$C$19>48,'OIT SaaS'!H59+1,"") | I60: =IF(H60<>"",IF(H60<$K$6,($C$5/$K$6)*H60,IF(H60=$K$6,($C$5+0),IF(H60>$K$6,($C$5+0),""))),"") | J60: =IF(H60<>"",IF(I60<$K$10,E$7*30%,IF(AND(I60>$K$8,I60<$K$12),$E$7*60%,IF(I60>=$K$12,$E$7*100%,""))),"")
H61: =IF(Proposal!$C$19>48,'OIT SaaS'!H60+1,"") | I61: =IF(H61<>"",IF(H61<$K$6,($C$5/$K$6)*H61,IF(H61=$K$6,($C$5+0),IF(H61>$K$6,($C$5+0),""))),"") | J61: =IF(H61<>"",IF(I61<$K$10,E$7*30%,IF(AND(I61>$K$8,I61<$K$12),$E$7*60%,IF(I61>=$K$12,$E$7*100%,""))),"")
H62: =IF(Proposal!$C$19>48,'OIT SaaS'!H61+1,"") | I62: =IF(H62<>"",IF(H62<$K$6,($C$5/$K$6)*H62,IF(H62=$K$6,($C$5+0),IF(H62>$K$6,($C$5+0),""))),"") | J62: =IF(H62<>"",IF(I62<$K$10,E$7*30%,IF(AND(I62>$K$8,I62<$K$12),$E$7*60%,IF(I62>=$K$12,$E$7*100%,""))),"")
H63: =IF(Proposal!$C$19>48,'OIT SaaS'!H62+1,"") | I63: =IF(H63<>"",IF(H63<$K$6,($C$5/$K$6)*H63,IF(H63=$K$6,($C$5+0),IF(H63>$K$6,($C$5+0),""))),"") | J63: =IF(H63<>"",IF(I63<$K$10,E$7*30%,IF(AND(I63>$K$8,I63<$K$12),$E$7*60%,IF(I63>=$K$12,$E$7*100%,""))),"")
H64: =IF(Proposal!$C$19>48,'OIT SaaS'!H63+1,"") | I64: =IF(H64<>"",IF(H64<$K$6,($C$5/$K$6)*H64,IF(H64=$K$6,($C$5+0),IF(H64>$K$6,($C$5+0),""))),"") | J64: =IF(H64<>"",IF(I64<$K$10,E$7*30%,IF(AND(I64>$K$8,I64<$K$12),$E$7*60%,IF(I64>=$K$12,$E$7*100%,""))),"")
H65: =IF(Proposal!$C$19>48,'OIT SaaS'!H64+1,"") | I65: =IF(H65<>"",IF(H65<$K$6,($C$5/$K$6)*H65,IF(H65=$K$6,($C$5+0),IF(H65>$K$6,($C$5+0),""))),"") | J65: =IF(H65<>"",IF(I65<$K$10,E$7*30%,IF(AND(I65>$K$8,I65<$K$12),$E$7*60%,IF(I65>=$K$12,$E$7*100%,""))),"")
H66: Total | J66: =SUM(J6:J65) -> 0

Sheet Modules
A1: 2 | C1: =HLOOKUP('General Information'!$C$6,'IDIOMA (hide)'!$A$1:$D$5016,A1,0) -> LTEP - Levantamento Técnico de Estimativa de Projeto TASY EMR Código do documento: 0060 - Rev 024
A3: 41 | B3: =HLOOKUP('General Information'!$C$6,'IDIOMA (hide)'!$A$1:$D$5016,A3,0) -> Informações Módulos de Interesse | C3: =HLOOKUP($F$4,'IDIOMA (hide)'!$A$1:$D$5016,B3,0) -> #N/A | D3: =HLOOKUP($F$4,'IDIOMA (hide)'!$A$1:$D$5016,C3,0) -> #N/A | E3: =HLOOKUP($F$4,'IDIOMA (hide)'!$A$1:$D$5016,D3,0) -> #N/A | F3: =HLOOKUP($F$4,'IDIOMA (hide)'!$A$1:$D$5016,E3,0) -> #N/A | G3: =HLOOKUP($F$4,'IDIOMA (hide)'!$A$1:$D$5016,F3,0) -> #N/A
B4: 42 | C4: 43 | D4: 44
B5: =HLOOKUP('General Information'!$C$6,'IDIOMA (hide)'!$A$1:$D$5016,B4,0) -> ID Módulo | C5: =HLOOKUP('General Information'!$C$6,'IDIOMA (hide)'!$A$1:$D$5016,C4,0) -> Módulo | D5: =HLOOKUP('General Information'!$C$6,'IDIOMA (hide)'!$A$1:$D$5016,D4,0) -> Interesse? | E5: Ocultar | F5: Área | K5: Módulo | L5: Interesse? | M5: Área
B6: 3 | C6: =IF('General Information'!$C$6="Português",VLOOKUP(Modules!B6,'ESTRUTURA_MODULO(hide)'!A:D,2,0),IF('General Information'!$C$6="English",VLOOKUP(Modules!B6,'ESTRUTURA_MODULO(hide)'!A:D,3,0),IF('General Information'!$C$6="Español",VLOOKUP(Modules!B6,'ESTRUTURA_MODULO(hide)'!A:D,4,0)))) -> Cadastros e Funções Gerais | D6: Yes | E6: =IF(OR(D6='Listas (Hide)'!$B$17,D6='Listas (Hide)'!$C$17,D6='Listas (Hide)'!$D$17)=TRUE,1,IF(OR(D6='Listas (Hide)'!$B$18,D6='Listas (Hide)'!$C$18,D6='Listas (Hide)'!$D$18)=TRUE,2,"")) -> 1 | F6: =HLOOKUP('General Information'!$C$6,'IDIOMA (hide)'!$A$1:$D$5016,G8,0) -> Core do sistema | K6: Cadastros e Funções Gerais | L6: =D6 -> Yes | M6: Core do sistema
B7: 36 | C7: =IF('General Information'!$C$6="Português",VLOOKUP(Modules!B7,'ESTRUTURA_MODULO(hide)'!A:D,2,0),IF('General Information'!$C$6="English",VLOOKUP(Modules!B7,'ESTRUTURA_MODULO(hide)'!A:D,3,0),IF('General Information'!$C$6="Español",VLOOKUP(Modules!B7,'ESTRUTURA_MODULO(hide)'!A:D,4,0)))) -> Gerenciador do Sistema | D7: Yes | E7: =IF(OR(D7='Listas (Hide)'!$B$17,D7='Listas (Hide)'!$C$17,D7='Listas (Hide)'!$D$17)=TRUE,1,IF(OR(D7='Listas (Hide)'!$B$18,D7='Listas (Hide)'!$C$18,D7='Listas (Hide)'!$D$18)=TRUE,2,"")) -> 1 | K7: Gerenciador do Sistema | L7: =D7 -> Yes | M7: Core do sistema
B8: 631 | C8: =IF('General Information'!$C$6="Português",VLOOKUP(Modules!B8,'ESTRUTURA_MODULO(hide)'!A:D,2,0),IF('General Information'!$C$6="English",VLOOKUP(Modules!B8,'ESTRUTURA_MODULO(hide)'!A:D,3,0),IF('General Information'!$C$6="Español",VLOOKUP(Modules!B8,'ESTRUTURA_MODULO(hide)'!A:D,4,0)))) -> Relatórios | D8: Yes | E8: =IF(OR(D8='Listas (Hide)'!$B$17,D8='Listas (Hide)'!$C$17,D8='Listas (Hide)'!$D$17)=TRUE,1,IF(OR(D8='Listas (Hide)'!$B$18,D8='Listas (Hide)'!$C$18,D8='Listas (Hide)'!$D$18)=TRUE,2,"")) -> 1 | G8: 203 | K8: Relatórios | L8: =D8 -> Yes | M8: Core do sistema
B9: 5 | C9: =IF('General Information'!$C$6="Português",VLOOKUP(Modules!B9,'ESTRUTURA_MODULO(hide)'!A:D,2,0),IF('General Information'!$C$6="English",VLOOKUP(Modules!B9,'ESTRUTURA_MODULO(hide)'!A:D,3,0),IF('General Information'!$C$6="Español",VLOOKUP(Modules!B9,'ESTRUTURA_MODULO(hide)'!A:D,4,0)))) -> Recepção e Internação | D9: =IF('General Information'!$C$18="OPS (Operadora de Saúde)","No","Yes") -> Yes | E9: =IF(OR(D9='Listas (Hide)'!$B$17,D9='Listas (Hide)'!$C$17,D9='Listas (Hide)'!$D$17)=TRUE,1,IF(OR(D9='Listas (Hide)'!$B$18,D9='Listas (Hide)'!$C$18,D9='Listas (Hide)'!$D$18)=TRUE,2,"")) -> 1 | K9: Recepção e Internação | L9: =D9 -> Yes | M9: Core do sistema
B10: 16 | C10: =IF('General Information'!$C$6="Português",VLOOKUP(Modules!B10,'ESTRUTURA_MODULO(hide)'!A:D,2,0),IF('General Information'!$C$6="English",VLOOKUP(Modules!B10,'ESTRUTURA_MODULO(hide)'!A:D,3,0),IF('General Information'!$C$6="Español",VLOOKUP(Modules!B10,'ESTRUTURA_MODULO(hide)'!A:D,4,0)))) -> Administração de Contratos (Preços) | D10: =IF('General Information'!$C$18="OPS (Operadora de Saúde)","No","Yes") -> Yes | E10: =IF(OR(D10='Listas (Hide)'!$B$17,D10='Listas (Hide)'!$C$17,D10='Listas (Hide)'!$D$17)=TRUE,1,IF(OR(D10='Listas (Hide)'!$B$18,D10='Listas (Hide)'!$C$18,D10='Listas (Hide)'!$D$18)=TRUE,2,"")) -> 1 | K10: Administração de Contratos (Preços) | L10: =D10 -> Yes | M10: Core do sistema
B11: 6 | C11: =IF('General Information'!$C$6="Português",VLOOKUP(Modules!B11,'ESTRUTURA_MODULO(hide)'!A:D,2,0),IF('General Information'!$C$6="English",VLOOKUP(Modules!B11,'ESTRUTURA_MODULO(hide)'!A:D,3,0),IF('General Information'!$C$6="Español",VLOOKUP(Modules!B11,'ESTRUTURA_MODULO(hide)'!A:D,4,0)))) -> Faturamento (Convênios e Particular) | D11: =IF('General Information'!$C$18="OPS (Operadora de Saúde)","No","Yes") -> Yes | E11: =IF(OR(D11='Listas (Hide)'!$B$17,D11='Listas (Hide)'!$C$17,D11='Listas (Hide)'!$D$17)=TRUE,1,IF(OR(D11='Listas (Hide)'!$B$18,D11='Listas (Hide)'!$C$18,D11='Listas (Hide)'!$D$18)=TRUE,2,"")) -> 1 | K11: Faturamento (Convênios e Particular) | L11: =D11 -> Yes | M11: Core do sistema
B12: 99 | C12: =IF('General Information'!$C$6="Português",VLOOKUP(Modules!B12,'ESTRUTURA_MODULO(hide)'!A:D,2,0),IF('General Information'!$C$6="English",VLOOKUP(Modules!B12,'ESTRUTURA_MODULO(hide)'!A:D,3,0),IF('General Information'!$C$6="Español",VLOOKUP(Modules!B12,'ESTRUTURA_MODULO(hide)'!A:D,4,0)))) -> Almoxarifado | D12: Yes | E12: =IF(OR(D12='Listas (Hide)'!$B$17,D12='Listas (Hide)'!$C$17,D12='Listas (Hide)'!$D$17)=TRUE,1,IF(OR(D12='Listas (Hide)'!$B$18,D12='Listas (Hide)'!$C$18,D12='Listas (Hide)'!$D$18)=TRUE,2,"")) -> 1 | K12: Almoxarifado | L12: =D12 -> Yes | M12: Core do sistema
B13: 4 | C13: =IF('General Information'!$C$6="Português",VLOOKUP(Modules!B13,'ESTRUTURA_MODULO(hide)'!A:D,2,0),IF('General Information'!$C$6="English",VLOOKUP(Modules!B13,'ESTRUTURA_MODULO(hide)'!A:D,3,0),IF('General Information'!$C$6="Español",VLOOKUP(Modules!B13,'ESTRUTURA_MODULO(hide)'!A:D,4,0)))) -> Estoque | D13: Yes | E13: =IF(OR(D13='Listas (Hide)'!$B$17,D13='Listas (Hide)'!$C$17,D13='Listas (Hide)'!$D$17)=TRUE,1,IF(OR(D13='Listas (Hide)'!$B$18,D13='Listas (Hide)'!$C$18,D13='Listas (Hide)'!$D$18)=TRUE,2,"")) -> 1 | K13: Estoque | L13: =D13 -> Yes | M13: Core do sistema
B14: 87 | C14: =IF('General Information'!$C$6="Português",VLOOKUP(Modules!B14,'ESTRUTURA_MODULO(hide)'!A:D,2,0),IF('General Information'!$C$6="English",VLOOKUP(Modules!B14,'ESTRUTURA_MODULO(hide)'!A:D,3,0),IF('General Information'!$C$6="Español",VLOOKUP(Modules!B14,'ESTRUTURA_MODULO(hide)'!A:D,4,0)))) -> Agenda | D14: No | E14: =IF(OR(D14='Listas (Hide)'!$B$17,D14='Listas (Hide)'!$C$17,D14='Listas (Hide)'!$D$17)=TRUE,1,IF(OR(D14='Listas (Hide)'!$B$18,D14='Listas (Hide)'!$C$18,D14='Listas (Hide)'!$D$18)=TRUE,2,"")) -> 2 | F14: =HLOOKUP('General Information'!$C$6,'IDIOMA (hide)'!$A$1:$D$5016,G14,0) -> Atendimento | G14: 204 | K14: Agenda | L14: =D14 -> No | M14: Atendimento
B15: 20 | C15: =IF('General Information'!$C$6="Português",VLOOKUP(Modules!B15,'ESTRUTURA_MODULO(hide)'!A:D,2,0),IF('General Information'!$C$6="English",VLOOKUP(Modules!B15,'ESTRUTURA_MODULO(hide)'!A:D,3,0),IF('General Information'!$C$6="Español",VLOOKUP(Modules!B15,'ESTRUTURA_MODULO(hide)'!A:D,4,0)))) -> SAC | D15: No | E15: =IF(OR(D15='Listas (Hide)'!$B$17,D15='Listas (Hide)'!$C$17,D15='Listas (Hide)'!$D$17)=TRUE,1,IF(OR(D15='Listas (Hide)'!$B$18,D15='Listas (Hide)'!$C$18,D15='Listas (Hide)'!$D$18)=TRUE,2,"")) -> 2 | K15: SAC | L15: =D15 -> No | M15: Atendimento
B16: 455 | C16: =IF('General Information'!$C$6="Português",VLOOKUP(Modules!B16,'ESTRUTURA_MODULO(hide)'!A:D,2,0),IF('General Information'!$C$6="English",VLOOKUP(Modules!B16,'ESTRUTURA_MODULO(hide)'!A:D,3,0),IF('General Information'!$C$6="Español",VLOOKUP(Modules!B16,'ESTRUTURA_MODULO(hide)'!A:D,4,0)))) -> Visitas | D16: No | E16: =IF(OR(D16='Listas (Hide)'!$B$17,D16='Listas (Hide)'!$C$17,D16='Listas (Hide)'!$D$17)=TRUE,1,IF(OR(D16='Listas (Hide)'!$B$18,D16='Listas (Hide)'!$C$18,D16='Listas (Hide)'!$D$18)=TRUE,2,"")) -> 2 | K16: Visitas | L16: =D16 -> No | M16: Atendimento
B17: 88 | C17: =IF('General Information'!$C$6="Português",VLOOKUP(Modules!B17,'ESTRUTURA_MODULO(hide)'!A:D,2,0),IF('General Information'!$C$6="English",VLOOKUP(Modules!B17,'ESTRUTURA_MODULO(hide)'!A:D,3,0),IF('General Information'!$C$6="Español",VLOOKUP(Modules!B17,'ESTRUTURA_MODULO(hide)'!A:D,4,0)))) -> Prontuário Eletrônico | D17: No | E17: =IF(OR(D17='Listas (Hide)'!$B$17,D17='Listas (Hide)'!$C$17,D17='Listas (Hide)'!$D$17)=TRUE,1,IF(OR(D17='Listas (Hide)'!$B$18,D17='Listas (Hide)'!$C$18,D17='Listas (Hide)'!$D$18)=TRUE,2,"")) -> 2 | F17: =HLOOKUP('General Information'!$C$6,'IDIOMA (hide)'!$A$1:$D$5016,G17,0) -> Assistencial | G17: 205 | K17: Prontuário Eletrônico | L17: =D17 -> No | M17: Assistencial
B18: 10 | C18: =IF('General Information'!$C$6="Português",VLOOKUP(Modules!B18,'ESTRUTURA_MODULO(hide)'!A:D,2,0),IF('General Information'!$C$6="English",VLOOKUP(Modules!B18,'ESTRUTURA_MODULO(hide)'!A:D,3,0),IF('General Information'!$C$6="Español",VLOOKUP(Modules!B18,'ESTRUTURA_MODULO(hide)'!A:D,4,0)))) -> Prescrição Eletrônica | D18: No | E18: =IF(OR(D18='Listas (Hide)'!$B$17,D18='Listas (Hide)'!$C$17,D18='Listas (Hide)'!$D$17)=TRUE,1,IF(OR(D18='Listas (Hide)'!$B$18,D18='Listas (Hide)'!$C$18,D18='Listas (Hide)'!$D$18)=TRUE,2,"")) -> 2 | K18: Prescrição Eletrônica | L18: =D18 -> No | M18: Assistencial
B19: 870 | C19: =IF('General Information'!$C$6="Português",VLOOKUP(Modules!B19,'ESTRUTURA_MODULO(hide)'!A:D,2,0),IF('General Information'!$C$6="English",VLOOKUP(Modules!B19,'ESTRUTURA_MODULO(hide)'!A:D,3,0),IF('General Information'!$C$6="Español",VLOOKUP(Modules!B19,'ESTRUTURA_MODULO(hide)'!A:D,4,0)))) -> Suporte a Decisão Clínica | D19: No | E19: =IF(OR(D19='Listas (Hide)'!$B$17,D19='Listas (Hide)'!$C$17,D19='Listas (Hide)'!$D$17)=TRUE,1,IF(OR(D19='Listas (Hide)'!$B$18,D19='Listas (Hide)'!$C$18,D19='Listas (Hide)'!$D$18)=TRUE,2,"")) -> 2 | K19: Suporte a Decisão Clínica | L19: =D19 -> No | M19: Assistencial
B20: 38 | C20: =IF('General Information'!$C$6="Português",VLOOKUP(Modules!B20,'ESTRUTURA_MODULO(hide)'!A:D,2,0),IF('General Information'!$C$6="English",VLOOKUP(Modules!B20,'ESTRUTURA_MODULO(hide)'!A:D,3,0),IF('General Information'!$C$6="Español",VLOOKUP(Modules!B20,'ESTRUTURA_MODULO(hide)'!A:D,4,0)))) -> Enfermagem | D20: No | E20: =IF(OR(D20='Listas (Hide)'!$B$17,D20='Listas (Hide)'!$C$17,D20='Listas (Hide)'!$D$17)=TRUE,1,IF(OR(D20='Listas (Hide)'!$B$18,D20='Listas (Hide)'!$C$18,D20='Listas (Hide)'!$D$18)=TRUE,2,"")) -> 2 | K20: Enfermagem | L20: =D20 -> No | M20: Assistencial
B21: 89 | C21: =IF('General Information'!$C$6="Português",VLOOKUP(Modules!B21,'ESTRUTURA_MODULO(hide)'!A:D,2,0),IF('General Information'!$C$6="English",VLOOKUP(Modules!B21,'ESTRUTURA_MODULO(hide)'!A:D,3,0),IF('General Information'!$C$6="Español",VLOOKUP(Modules!B21,'ESTRUTURA_MODULO(hide)'!A:D,4,0)))) -> Pronto Atendimento | D21: No | E21: =IF(OR(D21='Listas (Hide)'!$B$17,D21='Listas (Hide)'!$C$17,D21='Listas (Hide)'!$D$17)=TRUE,1,IF(OR(D21='Listas (Hide)'!$B$18,D21='Listas (Hide)'!$C$18,D21='Listas (Hide)'!$D$18)=TRUE,2,"")) -> 2 | K21: Pronto Atendimento | L21: =D21 -> No | M21: Assistencial
B22: 22 | C22: =IF('General Information'!$C$6="Português",VLOOKUP(Modules!B22,'ESTRUTURA_MODULO(hide)'!A:D,2,0),IF('General Information'!$C$6="English",VLOOKUP(Modules!B22,'ESTRUTURA_MODULO(hide)'!A:D,3,0),IF('General Information'!$C$6="Español",VLOOKUP(Modules!B22,'ESTRUTURA_MODULO(hide)'!A:D,4,0)))) -> Consultório Médico (Ambulatório) | D22: No | E22: =IF(OR(D22='Listas (Hide)'!$B$17,D22='Listas (Hide)'!$C$17,D22='Listas (Hide)'!$D$17)=TRUE,1,IF(OR(D22='Listas (Hide)'!$B$18,D22='Listas (Hide)'!$C$18,D22='Listas (Hide)'!$D$18)=TRUE,2,"")) -> 2 | K22: Consultório Médico (Ambulatório) | L22: =D22 -> No | M22: Assistencial
B23: 26 | C23: =IF('General Information'!$C$6="Português",VLOOKUP(Modules!B23,'ESTRUTURA_MODULO(hide)'!A:D,2,0),IF('General Information'!$C$6="English",VLOOKUP(Modules!B23,'ESTRUTURA_MODULO(hide)'!A:D,3,0),IF('General Information'!$C$6="Español",VLOOKUP(Modules!B23,'ESTRUTURA_MODULO(hide)'!A:D,4,0)))) -> Centro Cirúrgico | D23: No | E23: =IF(OR(D23='Listas (Hide)'!$B$17,D23='Listas (Hide)'!$C$17,D23='Listas (Hide)'!$D$17)=TRUE,1,IF(OR(D23='Listas (Hide)'!$B$18,D23='Listas (Hide)'!$C$18,D23='Listas (Hide)'!$D$18)=TRUE,2,"")) -> 2 | K23: Centro Cirúrgico | L23: =D23 -> No | M23: Assistencial
B24: 998 | C24: =IF('General Information'!$C$6="Português",VLOOKUP(Modules!B24,'ESTRUTURA_MODULO(hide)'!A:D,2,0),IF('General Information'!$C$6="English",VLOOKUP(Modules!B24,'ESTRUTURA_MODULO(hide)'!A:D,3,0),IF('General Information'!$C$6="Español",VLOOKUP(Modules!B24,'ESTRUTURA_MODULO(hide)'!A:D,4,0)))) -> Atenção Primária | D24: No | E24: =IF(OR(D24='Listas (Hide)'!$B$17,D24='Listas (Hide)'!$C$17,D24='Listas (Hide)'!$D$17)=TRUE,1,IF(OR(D24='Listas (Hide)'!$B$18,D24='Listas (Hide)'!$C$18,D24='Listas (Hide)'!$D$18)=TRUE,2,"")) -> 2 | K24: Atenção Primária | L24: =D24 -> No | M24: Assistencial
B25: 23 | C25: =IF('General Information'!$C$6="Português",VLOOKUP(Modules!B25,'ESTRUTURA_MODULO(hide)'!A:D,2,0),IF('General Information'!$C$6="English",VLOOKUP(Modules!B25,'ESTRUTURA_MODULO(hide)'!A:D,3,0),IF('General Information'!$C$6="Español",VLOOKUP(Modules!B25,'ESTRUTURA_MODULO(hide)'!A:D,4,0)))) -> Laboratório | D25: No | E25: =IF(OR(D25='Listas (Hide)'!$B$17,D25='Listas (Hide)'!$C$17,D25='Listas (Hide)'!$D$17)=TRUE,1,IF(OR(D25='Listas (Hide)'!$B$18,D25='Listas (Hide)'!$C$18,D25='Listas (Hide)'!$D$18)=TRUE,2,"")) -> 2 | F25: =HLOOKUP('General Information'!$C$6,'IDIOMA (hide)'!$A$1:$D$5016,G25,0) -> Diagnose e Terapia | G25: 206 | K25: Laboratório | L25: =D25 -> No | M25: Diagnose e Terapia
B26: 9 | C26: =IF('General Information'!$C$6="Português",VLOOKUP(Modules!B26,'ESTRUTURA_MODULO(hide)'!A:D,2,0),IF('General Information'!$C$6="English",VLOOKUP(Modules!B26,'ESTRUTURA_MODULO(hide)'!A:D,3,0),IF('General Information'!$C$6="Español",VLOOKUP(Modules!B26,'ESTRUTURA_MODULO(hide)'!A:D,4,0)))) -> Exames | D26: No | E26: =IF(OR(D26='Listas (Hide)'!$B$17,D26='Listas (Hide)'!$C$17,D26='Listas (Hide)'!$D$17)=TRUE,1,IF(OR(D26='Listas (Hide)'!$B$18,D26='Listas (Hide)'!$C$18,D26='Listas (Hide)'!$D$18)=TRUE,2,"")) -> 2 | K26: Exames | L26: =D26 -> No | M26: Diagnose e Terapia
B27: 95 | C27: =IF('General Information'!$C$6="Português",VLOOKUP(Modules!B27,'ESTRUTURA_MODULO(hide)'!A:D,2,0),IF('General Information'!$C$6="English",VLOOKUP(Modules!B27,'ESTRUTURA_MODULO(hide)'!A:D,3,0),IF('General Information'!$C$6="Español",VLOOKUP(Modules!B27,'ESTRUTURA_MODULO(hide)'!A:D,4,0)))) -> Check-up | D27: No | E27: =IF(OR(D27='Listas (Hide)'!$B$17,D27='Listas (Hide)'!$C$17,D27='Listas (Hide)'!$D$17)=TRUE,1,IF(OR(D27='Listas (Hide)'!$B$18,D27='Listas (Hide)'!$C$18,D27='Listas (Hide)'!$D$18)=TRUE,2,"")) -> 2 | K27: Check-up | L27: =D27 -> No | M27: Diagnose e Terapia
B28: 96 | C28: =IF('General Information'!$C$6="Português",VLOOKUP(Modules!B28,'ESTRUTURA_MODULO(hide)'!A:D,2,0),IF('General Information'!$C$6="English",VLOOKUP(Modules!B28,'ESTRUTURA_MODULO(hide)'!A:D,3,0),IF('General Information'!$C$6="Español",VLOOKUP(Modules!B28,'ESTRUTURA_MODULO(hide)'!A:D,4,0)))) -> Imunização | D28: No | E28: =IF(OR(D28='Listas (Hide)'!$B$17,D28='Listas (Hide)'!$C$17,D28='Listas (Hide)'!$D$17)=TRUE,1,IF(OR(D28='Listas (Hide)'!$B$18,D28='Listas (Hide)'!$C$18,D28='Listas (Hide)'!$D$18)=TRUE,2,"")) -> 2 | K28: Imunização | L28: =D28 -> No | M28: Diagnose e Terapia
B29: 24 | C29: =IF('General Information'!$C$6="Português",VLOOKUP(Modules!B29,'ESTRUTURA_MODULO(hide)'!A:D,2,0),IF('General Information'!$C$6="English",VLOOKUP(Modules!B29,'ESTRUTURA_MODULO(hide)'!A:D,3,0),IF('General Information'!$C$6="Español",VLOOKUP(Modules!B29,'ESTRUTURA_MODULO(hide)'!A:D,4,0)))) -> Banco de Sangue | D29: No | E29: =IF(OR(D29='Listas (Hide)'!$B$17,D29='Listas (Hide)'!$C$17,D29='Listas (Hide)'!$D$17)=TRUE,1,IF(OR(D29='Listas (Hide)'!$B$18,D29='Listas (Hide)'!$C$18,D29='Listas (Hide)'!$D$18)=TRUE,2,"")) -> 2 | K29: Banco de Sangue | L29: =D29 -> No | M29: Diagnose e Terapia
B30: 945 | C30: =IF('General Information'!$C$6="Português",VLOOKUP(Modules!B30,'ESTRUTURA_MODULO(hide)'!A:D,2,0),IF('General Information'!$C$6="English",VLOOKUP(Modules!B30,'ESTRUTURA_MODULO(hide)'!A:D,3,0),IF('General Information'!$C$6="Español",VLOOKUP(Modules!B30,'ESTRUTURA_MODULO(hide)'!A:D,4,0)))) -> Banco de Leite | D30: No | E30: =IF(OR(D30='Listas (Hide)'!$B$17,D30='Listas (Hide)'!$C$17,D30='Listas (Hide)'!$D$17)=TRUE,1,IF(OR(D30='Listas (Hide)'!$B$18,D30='Listas (Hide)'!$C$18,D30='Listas (Hide)'!$D$18)=TRUE,2,"")) -> 2 | K30: Banco de Leite | L30: =D30 -> No | M30: Diagnose e Terapia
B31: 90 | C31: =IF('General Information'!$C$6="Português",VLOOKUP(Modules!B31,'ESTRUTURA_MODULO(hide)'!A:D,2,0),IF('General Information'!$C$6="English",VLOOKUP(Modules!B31,'ESTRUTURA_MODULO(hide)'!A:D,3,0),IF('General Information'!$C$6="Español",VLOOKUP(Modules!B31,'ESTRUTURA_MODULO(hide)'!A:D,4,0)))) -> Quimioterapia | D31: No | E31: =IF(OR(D31='Listas (Hide)'!$B$17,D31='Listas (Hide)'!$C$17,D31='Listas (Hide)'!$D$17)=TRUE,1,IF(OR(D31='Listas (Hide)'!$B$18,D31='Listas (Hide)'!$C$18,D31='Listas (Hide)'!$D$18)=TRUE,2,"")) -> 2 | K31: Quimioterapia | L31: =D31 -> No | M31: Diagnose e Terapia
B32: 451 | C32: =IF('General Information'!$C$6="Português",VLOOKUP(Modules!B32,'ESTRUTURA_MODULO(hide)'!A:D,2,0),IF('General Information'!$C$6="English",VLOOKUP(Modules!B32,'ESTRUTURA_MODULO(hide)'!A:D,3,0),IF('General Information'!$C$6="Español",VLOOKUP(Modules!B32,'ESTRUTURA_MODULO(hide)'!A:D,4,0)))) -> Radioterapia | D32: No | E32: =IF(OR(D32='Listas (Hide)'!$B$17,D32='Listas (Hide)'!$C$17,D32='Listas (Hide)'!$D$17)=TRUE,1,IF(OR(D32='Listas (Hide)'!$B$18,D32='Listas (Hide)'!$C$18,D32='Listas (Hide)'!$D$18)=TRUE,2,"")) -> 2 | K32: Radioterapia | L32: =D32 -> No | M32: Diagnose e Terapia
B33: 212 | C33: =IF('General Information'!$C$6="Português",VLOOKUP(Modules!B33,'ESTRUTURA_MODULO(hide)'!A:D,2,0),IF('General Information'!$C$6="English",VLOOKUP(Modules!B33,'ESTRUTURA_MODULO(hide)'!A:D,3,0),IF('General Information'!$C$6="Español",VLOOKUP(Modules!B33,'ESTRUTURA_MODULO(hide)'!A:D,4,0)))) -> Hemodiálise | D33: No | E33: =IF(OR(D33='Listas (Hide)'!$B$17,D33='Listas (Hide)'!$C$17,D33='Listas (Hide)'!$D$17)=TRUE,1,IF(OR(D33='Listas (Hide)'!$B$18,D33='Listas (Hide)'!$C$18,D33='Listas (Hide)'!$D$18)=TRUE,2,"")) -> 2 | K33: Hemodiálise | L33: =D33 -> No | M33: Diagnose e Terapia
B34: 681 | C34: =IF('General Information'!$C$6="Português",VLOOKUP(Modules!B34,'ESTRUTURA_MODULO(hide)'!A:D,2,0),IF('General Information'!$C$6="English",VLOOKUP(Modules!B34,'ESTRUTURA_MODULO(hide)'!A:D,3,0),IF('General Information'!$C$6="Español",VLOOKUP(Modules!B34,'ESTRUTURA_MODULO(hide)'!A:D,4,0)))) -> Transplantes | D34: No | E34: =IF(OR(D34='Listas (Hide)'!$B$17,D34='Listas (Hide)'!$C$17,D34='Listas (Hide)'!$D$17)=TRUE,1,IF(OR(D34='Listas (Hide)'!$B$18,D34='Listas (Hide)'!$C$18,D34='Listas (Hide)'!$D$18)=TRUE,2,"")) -> 2 | K34: Transplantes | L34: =D34 -> No | M34: Diagnose e Terapia
A35: 341 | B35: 999 | C35: =IF('General Information'!$C$6="Português",VLOOKUP(Modules!B35,'ESTRUTURA_MODULO(hide)'!A:D,2,0),IF('General Information'!$C$6="English",VLOOKUP(Modules!B35,'ESTRUTURA_MODULO(hide)'!A:D,3,0),IF('General Information'!$C$6="Español",VLOOKUP(Modules!B35,'ESTRUTURA_MODULO(hide)'!A:D,4,0)))) -> Anatomia Patológica | D35: No | E35: =IF(OR(D35='Listas (Hide)'!$B$17,D35='Listas (Hide)'!$C$17,D35='Listas (Hide)'!$D$17)=TRUE,1,IF(OR(D35='Listas (Hide)'!$B$18,D35='Listas (Hide)'!$C$18,D35='Listas (Hide)'!$D$18)=TRUE,2,"")) -> 2 | K35: Anatomia Patológica | L35: =D35 -> No | M35: Diagnose e Terapia
B36: 904 | C36: =IF('General Information'!$C$6="Português",VLOOKUP(Modules!B36,'ESTRUTURA_MODULO(hide)'!A:D,2,0),IF('General Information'!$C$6="English",VLOOKUP(Modules!B36,'ESTRUTURA_MODULO(hide)'!A:D,3,0),IF('General Information'!$C$6="Español",VLOOKUP(Modules!B36,'ESTRUTURA_MODULO(hide)'!A:D,4,0)))) -> Medicina Preventiva | D36: No | E36: =IF(OR(D36='Listas (Hide)'!$B$17,D36='Listas (Hide)'!$C$17,D36='Listas (Hide)'!$D$17)=TRUE,1,IF(OR(D36='Listas (Hide)'!$B$18,D36='Listas (Hide)'!$C$18,D36='Listas (Hide)'!$D$18)=TRUE,2,"")) -> 2 | K36: Medicina Preventiva | L36: =D36 -> No | M36: Diagnose e Terapia
B37: 71 | C37: =IF('General Information'!$C$6="Português",VLOOKUP(Modules!B37,'ESTRUTURA_MODULO(hide)'!A:D,2,0),IF('General Information'!$C$6="English",VLOOKUP(Modules!B37,'ESTRUTURA_MODULO(hide)'!A:D,3,0),IF('General Information'!$C$6="Español",VLOOKUP(Modules!B37,'ESTRUTURA_MODULO(hide)'!A:D,4,0)))) -> Nutrição | D37: No | E37: =IF(OR(D37='Listas (Hide)'!$B$17,D37='Listas (Hide)'!$C$17,D37='Listas (Hide)'!$D$17)=TRUE,1,IF(OR(D37='Listas (Hide)'!$B$18,D37='Listas (Hide)'!$C$18,D37='Listas (Hide)'!$D$18)=TRUE,2,"")) -> 2 | F37: =HLOOKUP('General Information'!$C$6,'IDIOMA (hide)'!$A$1:$D$5016,G37,0) -> Hotelaria | G37: 207 | K37: Nutrição | L37: =D37 -> No | M37: Hotelaria
B38: 93 | C38: =IF('General Information'!$C$6="Português",VLOOKUP(Modules!B38,'ESTRUTURA_MODULO(hide)'!A:D,2,0),IF('General Information'!$C$6="English",VLOOKUP(Modules!B38,'ESTRUTURA_MODULO(hide)'!A:D,3,0),IF('General Information'!$C$6="Español",VLOOKUP(Modules!B38,'ESTRUTURA_MODULO(hide)'!A:D,4,0)))) -> Higienização | D38: No | E38: =IF(OR(D38='Listas (Hide)'!$B$17,D38='Listas (Hide)'!$C$17,D38='Listas (Hide)'!$D$17)=TRUE,1,IF(OR(D38='Listas (Hide)'!$B$18,D38='Listas (Hide)'!$C$18,D38='Listas (Hide)'!$D$18)=TRUE,2,"")) -> 2 | K38: Higienização | L38: =D38 -> No | M38: Hotelaria
B39: 312 | C39: =IF('General Information'!$C$6="Português",VLOOKUP(Modules!B39,'ESTRUTURA_MODULO(hide)'!A:D,2,0),IF('General Information'!$C$6="English",VLOOKUP(Modules!B39,'ESTRUTURA_MODULO(hide)'!A:D,3,0),IF('General Information'!$C$6="Español",VLOOKUP(Modules!B39,'ESTRUTURA_MODULO(hide)'!A:D,4,0)))) -> Rouparia | D39: No | E39: =IF(OR(D39='Listas (Hide)'!$B$17,D39='Listas (Hide)'!$C$17,D39='Listas (Hide)'!$D$17)=TRUE,1,IF(OR(D39='Listas (Hide)'!$B$18,D39='Listas (Hide)'!$C$18,D39='Listas (Hide)'!$D$18)=TRUE,2,"")) -> 2 | K39: Rouparia | L39: =D39 -> No | M39: Hotelaria
B40: 391 | C40: =IF('General Information'!$C$6="Português",VLOOKUP(Modules!B40,'ESTRUTURA_MODULO(hide)'!A:D,2,0),IF('General Information'!$C$6="English",VLOOKUP(Modules!B40,'ESTRUTURA_MODULO(hide)'!A:D,3,0),IF('General Information'!$C$6="Español",VLOOKUP(Modules!B40,'ESTRUTURA_MODULO(hide)'!A:D,4,0)))) -> Home Care | D40: No | E40: =IF(OR(D40='Listas (Hide)'!$B$17,D40='Listas (Hide)'!$C$17,D40='Listas (Hide)'!$D$17)=TRUE,1,IF(OR(D40='Listas (Hide)'!$B$18,D40='Listas (Hide)'!$C$18,D40='Listas (Hide)'!$D$18)=TRUE,2,"")) -> 2 | F40: =HLOOKUP('General Information'!$C$6,'IDIOMA (hide)'!$A$1:$D$5016,G40,0) -> Apoio | G40: 208 | K40: Home Care | L40: =D40 -> No | M40: Apoio
B41: 98 | C41: =IF('General Information'!$C$6="Português",VLOOKUP(Modules!B41,'ESTRUTURA_MODULO(hide)'!A:D,2,0),IF('General Information'!$C$6="English",VLOOKUP(Modules!B41,'ESTRUTURA_MODULO(hide)'!A:D,3,0),IF('General Information'!$C$6="Español",VLOOKUP(Modules!B41,'ESTRUTURA_MODULO(hide)'!A:D,4,0)))) -> SAME | D41: No | E41: =IF(OR(D41='Listas (Hide)'!$B$17,D41='Listas (Hide)'!$C$17,D41='Listas (Hide)'!$D$17)=TRUE,1,IF(OR(D41='Listas (Hide)'!$B$18,D41='Listas (Hide)'!$C$18,D41='Listas (Hide)'!$D$18)=TRUE,2,"")) -> 2 | K41: SAME | L41: =D41 -> No | M41: Apoio
B42: 15 | C42: =IF('General Information'!$C$6="Português",VLOOKUP(Modules!B42,'ESTRUTURA_MODULO(hide)'!A:D,2,0),IF('General Information'!$C$6="English",VLOOKUP(Modules!B42,'ESTRUTURA_MODULO(hide)'!A:D,3,0),IF('General Information'!$C$6="Español",VLOOKUP(Modules!B42,'ESTRUTURA_MODULO(hide)'!A:D,4,0)))) -> Controle de Infecção Hospitalar | D42: No | E42: =IF(OR(D42='Listas (Hide)'!$B$17,D42='Listas (Hide)'!$C$17,D42='Listas (Hide)'!$D$17)=TRUE,1,IF(OR(D42='Listas (Hide)'!$B$18,D42='Listas (Hide)'!$C$18,D42='Listas (Hide)'!$D$18)=TRUE,2,"")) -> 2 | K42: Controle de Infecção Hospitalar | L42: =D42 -> No | M42: Apoio
B43: 91 | C43: =IF('General Information'!$C$6="Português",VLOOKUP(Modules!B43,'ESTRUTURA_MODULO(hide)'!A:D,2,0),IF('General Information'!$C$6="English",VLOOKUP(Modules!B43,'ESTRUTURA_MODULO(hide)'!A:D,3,0),IF('General Information'!$C$6="Español",VLOOKUP(Modules!B43,'ESTRUTURA_MODULO(hide)'!A:D,4,0)))) -> CME - Central de Material Esterilizado | D43: No | E43: =IF(OR(D43='Listas (Hide)'!$B$17,D43='Listas (Hide)'!$C$17,D43='Listas (Hide)'!$D$17)=TRUE,1,IF(OR(D43='Listas (Hide)'!$B$18,D43='Listas (Hide)'!$C$18,D43='Listas (Hide)'!$D$18)=TRUE,2,"")) -> 2 | K43: CME - Central de Material Esterilizado | L43: =D43 -> No | M43: Apoio
B44: 105 | C44: =IF('General Information'!$C$6="Português",VLOOKUP(Modules!B44,'ESTRUTURA_MODULO(hide)'!A:D,2,0),IF('General Information'!$C$6="English",VLOOKUP(Modules!B44,'ESTRUTURA_MODULO(hide)'!A:D,3,0),IF('General Information'!$C$6="Español",VLOOKUP(Modules!B44,'ESTRUTURA_MODULO(hide)'!A:D,4,0)))) -> Qualidade | D44: No | E44: =IF(OR(D44='Listas (Hide)'!$B$17,D44='Listas (Hide)'!$C$17,D44='Listas (Hide)'!$D$17)=TRUE,1,IF(OR(D44='Listas (Hide)'!$B$18,D44='Listas (Hide)'!$C$18,D44='Listas (Hide)'!$D$18)=TRUE,2,"")) -> 2 | K44: Qualidade | L44: =D44 -> No | M44: Apoio
B45: 322 | C45: =IF('General Information'!$C$6="Português",VLOOKUP(Modules!B45,'ESTRUTURA_MODULO(hide)'!A:D,2,0),IF('General Information'!$C$6="English",VLOOKUP(Modules!B45,'ESTRUTURA_MODULO(hide)'!A:D,3,0),IF('General Information'!$C$6="Español",VLOOKUP(Modules!B45,'ESTRUTURA_MODULO(hide)'!A:D,4,0)))) -> Treinamentos | D45: No | E45: =IF(OR(D45='Listas (Hide)'!$B$17,D45='Listas (Hide)'!$C$17,D45='Listas (Hide)'!$D$17)=TRUE,1,IF(OR(D45='Listas (Hide)'!$B$18,D45='Listas (Hide)'!$C$18,D45='Listas (Hide)'!$D$18)=TRUE,2,"")) -> 2 | K45: Treinamentos | L45: =D45 -> No | M45: Apoio
B46: 94 | C46: =IF('General Information'!$C$6="Português",VLOOKUP(Modules!B46,'ESTRUTURA_MODULO(hide)'!A:D,2,0),IF('General Information'!$C$6="English",VLOOKUP(Modules!B46,'ESTRUTURA_MODULO(hide)'!A:D,3,0),IF('General Information'!$C$6="Español",VLOOKUP(Modules!B46,'ESTRUTURA_MODULO(hide)'!A:D,4,0)))) -> SOS | D46: No | E46: =IF(OR(D46='Listas (Hide)'!$B$17,D46='Listas (Hide)'!$C$17,D46='Listas (Hide)'!$D$17)=TRUE,1,IF(OR(D46='Listas (Hide)'!$B$18,D46='Listas (Hide)'!$C$18,D46='Listas (Hide)'!$D$18)=TRUE,2,"")) -> 2 | K46: SOS | L46: =D46 -> No | M46: Apoio
B47: 18 | C47: =IF('General Information'!$C$6="Português",VLOOKUP(Modules!B47,'ESTRUTURA_MODULO(hide)'!A:D,2,0),IF('General Information'!$C$6="English",VLOOKUP(Modules!B47,'ESTRUTURA_MODULO(hide)'!A:D,3,0),IF('General Information'!$C$6="Español",VLOOKUP(Modules!B47,'ESTRUTURA_MODULO(hide)'!A:D,4,0)))) -> Manutenção | D47: No | E47: =IF(OR(D47='Listas (Hide)'!$B$17,D47='Listas (Hide)'!$C$17,D47='Listas (Hide)'!$D$17)=TRUE,1,IF(OR(D47='Listas (Hide)'!$B$18,D47='Listas (Hide)'!$C$18,D47='Listas (Hide)'!$D$18)=TRUE,2,"")) -> 2 | K47: Manutenção | L47: =D47 -> No | M47: Apoio
B48: 182 | C48: =IF('General Information'!$C$6="Português",VLOOKUP(Modules!B48,'ESTRUTURA_MODULO(hide)'!A:D,2,0),IF('General Information'!$C$6="English",VLOOKUP(Modules!B48,'ESTRUTURA_MODULO(hide)'!A:D,3,0),IF('General Information'!$C$6="Español",VLOOKUP(Modules!B48,'ESTRUTURA_MODULO(hide)'!A:D,4,0)))) -> Comunicação | D48: No | E48: =IF(OR(D48='Listas (Hide)'!$B$17,D48='Listas (Hide)'!$C$17,D48='Listas (Hide)'!$D$17)=TRUE,1,IF(OR(D48='Listas (Hide)'!$B$18,D48='Listas (Hide)'!$C$18,D48='Listas (Hide)'!$D$18)=TRUE,2,"")) -> 2 | K48: Comunicação | L48: =D48 -> No | M48: Apoio
B49: 7 | C49: =IF('General Information'!$C$6="Português",VLOOKUP(Modules!B49,'ESTRUTURA_MODULO(hide)'!A:D,2,0),IF('General Information'!$C$6="English",VLOOKUP(Modules!B49,'ESTRUTURA_MODULO(hide)'!A:D,3,0),IF('General Information'!$C$6="Español",VLOOKUP(Modules!B49,'ESTRUTURA_MODULO(hide)'!A:D,4,0)))) -> Compras | D49: No | E49: =IF(OR(D49='Listas (Hide)'!$B$17,D49='Listas (Hide)'!$C$17,D49='Listas (Hide)'!$D$17)=TRUE,1,IF(OR(D49='Listas (Hide)'!$B$18,D49='Listas (Hide)'!$C$18,D49='Listas (Hide)'!$D$18)=TRUE,2,"")) -> 2 | F49: =HLOOKUP('General Information'!$C$6,'IDIOMA (hide)'!$A$1:$D$5016,G49,0) -> Suprimentos | G49: 209 | K49: Compras | L49: =D49 -> No | M49: Suprimentos
B50: 100 | C50: =IF('General Information'!$C$6="Português",VLOOKUP(Modules!B50,'ESTRUTURA_MODULO(hide)'!A:D,2,0),IF('General Information'!$C$6="English",VLOOKUP(Modules!B50,'ESTRUTURA_MODULO(hide)'!A:D,3,0),IF('General Information'!$C$6="Español",VLOOKUP(Modules!B50,'ESTRUTURA_MODULO(hide)'!A:D,4,0)))) -> Licitação | D50: No | E50: =IF(OR(D50='Listas (Hide)'!$B$17,D50='Listas (Hide)'!$C$17,D50='Listas (Hide)'!$D$17)=TRUE,1,IF(OR(D50='Listas (Hide)'!$B$18,D50='Listas (Hide)'!$C$18,D50='Listas (Hide)'!$D$18)=TRUE,2,"")) -> 2 | K50: Licitação | L50: =D50 -> No | M50: Suprimentos
B51: 8 | C51: =IF('General Information'!$C$6="Português",VLOOKUP(Modules!B51,'ESTRUTURA_MODULO(hide)'!A:D,2,0),IF('General Information'!$C$6="English",VLOOKUP(Modules!B51,'ESTRUTURA_MODULO(hide)'!A:D,3,0),IF('General Information'!$C$6="Español",VLOOKUP(Modules!B51,'ESTRUTURA_MODULO(hide)'!A:D,4,0)))) -> Farmácia | D51: No | E51: =IF(OR(D51='Listas (Hide)'!$B$17,D51='Listas (Hide)'!$C$17,D51='Listas (Hide)'!$D$17)=TRUE,1,IF(OR(D51='Listas (Hide)'!$B$18,D51='Listas (Hide)'!$C$18,D51='Listas (Hide)'!$D$18)=TRUE,2,"")) -> 2 | K51: Farmácia | L51: =D51 -> No | M51: Suprimentos
B52: 31 | C52: =IF('General Information'!$C$6="Português",VLOOKUP(Modules!B52,'ESTRUTURA_MODULO(hide)'!A:D,2,0),IF('General Information'!$C$6="English",VLOOKUP(Modules!B52,'ESTRUTURA_MODULO(hide)'!A:D,3,0),IF('General Information'!$C$6="Español",VLOOKUP(Modules!B52,'ESTRUTURA_MODULO(hide)'!A:D,4,0)))) -> SUS AIH | D52: No | E52: =IF(OR(D52='Listas (Hide)'!$B$17,D52='Listas (Hide)'!$C$17,D52='Listas (Hide)'!$D$17)=TRUE,1,IF(OR(D52='Listas (Hide)'!$B$18,D52='Listas (Hide)'!$C$18,D52='Listas (Hide)'!$D$18)=TRUE,2,"")) -> 2 | F52: =HLOOKUP('General Information'!$C$6,'IDIOMA (hide)'!$A$1:$D$5016,G52,0) -> Faturamento | G52: 210 | H52: =IF(AND('General Information'!$C$4<>"Brasil",'General Information'!$C$4<>"Brazil",'General Information'!$C$4<>"Brasil")=TRUE,HLOOKUP('General Information'!$C$6,'IDIOMA (hide)'!$A$1:$D$5016,$A$72,0),"") -> ESTE MÓDULO/APLICAÇÃO NÃO ESTÁ DISPONÍVEL PARA O PAÍS SELECIONADO | K52: SUS AIH | L52: =D52 -> No | M52: Faturamento
B53: 82 | C53: =IF('General Information'!$C$6="Português",VLOOKUP(Modules!B53,'ESTRUTURA_MODULO(hide)'!A:D,2,0),IF('General Information'!$C$6="English",VLOOKUP(Modules!B53,'ESTRUTURA_MODULO(hide)'!A:D,3,0),IF('General Information'!$C$6="Español",VLOOKUP(Modules!B53,'ESTRUTURA_MODULO(hide)'!A:D,4,0)))) -> SUS APAC | D53: No | E53: =IF(OR(D53='Listas (Hide)'!$B$17,D53='Listas (Hide)'!$C$17,D53='Listas (Hide)'!$D$17)=TRUE,1,IF(OR(D53='Listas (Hide)'!$B$18,D53='Listas (Hide)'!$C$18,D53='Listas (Hide)'!$D$18)=TRUE,2,"")) -> 2 | H53: =IF(AND('General Information'!$C$4<>"Brasil",'General Information'!$C$4<>"Brazil",'General Information'!$C$4<>"Brasil")=TRUE,HLOOKUP('General Information'!$C$6,'IDIOMA (hide)'!$A$1:$D$5016,$A$72,0),"") -> ESTE MÓDULO/APLICAÇÃO NÃO ESTÁ DISPONÍVEL PARA O PAÍS SELECIONADO | K53: SUS APAC | L53: =D53 -> No | M53: Faturamento
B54: 32 | C54: =IF('General Information'!$C$6="Português",VLOOKUP(Modules!B54,'ESTRUTURA_MODULO(hide)'!A:D,2,0),IF('General Information'!$C$6="English",VLOOKUP(Modules!B54,'ESTRUTURA_MODULO(hide)'!A:D,3,0),IF('General Information'!$C$6="Español",VLOOKUP(Modules!B54,'ESTRUTURA_MODULO(hide)'!A:D,4,0)))) -> SUS BPA | D54: No | E54: =IF(OR(D54='Listas (Hide)'!$B$17,D54='Listas (Hide)'!$C$17,D54='Listas (Hide)'!$D$17)=TRUE,1,IF(OR(D54='Listas (Hide)'!$B$18,D54='Listas (Hide)'!$C$18,D54='Listas (Hide)'!$D$18)=TRUE,2,"")) -> 2 | H54: =IF(AND('General Information'!$C$4<>"Brasil",'General Information'!$C$4<>"Brazil",'General Information'!$C$4<>"Brasil")=TRUE,HLOOKUP('General Information'!$C$6,'IDIOMA (hide)'!$A$1:$D$5016,$A$72,0),"") -> ESTE MÓDULO/APLICAÇÃO NÃO ESTÁ DISPONÍVEL PARA O PAÍS SELECIONADO | K54: SUS BPA | L54: =D54 -> No | M54: Faturamento
B55: 101 | C55: =IF('General Information'!$C$6="Português",VLOOKUP(Modules!B55,'ESTRUTURA_MODULO(hide)'!A:D,2,0),IF('General Information'!$C$6="English",VLOOKUP(Modules!B55,'ESTRUTURA_MODULO(hide)'!A:D,3,0),IF('General Information'!$C$6="Español",VLOOKUP(Modules!B55,'ESTRUTURA_MODULO(hide)'!A:D,4,0)))) -> Auditoria | D55: No | E55: =IF(OR(D55='Listas (Hide)'!$B$17,D55='Listas (Hide)'!$C$17,D55='Listas (Hide)'!$D$17)=TRUE,1,IF(OR(D55='Listas (Hide)'!$B$18,D55='Listas (Hide)'!$C$18,D55='Listas (Hide)'!$D$18)=TRUE,2,"")) -> 2 | K55: Auditoria | L55: =D55 -> No | M55: Faturamento
B56: 102 | C56: =IF('General Information'!$C$6="Português",VLOOKUP(Modules!B56,'ESTRUTURA_MODULO(hide)'!A:D,2,0),IF('General Information'!$C$6="English",VLOOKUP(Modules!B56,'ESTRUTURA_MODULO(hide)'!A:D,3,0),IF('General Information'!$C$6="Español",VLOOKUP(Modules!B56,'ESTRUTURA_MODULO(hide)'!A:D,4,0)))) -> Gestão de Autorizações | D56: No | E56: =IF(OR(D56='Listas (Hide)'!$B$17,D56='Listas (Hide)'!$C$17,D56='Listas (Hide)'!$D$17)=TRUE,1,IF(OR(D56='Listas (Hide)'!$B$18,D56='Listas (Hide)'!$C$18,D56='Listas (Hide)'!$D$18)=TRUE,2,"")) -> 2 | K56: Gestão de Autorizações | L56: =D56 -> No | M56: Faturamento
B57: 12 | C57: =IF('General Information'!$C$6="Português",VLOOKUP(Modules!B57,'ESTRUTURA_MODULO(hide)'!A:D,2,0),IF('General Information'!$C$6="English",VLOOKUP(Modules!B57,'ESTRUTURA_MODULO(hide)'!A:D,3,0),IF('General Information'!$C$6="Español",VLOOKUP(Modules!B57,'ESTRUTURA_MODULO(hide)'!A:D,4,0)))) -> Contas a Pagar | D57: No | E57: =IF(OR(D57='Listas (Hide)'!$B$17,D57='Listas (Hide)'!$C$17,D57='Listas (Hide)'!$D$17)=TRUE,1,IF(OR(D57='Listas (Hide)'!$B$18,D57='Listas (Hide)'!$C$18,D57='Listas (Hide)'!$D$18)=TRUE,2,"")) -> 2 | F57: =HLOOKUP('General Information'!$C$6,'IDIOMA (hide)'!$A$1:$D$5016,G57,0) -> Financeiro | G57: 211 | K57: Contas a Pagar | L57: =D57 -> No | M57: Financeiro
B58: 28 | C58: =IF('General Information'!$C$6="Português",VLOOKUP(Modules!B58,'ESTRUTURA_MODULO(hide)'!A:D,2,0),IF('General Information'!$C$6="English",VLOOKUP(Modules!B58,'ESTRUTURA_MODULO(hide)'!A:D,3,0),IF('General Information'!$C$6="Español",VLOOKUP(Modules!B58,'ESTRUTURA_MODULO(hide)'!A:D,4,0)))) -> Contas a Receber | D58: No | E58: =IF(OR(D58='Listas (Hide)'!$B$17,D58='Listas (Hide)'!$C$17,D58='Listas (Hide)'!$D$17)=TRUE,1,IF(OR(D58='Listas (Hide)'!$B$18,D58='Listas (Hide)'!$C$18,D58='Listas (Hide)'!$D$18)=TRUE,2,"")) -> 2 | K58: Contas a Receber | L58: =D58 -> No | M58: Financeiro
B59: 86 | C59: =IF('General Information'!$C$6="Português",VLOOKUP(Modules!B59,'ESTRUTURA_MODULO(hide)'!A:D,2,0),IF('General Information'!$C$6="English",VLOOKUP(Modules!B59,'ESTRUTURA_MODULO(hide)'!A:D,3,0),IF('General Information'!$C$6="Español",VLOOKUP(Modules!B59,'ESTRUTURA_MODULO(hide)'!A:D,4,0)))) -> Controle Bancário | D59: No | E59: =IF(OR(D59='Listas (Hide)'!$B$17,D59='Listas (Hide)'!$C$17,D59='Listas (Hide)'!$D$17)=TRUE,1,IF(OR(D59='Listas (Hide)'!$B$18,D59='Listas (Hide)'!$C$18,D59='Listas (Hide)'!$D$18)=TRUE,2,"")) -> 2 | K59: Controle Bancário | L59: =D59 -> No | M59: Financeiro
B60: 29 | C60: =IF('General Information'!$C$6="Português",VLOOKUP(Modules!B60,'ESTRUTURA_MODULO(hide)'!A:D,2,0),IF('General Information'!$C$6="English",VLOOKUP(Modules!B60,'ESTRUTURA_MODULO(hide)'!A:D,3,0),IF('General Information'!$C$6="Español",VLOOKUP(Modules!B60,'ESTRUTURA_MODULO(hide)'!A:D,4,0)))) -> Tesouraria | D60: No | E60: =IF(OR(D60='Listas (Hide)'!$B$17,D60='Listas (Hide)'!$C$17,D60='Listas (Hide)'!$D$17)=TRUE,1,IF(OR(D60='Listas (Hide)'!$B$18,D60='Listas (Hide)'!$C$18,D60='Listas (Hide)'!$D$18)=TRUE,2,"")) -> 2 | K60: Tesouraria | L60: =D60 -> No | M60: Financeiro
B61: 30 | C61: =IF('General Information'!$C$6="Português",VLOOKUP(Modules!B61,'ESTRUTURA_MODULO(hide)'!A:D,2,0),IF('General Information'!$C$6="English",VLOOKUP(Modules!B61,'ESTRUTURA_MODULO(hide)'!A:D,3,0),IF('General Information'!$C$6="Español",VLOOKUP(Modules!B61,'ESTRUTURA_MODULO(hide)'!A:D,4,0)))) -> Fluxo de Caixa | D61: No | E61: =IF(OR(D61='Listas (Hide)'!$B$17,D61='Listas (Hide)'!$C$17,D61='Listas (Hide)'!$D$17)=TRUE,1,IF(OR(D61='Listas (Hide)'!$B$18,D61='Listas (Hide)'!$C$18,D61='Listas (Hide)'!$D$18)=TRUE,2,"")) -> 2 | K61: Fluxo de Caixa | L61: =D61 -> No | M61: Financeiro
B62: 103 | C62: =IF('General Information'!$C$6="Português",VLOOKUP(Modules!B62,'ESTRUTURA_MODULO(hide)'!A:D,2,0),IF('General Information'!$C$6="English",VLOOKUP(Modules!B62,'ESTRUTURA_MODULO(hide)'!A:D,3,0),IF('General Information'!$C$6="Español",VLOOKUP(Modules!B62,'ESTRUTURA_MODULO(hide)'!A:D,4,0)))) -> Retorno de Convênios | D62: No | E62: =IF(OR(D62='Listas (Hide)'!$B$17,D62='Listas (Hide)'!$C$17,D62='Listas (Hide)'!$D$17)=TRUE,1,IF(OR(D62='Listas (Hide)'!$B$18,D62='Listas (Hide)'!$C$18,D62='Listas (Hide)'!$D$18)=TRUE,2,"")) -> 2 | K62: Retorno de Convênios | L62: =D62 -> No | M62: Financeiro
B63: 104 | C63: =IF('General Information'!$C$6="Português",VLOOKUP(Modules!B63,'ESTRUTURA_MODULO(hide)'!A:D,2,0),IF('General Information'!$C$6="English",VLOOKUP(Modules!B63,'ESTRUTURA_MODULO(hide)'!A:D,3,0),IF('General Information'!$C$6="Español",VLOOKUP(Modules!B63,'ESTRUTURA_MODULO(hide)'!A:D,4,0)))) -> Repasse a Terceiros | D63: No | E63: =IF(OR(D63='Listas (Hide)'!$B$17,D63='Listas (Hide)'!$C$17,D63='Listas (Hide)'!$D$17)=TRUE,1,IF(OR(D63='Listas (Hide)'!$B$18,D63='Listas (Hide)'!$C$18,D63='Listas (Hide)'!$D$18)=TRUE,2,"")) -> 2 | K63: Repasse a Terceiros | L63: =D63 -> No | M63: Financeiro
B64: 84 | C64: =IF('General Information'!$C$6="Português",VLOOKUP(Modules!B64,'ESTRUTURA_MODULO(hide)'!A:D,2,0),IF('General Information'!$C$6="English",VLOOKUP(Modules!B64,'ESTRUTURA_MODULO(hide)'!A:D,3,0),IF('General Information'!$C$6="Español",VLOOKUP(Modules!B64,'ESTRUTURA_MODULO(hide)'!A:D,4,0)))) -> Orçamento Contábil | D64: =IF(Questions!D36="Yes","Yes","No") -> No | E64: =IF(OR(D64='Listas (Hide)'!$B$17,D64='Listas (Hide)'!$C$17,D64='Listas (Hide)'!$D$17)=TRUE,1,IF(OR(D64='Listas (Hide)'!$B$18,D64='Listas (Hide)'!$C$18,D64='Listas (Hide)'!$D$18)=TRUE,2,"")) -> 2 | F64: =HLOOKUP('General Information'!$C$6,'IDIOMA (hide)'!$A$1:$D$5016,G64,0) -> Controladoria | G64: 212 | K64: Orçamento Contábil | L64: =D64 -> No | M64: Controladoria
B65: 85 | C65: =IF('General Information'!$C$6="Português",VLOOKUP(Modules!B65,'ESTRUTURA_MODULO(hide)'!A:D,2,0),IF('General Information'!$C$6="English",VLOOKUP(Modules!B65,'ESTRUTURA_MODULO(hide)'!A:D,3,0),IF('General Information'!$C$6="Español",VLOOKUP(Modules!B65,'ESTRUTURA_MODULO(hide)'!A:D,4,0)))) -> Patrimônio | D65: No | E65: =IF(OR(D65='Listas (Hide)'!$B$17,D65='Listas (Hide)'!$C$17,D65='Listas (Hide)'!$D$17)=TRUE,1,IF(OR(D65='Listas (Hide)'!$B$18,D65='Listas (Hide)'!$C$18,D65='Listas (Hide)'!$D$18)=TRUE,2,"")) -> 2 | K65: Patrimônio | L65: =D65 -> No | M65: Controladoria
B66: 685 | C66: =IF('General Information'!$C$6="Português",VLOOKUP(Modules!B66,'ESTRUTURA_MODULO(hide)'!A:D,2,0),IF('General Information'!$C$6="English",VLOOKUP(Modules!B66,'ESTRUTURA_MODULO(hide)'!A:D,3,0),IF('General Information'!$C$6="Español",VLOOKUP(Modules!B66,'ESTRUTURA_MODULO(hide)'!A:D,4,0)))) -> Fiscal | D66: No | E66: =IF(OR(D66='Listas (Hide)'!$B$17,D66='Listas (Hide)'!$C$17,D66='Listas (Hide)'!$D$17)=TRUE,1,IF(OR(D66='Listas (Hide)'!$B$18,D66='Listas (Hide)'!$C$18,D66='Listas (Hide)'!$D$18)=TRUE,2,"")) -> 2 | K66: Fiscal | L66: =D66 -> No | M66: Controladoria
B67: 11 | C67: =IF('General Information'!$C$6="Português",VLOOKUP(Modules!B67,'ESTRUTURA_MODULO(hide)'!A:D,2,0),IF('General Information'!$C$6="English",VLOOKUP(Modules!B67,'ESTRUTURA_MODULO(hide)'!A:D,3,0),IF('General Information'!$C$6="Español",VLOOKUP(Modules!B67,'ESTRUTURA_MODULO(hide)'!A:D,4,0)))) -> Contabilidade | D67: No | E67: =IF(OR(D67='Listas (Hide)'!$B$17,D67='Listas (Hide)'!$C$17,D67='Listas (Hide)'!$D$17)=TRUE,1,IF(OR(D67='Listas (Hide)'!$B$18,D67='Listas (Hide)'!$C$18,D67='Listas (Hide)'!$D$18)=TRUE,2,"")) -> 2 | H67: =IF(D75="Yes",HLOOKUP('General Information'!$C$6,'IDIOMA (hide)'!$A$1:$D$5016,A75,0),"") | K67: Contabilidade | L67: =D67 -> No | M67: Controladoria
B68: 13 | C68: =IF('General Information'!$C$6="Português",VLOOKUP(Modules!B68,'ESTRUTURA_MODULO(hide)'!A:D,2,0),IF('General Information'!$C$6="English",VLOOKUP(Modules!B68,'ESTRUTURA_MODULO(hide)'!A:D,3,0),IF('General Information'!$C$6="Español",VLOOKUP(Modules!B68,'ESTRUTURA_MODULO(hide)'!A:D,4,0)))) -> Custos | D68: No | E68: =IF(OR(D68='Listas (Hide)'!$B$17,D68='Listas (Hide)'!$C$17,D68='Listas (Hide)'!$D$17)=TRUE,1,IF(OR(D68='Listas (Hide)'!$B$18,D68='Listas (Hide)'!$C$18,D68='Listas (Hide)'!$D$18)=TRUE,2,"")) -> 2 | K68: Custos | L68: =D68 -> No | M68: Controladoria
B69: 456 | C69: =IF('General Information'!$C$6="Português",VLOOKUP(Modules!B69,'ESTRUTURA_MODULO(hide)'!A:D,2,0),IF('General Information'!$C$6="English",VLOOKUP(Modules!B69,'ESTRUTURA_MODULO(hide)'!A:D,3,0),IF('General Information'!$C$6="Español",VLOOKUP(Modules!B69,'ESTRUTURA_MODULO(hide)'!A:D,4,0)))) -> Projetos de Investimento | D69: No | E69: =IF(OR(D69='Listas (Hide)'!$B$17,D69='Listas (Hide)'!$C$17,D69='Listas (Hide)'!$D$17)=TRUE,1,IF(OR(D69='Listas (Hide)'!$B$18,D69='Listas (Hide)'!$C$18,D69='Listas (Hide)'!$D$18)=TRUE,2,"")) -> 2 | K69: Projetos de Investimento | L69: =D69 -> No | M69: Controladoria
B70: 14 | C70: =IF('General Information'!$C$6="Português",VLOOKUP(Modules!B70,'ESTRUTURA_MODULO(hide)'!A:D,2,0),IF('General Information'!$C$6="English",VLOOKUP(Modules!B70,'ESTRUTURA_MODULO(hide)'!A:D,3,0),IF('General Information'!$C$6="Español",VLOOKUP(Modules!B70,'ESTRUTURA_MODULO(hide)'!A:D,4,0)))) -> EIS | D70: No | E70: =IF(OR(D70='Listas (Hide)'!$B$17,D70='Listas (Hide)'!$C$17,D70='Listas (Hide)'!$D$17)=TRUE,1,IF(OR(D70='Listas (Hide)'!$B$18,D70='Listas (Hide)'!$C$18,D70='Listas (Hide)'!$D$18)=TRUE,2,"")) -> 2 | F70: =HLOOKUP('General Information'!$C$6,'IDIOMA (hide)'!$A$1:$D$5016,G70,0) -> Gerencial | G70: 213 | K70: EIS | L70: =D70 -> No | M70: Gerencial
B71: 453 | C71: =IF('General Information'!$C$6="Português",VLOOKUP(Modules!B71,'ESTRUTURA_MODULO(hide)'!A:D,2,0),IF('General Information'!$C$6="English",VLOOKUP(Modules!B71,'ESTRUTURA_MODULO(hide)'!A:D,3,0),IF('General Information'!$C$6="Español",VLOOKUP(Modules!B71,'ESTRUTURA_MODULO(hide)'!A:D,4,0)))) -> BSC | D71: No | E71: =IF(OR(D71='Listas (Hide)'!$B$17,D71='Listas (Hide)'!$C$17,D71='Listas (Hide)'!$D$17)=TRUE,1,IF(OR(D71='Listas (Hide)'!$B$18,D71='Listas (Hide)'!$C$18,D71='Listas (Hide)'!$D$18)=TRUE,2,"")) -> 2 | K71: BSC | L71: =D71 -> No | M71: Gerencial
A72: 362 | B72: 331 | C72: =IF('General Information'!$C$6="Português",VLOOKUP(Modules!B72,'ESTRUTURA_MODULO(hide)'!A:D,2,0),IF('General Information'!$C$6="English",VLOOKUP(Modules!B72,'ESTRUTURA_MODULO(hide)'!A:D,3,0),IF('General Information'!$C$6="Español",VLOOKUP(Modules!B72,'ESTRUTURA_MODULO(hide)'!A:D,4,0)))) -> Aplicação Tasy WEB | D72: No | E72: =IF(OR(D72='Listas (Hide)'!$B$17,D72='Listas (Hide)'!$C$17,D72='Listas (Hide)'!$D$17)=TRUE,1,IF(OR(D72='Listas (Hide)'!$B$18,D72='Listas (Hide)'!$C$18,D72='Listas (Hide)'!$D$18)=TRUE,2,"")) -> 2 | F72: =HLOOKUP('General Information'!$C$6,'IDIOMA (hide)'!$A$1:$D$5016,G72,0) -> Mobilidade | G72: 214 | K72: Aplicação Tasy WEB | L72: =D72 -> No | M72: Mobilidade
B73: 935 | C73: =IF('General Information'!$C$6="Português",VLOOKUP(Modules!B73,'ESTRUTURA_MODULO(hide)'!A:D,2,0),IF('General Information'!$C$6="English",VLOOKUP(Modules!B73,'ESTRUTURA_MODULO(hide)'!A:D,3,0),IF('General Information'!$C$6="Español",VLOOKUP(Modules!B73,'ESTRUTURA_MODULO(hide)'!A:D,4,0)))) -> Aplicação Tasy Palm | D73: No | E73: =IF(OR(D73='Listas (Hide)'!$B$17,D73='Listas (Hide)'!$C$17,D73='Listas (Hide)'!$D$17)=TRUE,1,IF(OR(D73='Listas (Hide)'!$B$18,D73='Listas (Hide)'!$C$18,D73='Listas (Hide)'!$D$18)=TRUE,2,"")) -> 2 | K73: Aplicação Tasy Palm | L73: =D73 -> No | M73: Mobilidade
B74: 944 | C74: =IF('General Information'!$C$6="Português",VLOOKUP(Modules!B74,'ESTRUTURA_MODULO(hide)'!A:D,2,0),IF('General Information'!$C$6="English",VLOOKUP(Modules!B74,'ESTRUTURA_MODULO(hide)'!A:D,3,0),IF('General Information'!$C$6="Español",VLOOKUP(Modules!B74,'ESTRUTURA_MODULO(hide)'!A:D,4,0)))) -> Aplicação Tasy iOS | D74: No | E74: =IF(OR(D74='Listas (Hide)'!$B$17,D74='Listas (Hide)'!$C$17,D74='Listas (Hide)'!$D$17)=TRUE,1,IF(OR(D74='Listas (Hide)'!$B$18,D74='Listas (Hide)'!$C$18,D74='Listas (Hide)'!$D$18)=TRUE,2,"")) -> 2 | K74: Aplicação Tasy iOS | L74: =D74 -> No | M74: Mobilidade
A75: 354 | B75: 283 | C75: =IF('General Information'!$C$6="Português",VLOOKUP(Modules!B75,'ESTRUTURA_MODULO(hide)'!A:D,2,0),IF('General Information'!$C$6="English",VLOOKUP(Modules!B75,'ESTRUTURA_MODULO(hide)'!A:D,3,0),IF('General Information'!$C$6="Español",VLOOKUP(Modules!B75,'ESTRUTURA_MODULO(hide)'!A:D,4,0)))) -> Tasy Web Suite | D75: No | E75: =IF(OR(D75='Listas (Hide)'!$B$17,D75='Listas (Hide)'!$C$17,D75='Listas (Hide)'!$D$17)=TRUE,1,IF(OR(D75='Listas (Hide)'!$B$18,D75='Listas (Hide)'!$C$18,D75='Listas (Hide)'!$D$18)=TRUE,2,"")) -> 2 | K75: Tasy Web Suite | L75: =D75 -> No | M75: Mobilidade
B77: Módulos de OPS
B79: 1 | C79: =IF('General Information'!$C$6="Português",VLOOKUP(Modules!B79,'ESTRUTURA_MODULO(hide)'!A:D,2,0),IF('General Information'!$C$6="English",VLOOKUP(Modules!B79,'ESTRUTURA_MODULO(hide)'!A:D,3,0),IF('General Information'!$C$6="Español",VLOOKUP(Modules!B79,'ESTRUTURA_MODULO(hide)'!A:D,4,0)))) -> Instalação do Produto | D79: =IF('General Information'!$C$18="Tasy Prestador","No","Yes") -> Yes | E79: =IF(OR(D79='Listas (Hide)'!$B$17,D79='Listas (Hide)'!$C$17,D79='Listas (Hide)'!$D$17)=TRUE,1,IF(OR(D79='Listas (Hide)'!$B$18,D79='Listas (Hide)'!$C$18,D79='Listas (Hide)'!$D$18)=TRUE,2,"")) -> 1 | F79: OPS
B80: 372 | C80: =IF('General Information'!$C$6="Português",VLOOKUP(Modules!B80,'ESTRUTURA_MODULO(hide)'!A:D,2,0),IF('General Information'!$C$6="English",VLOOKUP(Modules!B80,'ESTRUTURA_MODULO(hide)'!A:D,3,0),IF('General Information'!$C$6="Español",VLOOKUP(Modules!B80,'ESTRUTURA_MODULO(hide)'!A:D,4,0)))) -> Produtos | D80: =IF('General Information'!$C$18="Tasy Prestador","No","Yes") -> Yes | E80: =IF(OR(D80='Listas (Hide)'!$B$17,D80='Listas (Hide)'!$C$17,D80='Listas (Hide)'!$D$17)=TRUE,1,IF(OR(D80='Listas (Hide)'!$B$18,D80='Listas (Hide)'!$C$18,D80='Listas (Hide)'!$D$18)=TRUE,2,"")) -> 1
B81: 374 | C81: =IF('General Information'!$C$6="Português",VLOOKUP(Modules!B81,'ESTRUTURA_MODULO(hide)'!A:D,2,0),IF('General Information'!$C$6="English",VLOOKUP(Modules!B81,'ESTRUTURA_MODULO(hide)'!A:D,3,0),IF('General Information'!$C$6="Español",VLOOKUP(Modules!B81,'ESTRUTURA_MODULO(hide)'!A:D,4,0)))) -> Comercial | D81: =IF('General Information'!$C$18="Tasy Prestador","No","Yes") -> Yes | E81: =IF(OR(D81='Listas (Hide)'!$B$17,D81='Listas (Hide)'!$C$17,D81='Listas (Hide)'!$D$17)=TRUE,1,IF(OR(D81='Listas (Hide)'!$B$18,D81='Listas (Hide)'!$C$18,D81='Listas (Hide)'!$D$18)=TRUE,2,"")) -> 1
B82: 375 | C82: =IF('General Information'!$C$6="Português",VLOOKUP(Modules!B82,'ESTRUTURA_MODULO(hide)'!A:D,2,0),IF('General Information'!$C$6="English",VLOOKUP(Modules!B82,'ESTRUTURA_MODULO(hide)'!A:D,3,0),IF('General Information'!$C$6="Español",VLOOKUP(Modules!B82,'ESTRUTURA_MODULO(hide)'!A:D,4,0)))) -> Contratos e Beneficiários | D82: =IF('General Information'!$C$18="Tasy Prestador","No","Yes") -> Yes | E82: =IF(OR(D82='Listas (Hide)'!$B$17,D82='Listas (Hide)'!$C$17,D82='Listas (Hide)'!$D$17)=TRUE,1,IF(OR(D82='Listas (Hide)'!$B$18,D82='Listas (Hide)'!$C$18,D82='Listas (Hide)'!$D$18)=TRUE,2,"")) -> 1
B83: 377 | C83: =IF('General Information'!$C$6="Português",VLOOKUP(Modules!B83,'ESTRUTURA_MODULO(hide)'!A:D,2,0),IF('General Information'!$C$6="English",VLOOKUP(Modules!B83,'ESTRUTURA_MODULO(hide)'!A:D,3,0),IF('General Information'!$C$6="Español",VLOOKUP(Modules!B83,'ESTRUTURA_MODULO(hide)'!A:D,4,0)))) -> Produção de Contas Médicas | D83: =IF('General Information'!$C$18="Tasy Prestador","No","Yes") -> Yes | E83: =IF(OR(D83='Listas (Hide)'!$B$17,D83='Listas (Hide)'!$C$17,D83='Listas (Hide)'!$D$17)=TRUE,1,IF(OR(D83='Listas (Hide)'!$B$18,D83='Listas (Hide)'!$C$18,D83='Listas (Hide)'!$D$18)=TRUE,2,"")) -> 1
B84: 379 | C84: =IF('General Information'!$C$6="Português",VLOOKUP(Modules!B84,'ESTRUTURA_MODULO(hide)'!A:D,2,0),IF('General Information'!$C$6="English",VLOOKUP(Modules!B84,'ESTRUTURA_MODULO(hide)'!A:D,3,0),IF('General Information'!$C$6="Español",VLOOKUP(Modules!B84,'ESTRUTURA_MODULO(hide)'!A:D,4,0)))) -> Mensalidades | D84: =IF('General Information'!C18="Tasy Prestador","No",IF('General Information'!D17=7,"No","Yes")) -> Yes | E84: =IF(OR(D84='Listas (Hide)'!$B$17,D84='Listas (Hide)'!$C$17,D84='Listas (Hide)'!$D$17)=TRUE,1,IF(OR(D84='Listas (Hide)'!$B$18,D84='Listas (Hide)'!$C$18,D84='Listas (Hide)'!$D$18)=TRUE,2,"")) -> 1
B85: 380 | C85: =IF('General Information'!$C$6="Português",VLOOKUP(Modules!B85,'ESTRUTURA_MODULO(hide)'!A:D,2,0),IF('General Information'!$C$6="English",VLOOKUP(Modules!B85,'ESTRUTURA_MODULO(hide)'!A:D,3,0),IF('General Information'!$C$6="Español",VLOOKUP(Modules!B85,'ESTRUTURA_MODULO(hide)'!A:D,4,0)))) -> Informações ANS | D85: =IF('General Information'!$C$18="Tasy Prestador","No","Yes") -> Yes | E85: =IF(OR(D85='Listas (Hide)'!$B$17,D85='Listas (Hide)'!$C$17,D85='Listas (Hide)'!$D$17)=TRUE,1,IF(OR(D85='Listas (Hide)'!$B$18,D85='Listas (Hide)'!$C$18,D85='Listas (Hide)'!$D$18)=TRUE,2,"")) -> 1
B86: 381 | C86: =IF('General Information'!$C$6="Português",VLOOKUP(Modules!B86,'ESTRUTURA_MODULO(hide)'!A:D,2,0),IF('General Information'!$C$6="English",VLOOKUP(Modules!B86,'ESTRUTURA_MODULO(hide)'!A:D,3,0),IF('General Information'!$C$6="Español",VLOOKUP(Modules!B86,'ESTRUTURA_MODULO(hide)'!A:D,4,0)))) -> Portal Web | D86: =IF('General Information'!$C$18="Tasy Prestador","No","Yes") -> Yes | E86: =IF(OR(D86='Listas (Hide)'!$B$17,D86='Listas (Hide)'!$C$17,D86='Listas (Hide)'!$D$17)=TRUE,1,IF(OR(D86='Listas (Hide)'!$B$18,D86='Listas (Hide)'!$C$18,D86='Listas (Hide)'!$D$18)=TRUE,2,"")) -> 1
B87: 582 | C87: =IF('General Information'!$C$6="Português",VLOOKUP(Modules!B87,'ESTRUTURA_MODULO(hide)'!A:D,2,0),IF('General Information'!$C$6="English",VLOOKUP(Modules!B87,'ESTRUTURA_MODULO(hide)'!A:D,3,0),IF('General Information'!$C$6="Español",VLOOKUP(Modules!B87,'ESTRUTURA_MODULO(hide)'!A:D,4,0)))) -> Relacionamento | D87: =IF('General Information'!$C$18="Tasy Prestador","No","Yes") -> Yes | E87: =IF(OR(D87='Listas (Hide)'!$B$17,D87='Listas (Hide)'!$C$17,D87='Listas (Hide)'!$D$17)=TRUE,1,IF(OR(D87='Listas (Hide)'!$B$18,D87='Listas (Hide)'!$C$18,D87='Listas (Hide)'!$D$18)=TRUE,2,"")) -> 1
B88: 583 | C88: =IF('General Information'!$C$6="Português",VLOOKUP(Modules!B88,'ESTRUTURA_MODULO(hide)'!A:D,2,0),IF('General Information'!$C$6="English",VLOOKUP(Modules!B88,'ESTRUTURA_MODULO(hide)'!A:D,3,0),IF('General Information'!$C$6="Español",VLOOKUP(Modules!B88,'ESTRUTURA_MODULO(hide)'!A:D,4,0)))) -> Gestão de Cooperados | D88: =IF('General Information'!C18="Tasy Prestador","No",IF('General Information'!D17=7,"No","Yes")) -> Yes | E88: =IF(OR(D88='Listas (Hide)'!$B$17,D88='Listas (Hide)'!$C$17,D88='Listas (Hide)'!$D$17)=TRUE,1,IF(OR(D88='Listas (Hide)'!$B$18,D88='Listas (Hide)'!$C$18,D88='Listas (Hide)'!$D$18)=TRUE,2,"")) -> 1
B89: 690 | C89: =IF('General Information'!$C$6="Português",VLOOKUP(Modules!B89,'ESTRUTURA_MODULO(hide)'!A:D,2,0),IF('General Information'!$C$6="English",VLOOKUP(Modules!B89,'ESTRUTURA_MODULO(hide)'!A:D,3,0),IF('General Information'!$C$6="Español",VLOOKUP(Modules!B89,'ESTRUTURA_MODULO(hide)'!A:D,4,0)))) -> Prestadores | D89: =IF('General Information'!$C$18="Tasy Prestador","No","Yes") -> Yes | E89: =IF(OR(D89='Listas (Hide)'!$B$17,D89='Listas (Hide)'!$C$17,D89='Listas (Hide)'!$D$17)=TRUE,1,IF(OR(D89='Listas (Hide)'!$B$18,D89='Listas (Hide)'!$C$18,D89='Listas (Hide)'!$D$18)=TRUE,2,"")) -> 1
B90: 691 | C90: =IF('General Information'!$C$6="Português",VLOOKUP(Modules!B90,'ESTRUTURA_MODULO(hide)'!A:D,2,0),IF('General Information'!$C$6="English",VLOOKUP(Modules!B90,'ESTRUTURA_MODULO(hide)'!A:D,3,0),IF('General Information'!$C$6="Español",VLOOKUP(Modules!B90,'ESTRUTURA_MODULO(hide)'!A:D,4,0)))) -> Autorizações | D90: =IF('General Information'!$C$18="Tasy Prestador","No","Yes") -> Yes | E90: =IF(OR(D90='Listas (Hide)'!$B$17,D90='Listas (Hide)'!$C$17,D90='Listas (Hide)'!$D$17)=TRUE,1,IF(OR(D90='Listas (Hide)'!$B$18,D90='Listas (Hide)'!$C$18,D90='Listas (Hide)'!$D$18)=TRUE,2,"")) -> 1
B91: 692 | C91: =IF('General Information'!$C$6="Português",VLOOKUP(Modules!B91,'ESTRUTURA_MODULO(hide)'!A:D,2,0),IF('General Information'!$C$6="English",VLOOKUP(Modules!B91,'ESTRUTURA_MODULO(hide)'!A:D,3,0),IF('General Information'!$C$6="Español",VLOOKUP(Modules!B91,'ESTRUTURA_MODULO(hide)'!A:D,4,0)))) -> Autorizações de Intercâmbio | D91: =IF('General Information'!$C$18="Tasy Prestador","No","Yes") -> Yes | E91: =IF(OR(D91='Listas (Hide)'!$B$17,D91='Listas (Hide)'!$C$17,D91='Listas (Hide)'!$D$17)=TRUE,1,IF(OR(D91='Listas (Hide)'!$B$18,D91='Listas (Hide)'!$C$18,D91='Listas (Hide)'!$D$18)=TRUE,2,"")) -> 1
B92: 695 | C92: =IF('General Information'!$C$6="Português",VLOOKUP(Modules!B92,'ESTRUTURA_MODULO(hide)'!A:D,2,0),IF('General Information'!$C$6="English",VLOOKUP(Modules!B92,'ESTRUTURA_MODULO(hide)'!A:D,3,0),IF('General Information'!$C$6="Español",VLOOKUP(Modules!B92,'ESTRUTURA_MODULO(hide)'!A:D,4,0)))) -> Análise de Contas Médicas | D92: =IF('General Information'!$C$18="Tasy Prestador","No","Yes") -> Yes | E92: =IF(OR(D92='Listas (Hide)'!$B$17,D92='Listas (Hide)'!$C$17,D92='Listas (Hide)'!$D$17)=TRUE,1,IF(OR(D92='Listas (Hide)'!$B$18,D92='Listas (Hide)'!$C$18,D92='Listas (Hide)'!$D$18)=TRUE,2,"")) -> 1
B93: 706 | C93: =IF('General Information'!$C$6="Português",VLOOKUP(Modules!B93,'ESTRUTURA_MODULO(hide)'!A:D,2,0),IF('General Information'!$C$6="English",VLOOKUP(Modules!B93,'ESTRUTURA_MODULO(hide)'!A:D,3,0),IF('General Information'!$C$6="Español",VLOOKUP(Modules!B93,'ESTRUTURA_MODULO(hide)'!A:D,4,0)))) -> Contratos de Intercâmbio | D93: =IF('General Information'!$C$18="Tasy Prestador","No","Yes") -> Yes | E93: =IF(OR(D93='Listas (Hide)'!$B$17,D93='Listas (Hide)'!$C$17,D93='Listas (Hide)'!$D$17)=TRUE,1,IF(OR(D93='Listas (Hide)'!$B$18,D93='Listas (Hide)'!$C$18,D93='Listas (Hide)'!$D$18)=TRUE,2,"")) -> 1
B94: 708 | C94: =IF('General Information'!$C$6="Português",VLOOKUP(Modules!B94,'ESTRUTURA_MODULO(hide)'!A:D,2,0),IF('General Information'!$C$6="English",VLOOKUP(Modules!B94,'ESTRUTURA_MODULO(hide)'!A:D,3,0),IF('General Information'!$C$6="Español",VLOOKUP(Modules!B94,'ESTRUTURA_MODULO(hide)'!A:D,4,0)))) -> Regras | D94: =IF('General Information'!$C$18="Tasy Prestador","No","Yes") -> Yes | E94: =IF(OR(D94='Listas (Hide)'!$B$17,D94='Listas (Hide)'!$C$17,D94='Listas (Hide)'!$D$17)=TRUE,1,IF(OR(D94='Listas (Hide)'!$B$18,D94='Listas (Hide)'!$C$18,D94='Listas (Hide)'!$D$18)=TRUE,2,"")) -> 1
B95: 835 | C95: =IF('General Information'!$C$6="Português",VLOOKUP(Modules!B95,'ESTRUTURA_MODULO(hide)'!A:D,2,0),IF('General Information'!$C$6="English",VLOOKUP(Modules!B95,'ESTRUTURA_MODULO(hide)'!A:D,3,0),IF('General Information'!$C$6="Español",VLOOKUP(Modules!B95,'ESTRUTURA_MODULO(hide)'!A:D,4,0)))) -> Produção de Contas Médicas - Intercâmbio | D95: =IF('General Information'!D17=8,"Yes","No") -> No | E95: =IF(OR(D95='Listas (Hide)'!$B$17,D95='Listas (Hide)'!$C$17,D95='Listas (Hide)'!$D$17)=TRUE,1,IF(OR(D95='Listas (Hide)'!$B$18,D95='Listas (Hide)'!$C$18,D95='Listas (Hide)'!$D$18)=TRUE,2,"")) -> 2
B96: 836 | C96: =IF('General Information'!$C$6="Português",VLOOKUP(Modules!B96,'ESTRUTURA_MODULO(hide)'!A:D,2,0),IF('General Information'!$C$6="English",VLOOKUP(Modules!B96,'ESTRUTURA_MODULO(hide)'!A:D,3,0),IF('General Information'!$C$6="Español",VLOOKUP(Modules!B96,'ESTRUTURA_MODULO(hide)'!A:D,4,0)))) -> Faturamento | D96: =IF('General Information'!$C$18="Tasy Prestador","No","Yes") -> Yes | E96: =IF(OR(D96='Listas (Hide)'!$B$17,D96='Listas (Hide)'!$C$17,D96='Listas (Hide)'!$D$17)=TRUE,1,IF(OR(D96='Listas (Hide)'!$B$18,D96='Listas (Hide)'!$C$18,D96='Listas (Hide)'!$D$18)=TRUE,2,"")) -> 1
D1048572: Yes

Sheet Folha1
A1: Administração do Sistema | B1: Sim
A2: Ordem de Serviço (Nova) | B2: Sim
A3: Ger. de Relatório / Avaliações | B3: Sim
A4: Cadastro Médico | B4: Sim
A5: Pessoa jurídica | B5: Sim
A6: Procedimentos | B6: Sim
A7: Cadastro de Transações Financeiras | B7: Sim
A8: Empresa/Estabelecimento/Contas/CC | B8: Sim
A9: Cadastros Financeiros | B9: Sim
A10: Cargas Externas | B10: Sim
A11: OPS - Gestão de Análise de Produção Médica | B11: Sim
A12: OPS - Controle dos Grupos de Análise | B12: Sim
... A87: Vendas Online | B87: Sim

Sheet Questions
A1: 2 | B1: =HLOOKUP('General Information'!$C$6,'IDIOMA (hide)'!$A$1:$D$5016,A1,0) -> LTEP - Levantamento Técnico de Estimativa de Projeto TASY EMR Código do documento: 0060 - Rev 024
E2: ocultar | J2: ocultar | K2: ocultar | L2: ocultar
B3: Backoffice
B4: 215 | C4: 216 | D4: 217 | F4: 218 | J4: hide
B5: =HLOOKUP('General Information'!$C$6,'IDIOMA (hide)'!$A$1:$D$5016,B4,0) -> ID Pergunta | C5: =HLOOKUP('General Information'!$C$6,'IDIOMA (hide)'!$A$1:$D$5016,C4,0) -> Pergunta | D5: =HLOOKUP('General Information'!$C$6,'IDIOMA (hide)'!$A$1:$D$5016,D4,0) -> Resposta | E5: Id Função | F5: =HLOOKUP('General Information'!$C$6,'IDIOMA (hide)'!$A$1:$D$5016,F4,0) -> Horas Adicionais | G5: X | J5: Racional | K5: Horas Implantação | L5: Justificativa
A6: 62 | B6: 9 | C6: =HLOOKUP('General Information'!$C$6,'IDIOMA (hide)'!$A$1:$D$5016,A6,0) -> Quantas recepções a instituição possui? | E6: 916 | F6: =IF(D6>1,D6*(K6*0.5),"0") -> 0 | G6: =HLOOKUP('General Information'!$C$6,'IDIOMA (hide)'!$A$1:$D$5016,I6,0) -> LTEP - Levantamento Técnico de Estimativa de Projeto TASY EMR Código do documento: 0060 - Rev 024 | I6: 2 | J6: +50% para cada | K6: =VLOOKUP(E6,'BASE_FUNCOES (hide)'!A:I,9,0) -> 24 | L6: =IF(D6>0,CONCATENATE("Acrescido ",D6*50,"% de horas em virtude da instituição possuir ",D6," recepções."),"")
A7: 63 | B7: 10 | C7: =HLOOKUP('General Information'!$C$6,'IDIOMA (hide)'!$A$1:$D$5016,A7,0) -> Quantos setores utilizarão um painel de chamadas para controle de filas de atendimento? | E7: 10021 | F7: =IF(D7>1,(D7*(K7*0.4)),0) -> 0 | I7: 1 | J7: +40% para cada | K7: =VLOOKUP(E7,'BASE_FUNCOES (hide)'!A:I,9,0) -> 16 | L7: =IF(D7>0,CONCATENATE("Acrescido ",D7*40,"% de horas em virtude da instituição possuir ",D7," setores que utilizarão painel de chamadas para fila de atendimento."),"")
A8: 431 | B8: 74 | C8: =HLOOKUP('General Information'!$C$6,'IDIOMA (hide)'!$A$1:$D$5016,A8,0) -> Requer a personalização de relatórios no formato do hospital (contrato, etiquetas, aviso de privacidade etc.)? | E8: 260 | F8: =IF(D8>1,(D8*8),0) -> 0 | I8: 150 | J8: Personalizacao de relatorios à 8 horas por relatorio | K8: 8
A9: 68 | B9: 14 | C9: =HLOOKUP('General Information'!$C$6,'IDIOMA (hide)'!$A$1:$D$5016,A9,0) -> Utilizará auto atendimento? | E9: 10021 | F9: =IF(OR(D9="Yes",D9="Yes",D9="Yes")=TRUE,K9,0) -> 0 | I9: Yes | J9: Caso utilize, irá agregar mais 24 horas na função gerenciamento de senhas | K9: 24 | L9: =IF(D9="Sim","Acrescido 12 horas em virtude da instituição utilizar o auto-atendimento.","")
A10: 477 | B10: 96 | C10: =HLOOKUP('General Information'!$C$6,'IDIOMA (hide)'!$A$1:$D$5016,A10,0) -> O cliente irá utilizar a Tele Consulta? | E10: 821 | F10: =IF(D10="Yes",K10,0) -> 0 | I10: 1 a 30 | J10: Se utilizar a Tele Consulta, acrescentar 4 horas na função Agenda de Consultas | K10: 4
A11: 46 | B11: 1 | C11: =HLOOKUP('General Information'!$C$6,'IDIOMA (hide)'!$A$1:$D$5016,A11,0) -> Quantos convênios a instituição atende? | E11: 921 | F11: =IF(D11="1 a 30",0,IF(D11="31 a 60",K11*0.25,IF(D11="61 a 100",K11*0.4,IF(D11="acima de 100",K11*0.6,0)))) -> 0 | G11: =HLOOKUP('General Information'!$C$6,'IDIOMA (hide)'!$A$1:$D$5016,I11,0) -> Faturamento | I11: 210 | J11: 1 a 30 padrão, 31 a 60 + 25%, 60 a 100 + 40%, acima de 100 + 60% | K11: =VLOOKUP(E11,'BASE_FUNCOES (hide)'!A:I,9,0) -> 40 | L11: =IF(D11="1 a 30","",IF(D11="31 a 60","Acrescido 25% de horas em virtude da instituição atender de 31 a 60 convênios.",IF(D11="61 a 100","Acrescido 40% de horas em virtude da instituição atender de 61 a 100 convênios.",IF(D11="acima de 100","Acrescido 60% de horas em virtude da instituição atender mais de 100 convênios.",""))))
A12: 48 | B12: 3 | C12: =HLOOKUP('General Information'!$C$6,'IDIOMA (hide)'!$A$1:$D$5016,A12,0) -> Possui processo de auditoria externa de contas? | E12: 1116 | F12: =IF(OR(D12="Sim",D12="Yes",D12="Si")=TRUE,K12*0.3,0) -> 0 | I12: 0 | J12: Caso a resposta seja Yes, +30% | K12: =VLOOKUP(E12,'BASE_FUNCOES (hide)'!A:I,9,0) -> 32 | L12: =IF(D12="Sim","Acrescido 30% de horas em virtude da instituição possuir processo de auditoria de contas externas.","")
A13: 55 | B13: 7 | C13: =HLOOKUP('General Information'!$C$6,'IDIOMA (hide)'!$A$1:$D$5016,A13,0) -> Quantas centrais de atendimentos/autorização existem? | E13: 3004 | F13: =IF(D13>1,(D13*(K13*0.4)),0) -> 0 | I13: 2 | J13: +40% por central. | K13: =VLOOKUP(E13,'BASE_FUNCOES (hide)'!A:I,9,0) -> 16 | L13: =IF(D13>0,CONCATENATE("Acrescido ",D13*40," % em virtude da instituição possuir ",D13," centrais de atendimento/autorização."),"")
A14: 432 | B14: 75 | C14: =HLOOKUP('General Information'!$C$6,'IDIOMA (hide)'!$A$1:$D$5016,A14,0) -> Não aplicável | E14: 7028 | F14: =IF(D14>5,20*(D14-5),0) -> 0 | I14: 0 | J14: Se for acima de 5, agregar 20 horas por Layout.
A15: 433 | B15: 76 | C15: =HLOOKUP('General Information'!$C$6,'IDIOMA (hide)'!$A$1:$D$5016,A15,0) -> Não aplicável | E15: 7028 | F15: =D15*K15 -> 0 | I15: Yes | J15: Contas agrupadas: 16 hrs por cada convenio que trabalha com envio de contas agrupadas | K15: 16
A16: 70 | B16: 15 | C16: =HLOOKUP('General Information'!$C$6,'IDIOMA (hide)'!$A$1:$D$5016,A16,0) -> É realizado atendimento para o SUS? | E16: 281 | F16: =IF(OR(D16="Sim",D16="Yes",D16="Si")=TRUE,K16,0) -> 0 | I16: Yes | J16: Resposta sendo Sim, adiciona 8 horas no prontuário eletronico | K16: 8
A17: 47 | B17: 2 | C17: =HLOOKUP('General Information'!$C$6,'IDIOMA (hide)'!$A$1:$D$5016,A17,0) -> Os setores de farmácia e almoxarifado utilizam o processo de requisição? | E17: 109 | F17: =IF(OR(D17="Yes",D17="Yes",D17="Yes")=TRUE,K17*0.5,0) -> 0 | G17: =HLOOKUP('General Information'!$C$6,'IDIOMA (hide)'!$A$1:$D$5016,I17,0) -> Suprimentos | I17: 209 | J17: Caso a resposta seja sim, +50% | K17: =VLOOKUP(E17,'BASE_FUNCOES (hide)'!A:I,9,0) -> 8 | L17: =IF(D17="Sim","Acrescido 50% de horas pois os setores de farmacia e/ou almoxarifado utilizam o processo de requisição","")
A18: 434 | B18: 77 | C18: =HLOOKUP('General Information'!$C$6,'IDIOMA (hide)'!$A$1:$D$5016,A18,0) -> Quantos Armazéns Centrais você possui na instituição? | E18: 919 | F18: =IF(D18>2,20*(D18-2),0) -> 0 | I18: 5 | J18: Se for mas 2 agregar 20 hrs por almacen
A19: 53 | B19: 5 | C19: =HLOOKUP('General Information'!$C$6,'IDIOMA (hide)'!$A$1:$D$5016,A19,0) -> Quantos setores utilizarão o atendimento do lote? | E19: 7029 | F19: =IF(D19>1,D19*(K19*0.25),0) -> 0 | J19: Opções, Farmacia e P.A, +25% para cada selecionada | K19: =VLOOKUP(E19,'BASE_FUNCOES (hide)'!A:I,9,0) -> 24 | L19: =IF(D19>0,CONCATENATE("Acrescido ",D19*25,"% de horas em virtude de ",D19," setores utilizarem atendimento lote."),"")
A20: 435 | B20: 78 | C20: =HLOOKUP('General Information'!$C$6,'IDIOMA (hide)'!$A$1:$D$5016,A20,0) -> Qual é a forma de gerenciamento de inventário (PEPS, UEPS, MÉDIA)? | E20: 919 | F20: =IF(D20<>0,K20,0) -> 0 | I20: 5 | J20: Inventarios: Adicionar 16 hrs para qualquer resposta | K20: 16
A21: 54 | B21: 6 | C21: =HLOOKUP('General Information'!$C$6,'IDIOMA (hide)'!$A$1:$D$5016,A21,0) -> Quantos setores utilizarão o processo de devolução de materiais do paciente? | E21: 42 | F21: =IF(D21>1,(D21*(K21*0.25)),0) -> 0 | I21: 1 | J21: Opções, Farmacia e P.A, +25% para cada selecionada | K21: =VLOOKUP(E21,'BASE_FUNCOES (hide)'!A:I,9,0) -> 8 | L21: =IF(D21>0,CONCATENATE("Acrescido ",D21*25,"% de horas em virtude da instiuição possuir ",D21," setores utilizarem atendimento lote."),"")
A22: 436 | B22: 79 | C22: =HLOOKUP('General Information'!$C$6,'IDIOMA (hide)'!$A$1:$D$5016,A22,0) -> Quantos pontos de venda de Farmácia Externa possui a instituição? | E22: 10015 | F22: =IF(D22>2,K22*(D22-2),0) -> 0 | I22: No | J22: Arriba de 2 puntos de venta, Agregar 20hr para cada punto de venta | K22: 20
A23: 51 | B23: 4 | C23: =HLOOKUP('General Information'!$C$6,'IDIOMA (hide)'!$A$1:$D$5016,A23,0) -> É realizado importação do extrato bancário? | E23: 814 | F23: =IF(OR(D23="Yes",D23="Yes",D23="Yes")=TRUE,(K23*0.4),0) -> 0 | G23: =HLOOKUP('General Information'!$C$6,'IDIOMA (hide)'!$A$1:$D$5016,I23,0) -> Financeiro | I23: 211 | J23: Caso a resposta seja Yes, +40% | K23: =VLOOKUP(E23,'BASE_FUNCOES (hide)'!A:I,9,0) -> 40 | L23: =IF(D23="Não","Reduzido 40% de horas pois a instituição não deseja realizar a importação de extrato bancário.","")
A24: 437 | B24: 80 | C24: =HLOOKUP('General Information'!$C$6,'IDIOMA (hide)'!$A$1:$D$5016,A24,0) -> Você gerencia moeda estrangeira (USD, EUR, ETC)? Em quais processos? | E24: 851 | F24: =IF(D24="Yes",K24,0) -> 0 | I24: No | J24: Moeda Estrangeira: Adicionar 8 hr para cada processo. (Exemplo: Tesouraria, Contas a Pagar, Contas a Cobrar, Notas Fiscais). | K24: 8
A25: 66 | B25: 12 | C25: =HLOOKUP('General Information'!$C$6,'IDIOMA (hide)'!$A$1:$D$5016,A25,0) -> É realizado a importação de extratos da operadora de cartão de crédito? | E25: 3020 | F25: =IF(OR(D25="Yes",D25="Yes",D25="Yes")=TRUE,K25,0) -> 0 | J25: Caso a resposta seja Yes, +100% | K25: =VLOOKUP(E25,'BASE_FUNCOES (hide)'!A:I,9,0) -> 16 | L25: =IF(D25="Sim","Acrescido 100% de horas em virtude da instituição realizar a importação de extratos de cartão de crédito","" )
A26: 438 | B26: 81 | C26: =HLOOKUP('General Information'!$C$6,'IDIOMA (hide)'!$A$1:$D$5016,A26,0) -> Quantos layouts de pagamentos eletrônicos você gerencia na instituição? | E26: 860 | F26: =D26*K26 -> 0 | I26: 1 | J26: Agregar 32 hrs para cada banco | K26: 32
A27: 67 | B27: 13 | C27: =HLOOKUP('General Information'!$C$6,'IDIOMA (hide)'!$A$1:$D$5016,A27,0) -> Quantos caixas existem em toda a instituição? | E27: 813 | F27: =IF(D27>10,K27*0.5,0) -> 0 | J27: Caso a resposta seja acima de 10, +50% | K27: =VLOOKUP(E27,'BASE_FUNCOES (hide)'!A:I,9,0) -> 24 | L27: =IF(D27>10,CONCATENATE("Acrescido 50% de horas em virtude da instituição possuir ",D27," caixas."),"")
A28: 65 | B28: 11 | C28: =HLOOKUP('General Information'!$C$6,'IDIOMA (hide)'!$A$1:$D$5016,A28,0) -> Quantos Terceiros possuem repasse de pagamento?Ex.: Medicos, clinicas, laboratorios, corpo clinico e etc. | E28: 92 | F28: =IF(D28="0 a 100",0,IF(D28="101 a 200",K28*0.2,IF(D28="201 a 300",K28*0.4,IF(D28="acima de 300",(K28*0.6),0)))) -> 0 | I28: 19 | J28: Opções: 0 a 100 +0%, 100 a 200 + 20%, 200 a 300 + 40%, acima de 300 + 60% | K28: =VLOOKUP(E28,'BASE_FUNCOES (hide)'!A:I,9,0) -> 24 | L28: =IF(D28="0 a 100","",IF(D28="101 a 200","Acrescido 20% de horas em virtude da instituição possuir de 101 a 200 terceiros para realização de repasse.",IF(D28="201 a 300","Acrescido 40% de horas em virtude da instituição possuir de 201 a 300 terceiros para realização de repasse.",IF(D28="acima de 300","Acrescido 60% de horas em virtude da instituição possuir mais de 300 terceiros para realização de repasse.",""))))
A29: 476 | B29: 98 | C29: =HLOOKUP('General Information'!$C$6,'IDIOMA (hide)'!$A$1:$D$5016,A29,0) -> Utilizará o processo de Contabilidade On Line? | E29: 7050 | F29: =IF(D29="Yes",K29,0) -> 0 | I29: Yes | J29: Acrescentar a função "parâmetro da conta contábil" mais 16 horas de e manter as demais horas das funções e valores do módulo contábil. | K29: 16
A30: 56 | B30: 8 | C30: =HLOOKUP('General Information'!$C$6,'IDIOMA (hide)'!$A$1:$D$5016,A30,0) -> Quantos setores utilizarão o processo de Ordem de Serviço? | E30: 297 | F30: =IF(D30>1,D30*(K30*0.5),0) -> 0 | G30: =HLOOKUP('General Information'!$C$6,'IDIOMA (hide)'!$A$1:$D$5016,I30,0) -> Apoio | I30: 208 | J30: Opções: TI, Manutenção Predial, Engenharia Clinica, +50% para cada selecionada. | K30: =VLOOKUP(E30,'BASE_FUNCOES (hide)'!A:I,9,0) -> 24 | L30: =IF(D30>0,CONCATENATE("Acrescido ",D30*50,"% de horas em virtude da intituição possuir ",D30," setores com automatização do processo de ordem de serviço"),"")
A31: 71 | B31: 16 | C31: =HLOOKUP('General Information'!$C$6,'IDIOMA (hide)'!$A$1:$D$5016,A31,0) -> Deseja implantar o processo de Privacy? Ex. GDPR/LGPD | E31: 3291 | F31: =IF(OR(D31="Yes",D31="Yes",D31="Yes")=TRUE,K31,"0") -> 0 | I31: Sim | J31: Resposta sendo Yes, adiciona 80 horas ao processo de Privacy | K31: 80
A32: 439 | B32: 17 | C32: =HLOOKUP('General Information'!$C$6,'IDIOMA (hide)'!$A$1:$D$5016,A32,0) -> O cliente deseja criar relatórios personalizados? Quantos | E32: 69 | F32: =IF(D32>1,(D32*K32),0) -> 0 | J32: Agregar 24 hrs por reporte | K32: 24 | L32: =IF(D32="1 a 30","",IF(D32="31 a 60","Acrescido 25% de horas em virtude da instituição atender de 31 a 60 convênios.",IF(D32="61 a 100","Acrescido 40% de horas em virtude da instituição atender de 61 a 100 convênios.",IF(D32="acima de 100","Acrescido 60% de horas em virtude da instituição atender mais de 100 convênios.",""))))
A33: 440 | B33: 91 | C33: =HLOOKUP('General Information'!$C$6,'IDIOMA (hide)'!$A$1:$D$5016,A33,0) -> Cliente quer construir indicadores para medir? Quantos | E33: 290 | F33: =IF(D33>1,(D33*K33),0) -> 0 | J33: Agregar 24 hrs por reporte | K33: 24 | L33: =IF(D33="1 a 30","",IF(D33="31 a 60","Acrescido 25% de horas em virtude da instituição atender de 31 a 60 convênios.",IF(D33="61 a 100","Acrescido 40% de horas em virtude da instituição atender de 61 a 100 convênios.",IF(D33="acima de 100","Acrescido 60% de horas em virtude da instituição atender mais de 100 convênios.",""))))
A34: 479 | B34: 99 | C34: =HLOOKUP('General Information'!$C$6,'IDIOMA (hide)'!$A$1:$D$5016,A34,0) -> Quantos convênios a instituição atende? | E34: 69 | F34: =IF(D34="1 a 30",0,IF(D34="31 a 60",K34*0.25,IF(D34="61 a 100",K34*0.4,IF(D34="Acima de 100",K34*0.6,0)))) -> 0 | J34: Opções: 1 a 30 padrão, 31 a 60 + 25%, 60 a 100 + 40%, acima de 100 + 60% | K34: =VLOOKUP(E34,'BASE_FUNCOES (hide)'!A:I,9,0) -> 24 | L34: =IF(D34="1 a 30","",IF(D34="31 a 60","Acrescido 25% de horas em virtude da instituição atender de 31 a 60 convênios.",IF(D34="61 a 100","Acrescido 40% de horas em virtude da instituição atender de 61 a 100 convênios.",IF(D34="acima de 100","Acrescido 60% de horas em virtude da instituição atender mais de 100 convênios.",""))))
A35: 479 | B35: 18 | C35: =HLOOKUP('General Information'!$C$6,'IDIOMA (hide)'!$A$1:$D$5016,A35,0) -> Quantos convênios a instituição atende? | E35: 27 | F35: =IF(D35="1 a 30",0,IF(D35="31 a 60",K35*0.25,IF(D35="61 a 100",K35*0.4,IF(D35="Acima de 100",K35*0.6,0)))) -> 0 | J35: Opções: 1 a 30 padrão, 31 a 60 + 25%, 61 a 100 + 40%, acima de 100 + 60% | K35: =VLOOKUP(E35,'BASE_FUNCOES (hide)'!A:I,9,0) -> 24 | L35: =IF(D35="1 a 30","",IF(D35="31 a 60","Acrescido 25% de horas em virtude da instituição atender de 31 a 60 convênios.",IF(D35="61 a 100","Acrescido 40% de horas em virtude da instituição atender de 61 a 100 convênios.",IF(D35="acima de 100","Acrescido 60% de horas em virtude da instituição atender mais de 100 convênios.",""))))
A36: 531 | B36: 114 | C36: O cliente utilizará o Planejamento Orçamentário? | E36: 8000 | F36: =IF(D36="Yes","Função Planejamento Orçamentário Adicionada",0) -> 0 | J36: N/A | K36: =VLOOKUP(E36,'BASE_FUNCOES (hide)'!A:I,9,0) -> 4 | L36: =IF(D36="1 a 30","",IF(D36="31 a 60","Acrescido 25% de horas em virtude da instituição atender de 31 a 60 convênios.",IF(D36="61 a 100","Acrescido 40% de horas em virtude da instituição atender de 61 a 100 convênios.",IF(D36="acima de 100","Acrescido 60% de horas em virtude da instituição atender mais de 100 convênios.",""))))
B38: OPERADORA (BRAZIL ONLY)
C39: 216 | D39: 217 | F39: 218
A40: 215 | B40: =HLOOKUP('General Information'!$C$6,'IDIOMA (hide)'!$A$1:$D$5016,A40,0) -> ID Pergunta | C40: =HLOOKUP('General Information'!$C$6,'IDIOMA (hide)'!$A$1:$D$5016,C39,0) -> Pergunta | D40: =HLOOKUP('General Information'!$C$6,'IDIOMA (hide)'!$A$1:$D$5016,D39,0) -> Resposta | E40: Id Função | F40: =HLOOKUP('General Information'!$C$6,'IDIOMA (hide)'!$A$1:$D$5016,F39,0) -> Horas Adicionais | G40: X | J40: Racional | K40: Horas Implantação | L40: Justificativa
A41: 517 | B41: 100 | C41: =HLOOKUP('General Information'!$C$6,'IDIOMA (hide)'!$A$1:$D$5016,A41,0) -> Utiliza o processo de compras diretas de OPME? | E41: ='BASE_FUNCOES (hide)'!A389 -> 267 | F41: =IF(D41="Yes","Funções Inclusas: Aprovações Pendentes, Solicitação de Compras, Cotação de Compras, Ordem de Compra",0) -> 0 | G41: =B38 -> OPERADORA (BRAZIL ONLY) | I41: cotação, ordem de compra, aprovação pendente, solicitação de compra | J41: Incluir funções: Aprovações Pendentes, Solicitação de Compras, Cotação de Compras, Ordem de Compra. Foi adicionada uma fórmula no "Hours Detail" especificamente nessas funções para: Se a pergunta é respondida como "Sim" então, lá deve ficar como sim, se não, pega a fórmula do escopo original, como estava antes. Ou seja, é possível o gestor ainda ir lá e retirar a função (o que não faria sentido). | K41: =VLOOKUP(E41,'BASE_FUNCOES (hide)'!A:I,9,0) -> 12 | L41: =IF(D41="1 a 30","",IF(D41="31 a 60","Acrescido 25% de horas em virtude da instituição atender de 31 a 60 convênios.",IF(D41="61 a 100","Acrescido 40% de horas em virtude da instituição atender de 61 a 100 convênios.",IF(D41="acima de 100","Acrescido 60% de horas em virtude da instituição atender mais de 100 convênios.",""))))
C42: Utiliza o processo de compras diretas de OPME? | E42: ='BASE_FUNCOES (hide)'!A398 -> 913 | F42: =IF(D42="Yes","Funções Inclusas: Aprovações Pendentes, Solicitação de Compras, Cotação de Compras, Ordem de Compra",0) -> 0 | J42: Incluir funções: Aprovações Pendentes, Solicitação de Compras, Cotação de Compras, Ordem de Compra. Foi adicionada uma fórmula no "Hours Detail" especificamente nessas funções para: Se a pergunta é respondida como "Sim" então, lá deve ficar como sim, se não, pega a fórmula do escopo original, como estava antes. Ou seja, é possível o gestor ainda ir lá e retirar a função (o que não faria sentido).
C43: Utiliza o processo de compras diretas de OPME? | E43: ='BASE_FUNCOES (hide)'!A397 -> 915 | F43: =IF(D43="Yes","Funções Inclusas: Aprovações Pendentes, Solicitação de Compras, Cotação de Compras, Ordem de Compra",0) -> 0 | J43: Incluir funções: Aprovações Pendentes, Solicitação de Compras, Cotação de Compras, Ordem de Compra. Foi adicionada uma fórmula no "Hours Detail" especificamente nessas funções para: Se a pergunta é respondida como "Sim" então, lá deve ficar como sim, se não, pega a fórmula do escopo original, como estava antes. Ou seja, é possível o gestor ainda ir lá e retirar a função (o que não faria sentido).
C44: Utiliza o processo de compras diretas de OPME? | E44: ='BASE_FUNCOES (hide)'!A396 -> 917 | F44: =IF(D44="Yes","Funções Inclusas: Aprovações Pendentes, Solicitação de Compras, Cotação de Compras, Ordem de Compra",0) -> 0 | J44: Incluir funções: Aprovações Pendentes, Solicitação de Compras, Cotação de Compras, Ordem de Compra. Foi adicionada uma fórmula no "Hours Detail" especificamente nessas funções para: Se a pergunta é respondida como "Sim" então, lá deve ficar como sim, se não, pega a fórmula do escopo original, como estava antes. Ou seja, é possível o gestor ainda ir lá e retirar a função (o que não faria sentido).
A45: 518 | B45: 101 | C45: =HLOOKUP('General Information'!$C$6,'IDIOMA (hide)'!$A$1:$D$5016,A45,0) -> Utiliza o processo de compras de materiais e medicamentos? | E45: =E41 -> 267 | F45: =IF(D45="Yes","Funções Inclusas: Aprovações Pendentes, Solicitação de Compras, Cotação de Compras, Ordem de Compra",0) -> 0 | I45: cotação, ordem de compra, aprovação pendente, solicitação de compra | J45: Incluir funções: Aprovações Pendentes, Solicitação de Compras, Cotação de Compras, Ordem de Compra. Foi adicionada uma fórmula no "Hours Detail" especificamente nessas funções para: Se a pergunta é respondida como "Sim" então, lá deve ficar como sim, se não, pega a fórmula do escopo original, como estava antes. Ou seja, é possível o gestor ainda ir lá e retirar a função (o que não faria sentido). | K45: =VLOOKUP(E45,'BASE_FUNCOES (hide)'!A:I,9,0) -> 12 | L45: =IF(D45="1 a 30","",IF(D45="31 a 60","Acrescido 25% de horas em virtude da instituição atender de 31 a 60 convênios.",IF(D45="61 a 100","Acrescido 40% de horas em virtude da instituição atender de 61 a 100 convênios.",IF(D45="acima de 100","Acrescido 60% de horas em virtude da instituição atender mais de 100 convênios.",""))))
C46: Utiliza o processo de compras de materiais e medicamentos? | E46: =E42 -> 913 | F46: =IF(D46="Yes","Funções Inclusas: Aprovações Pendentes, Solicitação de Compras, Cotação de Compras, Ordem de Compra",0) -> 0 | J46: Incluir funções: Aprovações Pendentes, Solicitação de Compras, Cotação de Compras, Ordem de Compra. Foi adicionada uma fórmula no "Hours Detail" especificamente nessas funções para: Se a pergunta é respondida como "Sim" então, lá deve ficar como sim, se não, pega a fórmula do escopo original, como estava antes. Ou seja, é possível o gestor ainda ir lá e retirar a função (o que não faria sentido).
C47: Utiliza o processo de compras de materiais e medicamentos? | E47: =E43 -> 915 | F47: =IF(D47="Yes","Funções Inclusas: Aprovações Pendentes, Solicitação de Compras, Cotação de Compras, Ordem de Compra",0) -> 0 | J47: Incluir funções: Aprovações Pendentes, Solicitação de Compras, Cotação de Compras, Ordem de Compra. Foi adicionada uma fórmula no "Hours Detail" especificamente nessas funções para: Se a pergunta é respondida como "Sim" então, lá deve ficar como sim, se não, pega a fórmula do escopo original, como estava antes. Ou seja, é possível o gestor ainda ir lá e retirar a função (o que não faria sentido).
C48: Utiliza o processo de compras de materiais e medicamentos? | E48: =E44 -> 917 | F48: =IF(D48="Yes","Funções Inclusas: Aprovações Pendentes, Solicitação de Compras, Cotação de Compras, Ordem de Compra",0) -> 0 | J48: Incluir funções: Aprovações Pendentes, Solicitação de Compras, Cotação de Compras, Ordem de Compra. Foi adicionada uma fórmula no "Hours Detail" especificamente nessas funções para: Se a pergunta é respondida como "Sim" então, lá deve ficar como sim, se não, pega a fórmula do escopo original, como estava antes. Ou seja, é possível o gestor ainda ir lá e retirar a função (o que não faria sentido).
A49: 519 | B49: 102 | C49: =HLOOKUP('General Information'!$C$6,'IDIOMA (hide)'!$A$1:$D$5016,A49,0) -> Utiliza o processo de controle de estoques? | E49: ='BASE_FUNCOES (hide)'!A319 -> 143 | F49: =IF(D49="Yes","Funções Inclusas: Administração de Estoque, Nota Fiscal, Requisição de Materiais e Medicamentos, Atendimento da Requisição.",0) -> 0 | I49: adm estoque, nota fiscal | J49: Incluir funções: Administração de Estoque, Nota Fiscal, Requisição de Materiais e Medicamentos, Atendimento da Requisição. Foi adicionada uma fórmula no "Hours Detail" especificamente nessas funções para: Se a pergunta é respondida como "Sim" então, lá deve ficar como sim, se não, pega a fórmula do escopo original, como estava antes. Ou seja, é possível o gestor ainda ir lá e retirar a função (o que não faria sentido). | K49: =VLOOKUP(E49,'BASE_FUNCOES (hide)'!A:I,9,0) -> 24 | L49: =IF(D49="1 a 30","",IF(D49="31 a 60","Acrescido 25% de horas em virtude da instituição atender de 31 a 60 convênios.",IF(D49="61 a 100","Acrescido 40% de horas em virtude da instituição atender de 61 a 100 convênios.",IF(D49="acima de 100","Acrescido 60% de horas em virtude da instituição atender mais de 100 convênios.",""))))
C50: Utiliza o processo de controle de estoques? | E50: ='BASE_FUNCOES (hide)'!A257 -> 40 | J50: Incluir funções: Administração de Estoque, Nota Fiscal, Requisição de Materiais e Medicamentos, Atendimento da Requisição. Foi adicionada uma fórmula no "Hours Detail" especificamente nessas funções para: Se a pergunta é respondida como "Sim" então, lá deve ficar como sim, se não, pega a fórmula do escopo original, como estava antes. Ou seja, é possível o gestor ainda ir lá e retirar a função (o que não faria sentido).
C51: Utiliza o processo de controle de estoques? | E51: ='BASE_FUNCOES (hide)'!A256 -> 919 | J51: Incluir funções: Administração de Estoque, Nota Fiscal, Requisição de Materiais e Medicamentos, Atendimento da Requisição. Foi adicionada uma fórmula no "Hours Detail" especificamente nessas funções para: Se a pergunta é respondida como "Sim" então, lá deve ficar como sim, se não, pega a fórmula do escopo original, como estava antes. Ou seja, é possível o gestor ainda ir lá e retirar a função (o que não faria sentido).
C52: Utiliza o processo de controle de estoques? | E52: ='BASE_FUNCOES (hide)'!A260 -> 109 | J52: Incluir funções: Administração de Estoque, Nota Fiscal, Requisição de Materiais e Medicamentos, Atendimento da Requisição. Foi adicionada uma fórmula no "Hours Detail" especificamente nessas funções para: Se a pergunta é respondida como "Sim" então, lá deve ficar como sim, se não, pega a fórmula do escopo original, como estava antes. Ou seja, é possível o gestor ainda ir lá e retirar a função (o que não faria sentido).
A53: 520 | B53: 103 | C53: =HLOOKUP('General Information'!$C$6,'IDIOMA (hide)'!$A$1:$D$5016,A53,0) -> Se utiliza o processo de qualidade? | E53: 4003 | F53: =IF(D53="Yes","Funções Inclusas: Incluir funções: Consulta da Qualidade, Gestão da Qualidade",0) -> 0 | J53: Incluir funções: Administração de Estoque, Nota Fiscal, Requisição de Materiais e Medicamentos, Atendimento da Requisição. Foi adicionada uma fórmula no "Hours Detail" especificamente nessas funções para: Se a pergunta é respondida como "Sim" então, lá deve ficar como sim, se não, pega a fórmula do escopo original, como estava antes. Ou seja, é possível o gestor ainda ir lá e retirar a função (o que não faria sentido). | K53: =VLOOKUP(E53,'BASE_FUNCOES (hide)'!A:I,9,0) -> 0 | L53: =IF(D53="1 a 30","",IF(D53="31 a 60","Acrescido 25% de horas em virtude da instituição atender de 31 a 60 convênios.",IF(D53="61 a 100","Acrescido 40% de horas em virtude da instituição atender de 61 a 100 convênios.",IF(D53="acima de 100","Acrescido 60% de horas em virtude da instituição atender mais de 100 convênios.",""))))
C54: Se utiliza o processo de qualidade? | E54: 4000 | F54: =IF(D54="Yes","Funções Inclusas: Incluir funções: Consulta da Qualidade, Gestão da Qualidade",0) -> 0
A55: 521 | B55: 104 | C55: =HLOOKUP('General Information'!$C$6,'IDIOMA (hide)'!$A$1:$D$5016,A55,0) -> Se utiliza o processo de painel de chamadas? | E55: 10021 | F55: =IF(D55="Yes","Funções Inclusas: Gerenciamento de Senhas",0) -> 0 | J55: Incluir função gerenciamento de senhas Foi adicionada uma fórmula no "Hours Detail" especificamente nessas funções para: Se a pergunta é respondida como "Sim" então, lá deve ficar como sim, se não, pega a fórmula do escopo original, como estava antes. Ou seja, é possível o gestor ainda ir lá e retirar a função (o que não faria sentido).
A56: 522 | B56: 105 | C56: =HLOOKUP('General Information'!$C$6,'IDIOMA (hide)'!$A$1:$D$5016,A56,0) -> Utiliza o processo de Auditoria Concorrente? | E56: ='BASE_FUNCOES (hide)'!A691 -> 1397 | F56: =IF(D56="Yes","Função já é padrão em qualquer modalidade","") | K56: =VLOOKUP(E56,'BASE_FUNCOES (hide)'!A:I,9,0) -> 56 | L56: =IF(D56="1 a 30","",IF(D56="31 a 60","Acrescido 25% de horas em virtude da instituição atender de 31 a 60 convênios.",IF(D56="61 a 100","Acrescido 40% de horas em virtude da instituição atender de 61 a 100 convênios.",IF(D56="acima de 100","Acrescido 60% de horas em virtude da instituição atender mais de 100 convênios.",""))))
A57: 523 | B57: 106 | C57: =HLOOKUP('General Information'!$C$6,'IDIOMA (hide)'!$A$1:$D$5016,A57,0) -> O cliente já possui recurso próprio ou hospital com Tasy? | E57: 281 | F57: =IF(D57="Yes","Funções Inclusas: Prontuário, Call Center e Entrada Única",0) -> 0 | J57: Se não, adicionar prontuário, call center e entrada única. Foi adicionada uma fórmula no "Hours Detail" especificamente nessas funções para: Se a pergunta é respondida como "Sim" então, lá deve ficar como sim, se não, pega a fórmula do escopo original, como estava antes. Ou seja, é possível o gestor ainda ir lá e retirar a função (o que não faria sentido).
A58: 524 | B58: 107 | C58: =HLOOKUP('General Information'!$C$6,'IDIOMA (hide)'!$A$1:$D$5016,A58,0) -> Haverá acompanhamento do monitoramento ANS? | E58: ='Hours Detail'!E15 -> 010 | F58: =IF(D58="Yes",40,0) -> 0 | J58: (acrescer 40 horas), normalmente o envio do primeiro monitoramento ocorre 2 meses após a virada. | K58: =VLOOKUP(E58,'BASE_FUNCOES (hide)'!A:I,9,0) -> #N/A | L58: =IF(D58="1 a 30","",IF(D58="31 a 60","Acrescido 25% de horas em virtude da instituição atender de 31 a 60 convênios.",IF(D58="61 a 100","Acrescido 40% de horas em virtude da instituição atender de 61 a 100 convênios.",IF(D58="acima de 100","Acrescido 60% de horas em virtude da instituição atender mais de 100 convênios.",""))))
A59: 525 | B59: 108 | C59: =HLOOKUP('General Information'!$C$6,'IDIOMA (hide)'!$A$1:$D$5016,A59,0) -> Haverá acompanhamento para o SIP? | E59: 010 | F59: =IF(D59="Yes",40,0) -> 0 | J59: (acrescer 40 horas), normalmente o envio do primeiro SIP ocorre 4 meses após a virada. | K59: =VLOOKUP(E59,'BASE_FUNCOES (hide)'!A:I,9,0) -> #N/A | L59: =IF(D59="1 a 30","",IF(D59="31 a 60","Acrescido 25% de horas em virtude da instituição atender de 31 a 60 convênios.",IF(D59="61 a 100","Acrescido 40% de horas em virtude da instituição atender de 61 a 100 convênios.",IF(D59="acima de 100","Acrescido 60% de horas em virtude da instituição atender mais de 100 convênios.",""))))
A60: 526 | B60: 109 | C60: =HLOOKUP('General Information'!$C$6,'IDIOMA (hide)'!$A$1:$D$5016,A60,0) -> Haverá acompanhamento para o DIOPS e geração livros auxiliares para auditoria? | E60: 010 | F60: =IF(D60="Yes",40,0) -> 0 | J60: (acrescer 80 horas), normalmente o envio do primeiro DIOPS ocorre 4 meses após a virada. | K60: =VLOOKUP(E60,'BASE_FUNCOES (hide)'!A:I,9,0) -> #N/A | L60: =IF(D60="1 a 30","",IF(D60="31 a 60","Acrescido 25% de horas em virtude da instituição atender de 31 a 60 convênios.",IF(D60="61 a 100","Acrescido 40% de horas em virtude da instituição atender de 61 a 100 convênios.",IF(D60="acima de 100","Acrescido 60% de horas em virtude da instituição atender mais de 100 convênios.",""))))
A61: 527 | B61: 110 | C61: =HLOOKUP('General Information'!$C$6,'IDIOMA (hide)'!$A$1:$D$5016,A61,0) -> Quantidade de prestadores? | E61: 1203 | F61: =IF(D61="De 1000 até 1999",K61*10%,IF(D61="2000 até 3999",K61*20%,IF(D61="4000 até 5999",K61*30%,IF(D61="Acima de 6000.",K61*40%,0)))) -> 0 | J61: (aumentar 10% das horas dos módulos prestadores, contas médicas e autorizações a cada 2000) Só na função OPS Prestadores. Aumentar 10% das horas aqui. Pra cada 2000 prestadores, 10% a mais. Na função glosas e ocorrências. Aumentar 10% a cada 2000. | K61: =VLOOKUP(E61,'BASE_FUNCOES (hide)'!A:I,9,0) -> 40 | L61: =IF(D61="1 a 30","",IF(D61="31 a 60","Acrescido 25% de horas em virtude da instituição atender de 31 a 60 convênios.",IF(D61="61 a 100","Acrescido 40% de horas em virtude da instituição atender de 61 a 100 convênios.",IF(D61="acima de 100","Acrescido 60% de horas em virtude da instituição atender mais de 100 convênios.",""))))
A62: 526 | E62: 1306 | F62: =IF(D62="De 1000 até 1999",K62*10%,IF(D62="2000 até 3999",K62*20%,IF(D62="4000 até 5999",K62*30%,IF(D62="Acima de 6000.",K62*40%,0)))) -> 0 | J62: (aumentar 10% das horas dos módulos prestadores, contas médicas e autorizações a cada 2000) Só na função OPS Prestadores. Aumentar 10% das horas aqui. Pra cada 2000 prestadores, 10% a mais. Na função glosas e ocorrências. Aumentar 10% a cada 2000. | K62: =VLOOKUP(E62,'BASE_FUNCOES (hide)'!A:I,9,0) -> 40
A63: 528 | B63: 111 | C63: =HLOOKUP('General Information'!$C$6,'IDIOMA (hide)'!$A$1:$D$5016,A63,0) -> Quantidade de locais de atendimento presenciais? | E63: 1274 | F63: =IF(D63>1,(K63*40%)*D63,0) -> 0 | J63: (aumentar 40% das horas dos módulos call center e senhas a cada local excedente de 1) | K63: =VLOOKUP(E63,'BASE_FUNCOES (hide)'!A:I,9,0) -> 24 | L63: =IF(D63="1 a 30","",IF(D63="31 a 60","Acrescido 25% de horas em virtude da instituição atender de 31 a 60 convênios.",IF(D63="61 a 100","Acrescido 40% de horas em virtude da instituição atender de 61 a 100 convênios.",IF(D63="acima de 100","Acrescido 60% de horas em virtude da instituição atender mais de 100 convênios.",""))))
A64: 529 | B64: 112 | C64: =HLOOKUP('General Information'!$C$6,'IDIOMA (hide)'!$A$1:$D$5016,A64,0) -> Quantidade de bancos que importam extrato no controle bancário? | E64: 814 | F64: =IF(D64="Yes",(K64*40%),0) -> 0 | J64: Caso a resposta seja Yes, +40% | K64: =VLOOKUP(E64,'BASE_FUNCOES (hide)'!A:I,9,0) -> 40 | L64: =IF(D64="1 a 30","",IF(D64="31 a 60","Acrescido 25% de horas em virtude da instituição atender de 31 a 60 convênios.",IF(D64="61 a 100","Acrescido 40% de horas em virtude da instituição atender de 61 a 100 convênios.",IF(D64="acima de 100","Acrescido 60% de horas em virtude da instituição atender mais de 100 convênios.",""))))
A65: 530 | B65: 113 | C65: =HLOOKUP('General Information'!$C$6,'IDIOMA (hide)'!$A$1:$D$5016,A65,0) -> Quantidade de bancos que geram cobrança escritural? | E65: 815 | F65: =IF(D65>1,(K65*20%)*D65,0) -> 0 | J65: (aumentar 20% das horas da cobrança escritural a cada banco adicional) | K65: =VLOOKUP(E65,'BASE_FUNCOES (hide)'!A:I,9,0) -> 24 | L65: =IF(D65="1 a 30","",IF(D65="31 a 60","Acrescido 25% de horas em virtude da instituição atender de 31 a 60 convênios.",IF(D65="61 a 100","Acrescido 40% de horas em virtude da instituição atender de 61 a 100 convênios.",IF(D65="acima de 100","Acrescido 60% de horas em virtude da instituição atender mais de 100 convênios.",""))))
A69: 205 | B69: =HLOOKUP('General Information'!$C$6,'IDIOMA (hide)'!$A$1:$D$5016,A69,0) -> Assistencial
B71: =HLOOKUP('General Information'!$C$6,'IDIOMA (hide)'!$A$1:$D$5016,B4,0) -> ID Pergunta | C71: =HLOOKUP('General Information'!$C$6,'IDIOMA (hide)'!$A$1:$D$5016,C4,0) -> Pergunta | D71: =HLOOKUP('General Information'!$C$6,'IDIOMA (hide)'!$A$1:$D$5016,D4,0) -> Resposta | E71: Id Função | F71: =HLOOKUP('General Information'!$C$6,'IDIOMA (hide)'!$A$1:$D$5016,F4,0) -> Horas Adicionais
A72: 69 | B72: 28 | C72: =HLOOKUP('General Information'!$C$6,'IDIOMA (hide)'!$A$1:$D$5016,A72,0) -> É realizado serviços de oncologia? | E72: 281 | F72: =IF(OR(D72="Sim",D72="Yes",D72="Si")=TRUE,K72,0) -> 0 | G72: =HLOOKUP('General Information'!$C$6,'IDIOMA (hide)'!$A$1:$D$5016,I72,0) -> Prontuario / Mentor | I72: 272 | J72: Resposta sendo Yes, adiciona 32 horas no prontuário eletronico | K72: 32
A73: 74 | B73: 31 | C73: =HLOOKUP('General Information'!$C$6,'IDIOMA (hide)'!$A$1:$D$5016,A73,0) -> Deseja implantar o item de Prontuário Oftalmologia? | E73: 281 | F73: =IF(OR(D73="Sim",D73="Yes",D73="Si")=TRUE,K73,0) -> 0 | J73: Resposta sendo Yes, adicionado 40 hrs na função Prontuário Eletrônico Paciente | K73: 40
A74: 72 | B74: 29 | C74: =HLOOKUP('General Information'!$C$6,'IDIOMA (hide)'!$A$1:$D$5016,A74,0) -> Instituição utiliza Protocolo de Sepse Ilas II? | E74: 354 | F74: =IF(OR(D74="Sim",D74="Yes",D74="Si")=TRUE,K74,0) -> 0 | J74: Resposta sendo Yes, adicionado 40 hrs na função Suporte a Decisão Clinica | K74: 40
A75: 342 | B75: 73 | C75: =HLOOKUP('General Information'!$C$6,'IDIOMA (hide)'!$A$1:$D$5016,A75,0) -> A função Gestão dos Planos Terapêuticos - GPT - será utilizada em qual setor ? | E75: 252 | F75: =IF(OR(D75="Enfermagem e Farmácia",D75="Nursing and Pharmacy",D75="Enfermería y Farmacia")=TRUE,K75*1,0) -> 0 | J75: Resposta sendo Enfermagem e Farmácia adicionar + 100% | K75: =VLOOKUP(E75,'BASE_FUNCOES (hide)'!A:I,9,0) -> 32
A76: 343 | B76: 60 | C76: =HLOOKUP('General Information'!$C$6,'IDIOMA (hide)'!$A$1:$D$5016,A76,0) -> Quantos consultórios ambulatoriais? | E76: 28122 | F76: =IF(D76="1 a 10",0,IF(D76="11 a 30",K76*0.25,IF(D76="31 a 50",K76*0.5,IF(D76="51 a 100",K76*0.75,IF(D76="acima de 100",K76*1,0))))) -> 0 | J76: 1 a 10 padrão, 11 a 30 + 25%, 31 a 50 + 50%, 51 a 100 + 75%, acima de 100 = 100% | K76: =VLOOKUP(E76,'BASE_FUNCOES (hide)'!A:I,9,0) -> 80
A77: 73 | B77: 30 | C77: =HLOOKUP('General Information'!$C$6,'IDIOMA (hide)'!$A$1:$D$5016,A77,0) -> O cliente deseja medir os indicadores de qualidade do protocolo de Sepse? | E77: 275 | F77: =CONCATENATE("Detalhe de horas GQA: ",VLOOKUP(E77,'Hours Detail'!E:H,4,FALSE)) -> Detalhe de horas GQA: No | I77: =IF((D77="Sim")*AND(VLOOKUP(E77,'Hours Detail'!E:H,4,FALSE)="Não"),"Para medir os indicadores de Qualidade do protocolo Sepse, é necessária a implantação da função Gestão de Qualidade Assistencial GQA. É necessário adicionar ao escopo a função GQA na aba Detalhe de horas","") | J77: Orientação para o Vendedor incluir a função GQA no detalhe de horas
A78: 344 | B78: 61 | C78: =HLOOKUP('General Information'!$C$6,'IDIOMA (hide)'!$A$1:$D$5016,A78,0) -> Deseja implantar certificação digital para o Prontuário Eletrônico Paciente? | E78: 28188 | F78: =CONCATENATE("Detalhe de horas Certificação Digital: ",VLOOKUP(E78,'Hours Detail'!E:H,4,FALSE)) -> Detalhe de horas Certificação Digital: No | I78: =IF((D78="Sim")*AND('Hours Detail'!H255="Não"),"Para a implantação do Certificação Digital. É necessário adicionar ao escopo a função Certificado Digital na aba Detalhe de horas","") | J78: Orientação para o Vendedor incluir a certificação digital do detalhe de horas
A79: 473 | B79: 92 | C79: =HLOOKUP('General Information'!$C$6,'IDIOMA (hide)'!$A$1:$D$5016,A79,0) -> Em relação ao Care Plan, o cliente irá criar o seu plano de cuidado e cadastrar no Tasy, ou integrará com a Elevier? | E79: 99023 | F79: =IF(D79="Elsevier",K79,IF(D79="Tasy",8,0)) -> 0 | J79: Se for direto no Tasy são +8 para Cadastros PEP e se for com Elsevier, são + 40 | K79: 40
A80: 474 | B80: 93 | C80: =HLOOKUP('General Information'!$C$6,'IDIOMA (hide)'!$A$1:$D$5016,A80,0) -> Será utilizado o TNM? | E80: 3131 | F80: =IF(D80="Yes",K80,0) -> 0 | J80: Quando utilizar o TNM adicionar 40 horas em Registro Hospitalar do Cancer | K80: 40
A81: 478 | B81: 97 | C81: =HLOOKUP('General Information'!$C$6,'IDIOMA (hide)'!$A$1:$D$5016,A81,0) -> Será utilizado o Neocenter? | E81: 2314 | F81: =IF(D81="Yes",K81,0) -> 0 | J81: Se utilizar o Neo Center, adicionar 40 horasn a CPOE. | K81: 40
B82: 94 | C82: =C80 -> Será utilizado o TNM? | E82: 281 | F82: =IF(D80="Yes",K80,0) -> 0 | J82: E itens oncológicos do PEP | K82: 40
A83: 475 | B83: 95 | C83: =HLOOKUP('General Information'!$C$6,'IDIOMA (hide)'!$A$1:$D$5016,A83,0) -> O cliente utilizará Jornada do Paciente? | E83: 2811 | F83: =IF(D83="Yes",K83,0) -> 0 | J83: 40 horas se implementar jornada do paciente ( SUEP e protocolos clínicos) e cadastros relacionados | K83: 40
C84: Plano de implantação: Cronogramas de implantação revisados –24 horas para implementação, sendo:ADM TASY -3horasCadastros Gerais -1 horaNova função "Painel do Panorama Clínico" -20 horasInformações comerciais: Base de demonstração do Pré Vendas atualizada e disponível para demonstrações. LTEP de Vendas e Pós Vendas atualizado. Nenhuma alteração na Política e Proposta Comercial. | E84: 6001 | F84: 3
A87: 488 | C87: =HLOOKUP('General Information'!$C$6,'IDIOMA (hide)'!$A$1:$D$5016,A87,0) -> PEP / CPOE / ADEP | F87: =HLOOKUP('General Information'!$C$6,'IDIOMA (hide)'!$A$1:$D$5016,F4,0) -> Horas Adicionais
A88: 329 | B88: =HLOOKUP('General Information'!$C$6,'IDIOMA (hide)'!$A$1:$D$5016,A88,0) -> Quais são os tipos de serviços existentes na instituição?
A89: 333 | B89: 62 | C89: =HLOOKUP('General Information'!$C$6,'IDIOMA (hide)'!$A$1:$D$5016,A89,0) -> UTI | F89: =IF(D89="Yes",0.3,0) -> 0
A90: 334 | B90: 63 | C90: =HLOOKUP('General Information'!$C$6,'IDIOMA (hide)'!$A$1:$D$5016,A90,0) -> Internação | F90: =IF(D90="Yes",0.3,0) -> 0
A91: 335 | B91: 64 | C91: =HLOOKUP('General Information'!$C$6,'IDIOMA (hide)'!$A$1:$D$5016,A91,0) -> Centro Cirurgico | F91: =IF(D91="Yes",0.2,0) -> 0
A92: 336 | B92: 65 | C92: =HLOOKUP('General Information'!$C$6,'IDIOMA (hide)'!$A$1:$D$5016,A92,0) -> Pronto Atendimento | F92: =IF(D92="Yes",0.2,0) -> 0
A93: 337 | B93: 66 | C93: =HLOOKUP('General Information'!$C$6,'IDIOMA (hide)'!$A$1:$D$5016,A93,0) -> Oncologia | F93: =IF(D93="Yes",0.15,0) -> 0
A94: 338 | B94: 67 | C94: =HLOOKUP('General Information'!$C$6,'IDIOMA (hide)'!$A$1:$D$5016,A94,0) -> Hemodiálises | F94: =IF(D94="Yes",0.1,0) -> 0
A95: 339 | B95: 68 | C95: =HLOOKUP('General Information'!$C$6,'IDIOMA (hide)'!$A$1:$D$5016,A95,0) -> Exames de Imagem | F95: =IF(D95="Yes",0.1,0) -> 0
A96: 340 | B96: 69 | C96: =HLOOKUP('General Information'!$C$6,'IDIOMA (hide)'!$A$1:$D$5016,A96,0) -> Outros (nutrição, banco de sangue, etc.) | F96: =IF(D96="Yes",0.15,0) -> 0
A97: 330 | B97: 70 | C97: =HLOOKUP('General Information'!$C$6,'IDIOMA (hide)'!$A$1:$D$5016,A97,0) -> Prontuário Eletrônico Paciente - PEP | D97: Horas / Hours | E97: 281 | F97: =SUM(F89:F96)*K97 -> 0 | J97: Acréscimo de horas de acordo com os serviços existentes na instituição | K97: =VLOOKUP(E97,'BASE_FUNCOES (hide)'!A:I,9,0) -> 120
A98: 332 | B98: 71 | C98: =HLOOKUP('General Information'!$C$6,'IDIOMA (hide)'!$A$1:$D$5016,A98,0) -> CPOE | D98: Horas / Hours | E98: 2314 | F98: =SUM(F89:F96)*K98 -> 0 | J98: Acréscimo de horas de acordo com os serviços existentes na instituição | K98: =VLOOKUP(E98,'BASE_FUNCOES (hide)'!A:I,9,0) -> 160
A99: 331 | B99: 72 | C99: =HLOOKUP('General Information'!$C$6,'IDIOMA (hide)'!$A$1:$D$5016,A99,0) -> Adm. Eletrônica da Prescrição - ADEP | D99: Horas / Hours | E99: 1113 | F99: =SUM(F89:F96)*K99 -> 0 | J99: Acréscimo de horas de acordo com os serviços existentes na instituição | K99: =VLOOKUP(E99,'BASE_FUNCOES (hide)'!A:I,9,0) -> 40
F100: =HLOOKUP('General Information'!$C$6,'IDIOMA (hide)'!$A$1:$D$5016,F4,0) -> Horas Adicionais | I100: 347
A101: 59 | B101: 24 | C101: =HLOOKUP('General Information'!$C$6,'IDIOMA (hide)'!$A$1:$D$5016,A101,0) -> Possui P.A com processos diferentes? Ex: P.A Adulto e P.A Infantil. Caso possua, quantos são? | E101: 935 | F101: =D101*(K101*0.3) -> 0 | G101: P.A | J101: +30% por processo. | K101: =VLOOKUP(E101,'BASE_FUNCOES (hide)'!A:I,9,0) -> 40 | L101: =IF(D101>0,CONCATENATE("Acrescido ",D101*30,"% de horas em virtude da instituição possuir B32'mais de um P.A com processos diferentes."),"")
A102: 165 | B102: 33 | C102: =HLOOKUP('General Information'!$C$6,'IDIOMA (hide)'!$A$1:$D$5016,A102,0) -> Cliente deseja implantar Protocolo de Manchester (somente versão 2.0)? | F102: =IF(D102="Yes",HLOOKUP('General Information'!$C$6,'IDIOMA (hide)'!$A$1:$D$5016,G114,0),"") | I102: =IF(D102="Yes",HLOOKUP('General Information'!$C$6,'IDIOMA (hide)'!$A$1:$D$5016,I100,0),"") | J102: Orientação para o Vendedor
A103: 49 | B103: 19 | C103: =HLOOKUP('General Information'!$C$6,'IDIOMA (hide)'!$A$1:$D$5016,A103,0) -> Existe Banco de Sangue ou agencia transfuncional? | E103: 450 | F103: =IF(OR(D103="Banco de Sangue",D103="Blood Bank",D103="Banco de Sangre")=TRUE,K103*1,0) -> 0 | G103: =HLOOKUP('General Information'!$C$6,'IDIOMA (hide)'!$A$1:$D$5016,H103,0) -> Apoio | H103: 208 | J103: Caso a opção banco de sangue seja selecionada, +100% | K103: =VLOOKUP(E103,'BASE_FUNCOES (hide)'!A:I,9,0) -> 24 | L103: =IF(D103="Sim","Acrescido 100% de horas em virtude da instituição possuir Banco de Sangue.","")
A104: 50 | B104: 20 | C104: =HLOOKUP('General Information'!$C$6,'IDIOMA (hide)'!$A$1:$D$5016,A104,0) -> Possui centro obstétrico? | E104: 900 | F104: =IF(OR(D104="Yes",D104="Yes",D104="Yes")=TRUE,K104*0.3,0) -> 0 | J104: Caso a resposta seja sim, +30% | K104: =VLOOKUP(E104,'BASE_FUNCOES (hide)'!A:I,9,0) -> 24 | L104: =IF(D104="Sim","Acrescido 30% de horas em virtude da instituição possuir centro obstétrico","")
A105: 164 | B105: 32 | C105: =HLOOKUP('General Information'!$C$6,'IDIOMA (hide)'!$A$1:$D$5016,A105,0) -> Possui processo de diálise externa? | E105: 7009 | F105: =IF(OR(D105="Yes",D105="Yes",D105="Yes")=TRUE,K105,0) -> 0 | J105: Resposta sendo Sim, adicionado 20 hrs na função Gestão de Insuficiência Renal | K105: 20
A106: 57 | B106: 22 | C106: =HLOOKUP('General Information'!$C$6,'IDIOMA (hide)'!$A$1:$D$5016,A106,0) -> Controla ou pretende controlar o processo de produção de refeição? | E106: 1003 | F106: =IF(OR(D106="Yes",D106="Yes",D106="Yes")=TRUE,K106,0) -> 0 | J106: Caso a resposta seja sim, +100% | K106: =VLOOKUP(E106,'BASE_FUNCOES (hide)'!A:I,9,0) -> 40 | L106: =IF(D106="Sim","Acrescido 100% de horas em virtude da instituição controlar o processo de processo de produção de refeição","")
A107: 61 | B107: 26 | C107: =HLOOKUP('General Information'!$C$6,'IDIOMA (hide)'!$A$1:$D$5016,A107,0) -> Possui algumas certificação?Ex: ISO,JCI,ONA, HIMSS | E107: 4000 | F107: =IF(OR(D107="Yes",D107="Yes",D107="Yes")=TRUE,K107,0) -> 0 | J107: Opções: ISO, JCI, ONA, Outras, Qual?, +100% | K107: =VLOOKUP(E107,'BASE_FUNCOES (hide)'!A:I,9,0) -> 40 | L107: =IF(D107="Sim","Acrescido 100% de horas em virtude da instiuição possuir ou ter interesse em possuir certificações com JCI, ONA, ISO e etc.","")
...

Sheet Hours Detail
A1: 2 | B1: =HLOOKUP('General Information'!$C$6,'IDIOMA (hide)'!$A$1:$D$5016,A1,0) -> LTEP - Levantamento Técnico de Estimativa de Projeto TASY EMR Código do documento: 0060 - Rev 024
B2: 197 | H2: 189
B3: =HLOOKUP('General Information'!$C$6,'IDIOMA (hide)'!$A$1:$D$5016,B2,0) -> Detalhamento de Horas | H3: 190
H4: =HLOOKUP('General Information'!$C$6,'IDIOMA (hide)'!$A$1:$D$5016,H2,0) -> Alterações manuais do escopo serão destacadas em vermelho.
B5: 184 | D5: 185 | E5: 186 | F5: 187 | G5: 188 | I5: 191 | J5: 192 | K5: 193 | L5: 194 | M5: 195 | N5: 196
B6: =HLOOKUP('General Information'!$C$6,'IDIOMA (hide)'!$A$1:$D$5016,B5,0) -> ID MODULE | C6: Produto | D6: =HLOOKUP('General Information'!$C$6,'IDIOMA (hide)'!$A$1:$D$5016,D5,0) -> MODULE | E6: =HLOOKUP('General Information'!$C$6,'IDIOMA (hide)'!$A$1:$D$5016,E5,0) -> ID FUNCTION | F6: =HLOOKUP('General Information'!$C$6,'IDIOMA (hide)'!$A$1:$D$5016,F5,0) -> DESCRIPTION FUNCTION | G6: =HLOOKUP('General Information'!$C$6,'IDIOMA (hide)'!$A$1:$D$5016,G5,0) -> Escopo Original | H6: =HLOOKUP('General Information'!$C$6,'IDIOMA (hide)'!$A$1:$D$5016,H3,0) -> SCOPE | I6: =HLOOKUP('General Information'!$C$6,'IDIOMA (hide)'!$A$1:$D$5016,I5,0) -> HOURS STANDARD IMPLANTATION | J6: =HLOOKUP('General Information'!$C$6,'IDIOMA (hide)'!$A$1:$D$5016,J5,0) -> ADDITIONAL HOURS (QUESTIONS) | K6: =HLOOKUP('General Information'!$C$6,'IDIOMA (hide)'!$A$1:$D$5016,K5,0) -> TOTAL HOURS (STANDARD HOURS + ADDITIONAL HOURS) | L6: =HLOOKUP('General Information'!$C$6,'IDIOMA (hide)'!$A$1:$D$5016,L5,0) -> VARIABLE HOURS JUSTIFICATION | M6: =HLOOKUP('General Information'!$C$6,'IDIOMA (hide)'!$A$1:$D$5016,M5,0) -> PHASE | N6: =HLOOKUP('General Information'!$C$6,'IDIOMA (hide)'!$A$1:$D$5016,N5,0) -> Deployment Wave
A7: 166 | D7: =HLOOKUP('General Information'!$C$6,'IDIOMA (hide)'!$A$1:$D$5016,A7,0) -> Inicialização | F7: =HLOOKUP('General Information'!$C$6,'IDIOMA (hide)'!$A$1:$D$5016,O7,0) -> Lançamento de Projetos | G7: Yes | H7: =G7 -> Yes | I7: =Questions!D145*Questions!D147 -> 8 | K7: =IF(H7="Yes",ROUNDUP((I7*J7)+I7,0),0) -> 8 | L7: =IF(ISERROR(VLOOKUP(E7,Questions!$E$5:$L$568,6,0))=FALSE,VLOOKUP(E7,Questions!$E$5:$L$568,6,0),"") | M7: Fase: Lançamento do Projeto | N7: 1ª Onda | O7: 175
A8: 167 | D8: =HLOOKUP('General Information'!$C$6,'IDIOMA (hide)'!$A$1:$D$5016,A8,0) -> Instalação | F8: =HLOOKUP('General Information'!$C$6,'IDIOMA (hide)'!$A$1:$D$5016,O8,0) -> Validação da Instalação do Produto | G8: Yes | H8: =G8 -> Yes | I8: =Questions!D148 -> 8 | K8: =IF(H8="Yes",ROUNDUP((I8*J8)+I8,0),0) -> 8 | L8: =IF(ISERROR(VLOOKUP(E8,Questions!$E$5:$L$568,6,0))=FALSE,VLOOKUP(E8,Questions!$E$5:$L$568,6,0),"") | M8: Fase: Instalação | N8: 1ª Onda | O8: 176
A9: 168 | D9: =HLOOKUP('General Information'!$C$6,'IDIOMA (hide)'!$A$1:$D$5016,A9,0) -> Go Live | F9: =HLOOKUP('General Information'!$C$6,'IDIOMA (hide)'!$A$1:$D$5016,O9,0) -> Teste Piloto | G9: Yes | H9: =G9 -> Yes | I9: =Questions!D149*Questions!D145 -> 40 | K9: =IF(H9="Yes",ROUNDUP((I9*J9)+I9,0),0) -> 40 | L9: =IF(ISERROR(VLOOKUP(E9,Questions!$E$5:$L$568,6,0))=FALSE,VLOOKUP(E9,Questions!$E$5:$L$568,6,0),"") | M9: Fase: Liberação e Acompanhamento | N9: 1ª Onda | O9: 177
A10: 169 | D10: =HLOOKUP('General Information'!$C$6,'IDIOMA (hide)'!$A$1:$D$5016,A10,0) -> Go Live | F10: =HLOOKUP('General Information'!$C$6,'IDIOMA (hide)'!$A$1:$D$5016,O10,0) -> Processo de Virada | G10: Yes | H10: =G10 -> Yes | I10: =Questions!D145*Questions!D150 -> 16 | K10: =IF(H10="Yes",ROUNDUP((I10*J10)+I10,0),0) -> 16 | L10: =IF(ISERROR(VLOOKUP(E10,Questions!$E$5:$L$568,6,0))=FALSE,VLOOKUP(E10,Questions!$E$5:$L$568,6,0),"") | M10: Fase: Liberação e Acompanhamento | N10: 1ª Onda | O10: 178
A11: 170 | D11: =HLOOKUP('General Information'!$C$6,'IDIOMA (hide)'!$A$1:$D$5016,A11,0) -> Go Live | F11: =HLOOKUP('General Information'!$C$6,'IDIOMA (hide)'!$A$1:$D$5016,O11,0) -> Acompanhamento Pós-Virada | G11: Yes | H11: =G11 -> Yes | I11: =Questions!D145*Questions!D151 -> 160 | K11: =IF(H11="Yes",ROUNDUP((I11*J11)+I11,0),0) -> 160 | L11: =IF(ISERROR(VLOOKUP(E11,Questions!$E$5:$L$568,6,0))=FALSE,VLOOKUP(E11,Questions!$E$5:$L$568,6,0),"") | M11: Fase: Liberação e Acompanhamento | N11: 1ª Onda | O11: 179
A12: 171 | D12: =HLOOKUP('General Information'!$C$6,'IDIOMA (hide)'!$A$1:$D$5016,A12,0) -> Inicialização - 2ª Onda | F12: =HLOOKUP('General Information'!$C$6,'IDIOMA (hide)'!$A$1:$D$5016,O12,0) -> Lançamento de Projetos | G12: Yes | H12: =G12 -> Yes | I12: =Questions!D145*Questions!D147 -> 8 | K12: =IF(H12="Yes",ROUNDUP((I12*J12)+I12,0),0) -> 8 | L12: =IF(ISERROR(VLOOKUP(E12,Questions!$E$5:$L$568,6,0))=FALSE,VLOOKUP(E12,Questions!$E$5:$L$568,6,0),"") | M12: Fase: Lançamento do Projeto | N12: 2ª Onda | O12: 180
A13: 172 | D13: =HLOOKUP('General Information'!$C$6,'IDIOMA (hide)'!$A$1:$D$5016,A13,0) -> Go Live - 2ª Onda | F13: =HLOOKUP('General Information'!$C$6,'IDIOMA (hide)'!$A$1:$D$5016,O13,0) -> Teste Piloto | G13: Yes | H13: =G13 -> Yes | I13: =Questions!D149*Questions!D145 -> 40 | K13: =IF(H13="Yes",ROUNDUP((I13*J13)+I13,0),0) -> 40 | L13: =IF(ISERROR(VLOOKUP(E13,Questions!$E$5:$L$568,6,0))=FALSE,VLOOKUP(E13,Questions!$E$5:$L$568,6,0),"") | M13: Fase: Liberação e Acompanhamento | N13: 2ª Onda | O13: 181
A14: 173 | D14: =HLOOKUP('General Information'!$C$6,'IDIOMA (hide)'!$A$1:$D$5016,A14,0) -> Go Live - 2ª Onda | F14: =HLOOKUP('General Information'!$C$6,'IDIOMA (hide)'!$A$1:$D$5016,O14,0) -> Processo de Virada | G14: Yes | H14: =G14 -> Yes | I14: =Questions!D145*Questions!D150 -> 16 | K14: =IF(H14="Yes",ROUNDUP((I14*J14)+I14,0),0) -> 16 | L14: =IF(ISERROR(VLOOKUP(E14,Questions!$E$5:$L$568,6,0))=FALSE,VLOOKUP(E14,Questions!$E$5:$L$568,6,0),"") | M14: Fase: Liberação e Acompanhamento | N14: 2ª Onda | O14: 182
A15: 174 | D15: =HLOOKUP('General Information'!$C$6,'IDIOMA (hide)'!$A$1:$D$5016,A15,0) -> Go Live - 2ª Onda | E15: 010 | F15: =HLOOKUP('General Information'!$C$6,'IDIOMA (hide)'!$A$1:$D$5016,O15,0) -> Acompanhamento Pós-Virada | G15: Yes | H15: =G15 -> Yes | I15: =Questions!D145*Questions!D151 -> 160 | J15: =ROUNDUP(SUMIF(Questions!$E$5:$E$558,'Hours Detail'!E15,Questions!$F$5:$F$558),0) -> 0 | K15: =IF(H15="Yes",ROUNDUP((I15+J15)+I15,0),0) -> 320 | L15: =IF(ISERROR(VLOOKUP(E15,Questions!$E$5:$L$568,6,0))=FALSE,VLOOKUP(E15,Questions!$E$5:$L$568,6,0),"") -> (acrescer 40 horas), normalmente o envio do primeiro monitoramento ocorre 2 meses após a virada. | M15: Fase: Liberação e Acompanhamento | N15: 2ª Onda | O15: 183
K16: =IF(H16="Yes",ROUNDUP(IF(E16<>281,IF(E16<>252,IF(E16<>1355,IF(E16<>2314,IF('General Information'!$C$19="HTML5",(I16+J16)*120%,I16+J16),I16+J16),I16+J16),I16+J16),I16+J16),I16+J16),I16+J16) -> 0 | L16: =IF(ISERROR(VLOOKUP(E16,Questions!$E$5:$L$568,6,0))=FALSE,VLOOKUP(E16,Questions!$E$5:$L$568,6,0),"")
B17: =VLOOKUP('Hours Detail'!E17,'BASE_FUNCOES (hide)'!A:W,5,FALSE) -> 3 | C17: Prestador | D17: =IF('General Information'!$C$6="Português",VLOOKUP(B17,'ESTRUTURA_MODULO(hide)'!A:D,2,0),IF('General Information'!$C$6="English",VLOOKUP(B17,'ESTRUTURA_MODULO(hide)'!A:D,3,0),IF('General Information'!$C$6="Español",VLOOKUP(B17,'ESTRUTURA_MODULO(hide)'!A:D,4,0)))) -> Cadastros e Funções Gerais | E17: 4 | F17: =IF('General Information'!$C$6="Português",VLOOKUP(E17,'BASE_FUNCOES (hide)'!A:H,2,0),IF('General Information'!$C$6="English",VLOOKUP(E17,'BASE_FUNCOES (hide)'!A:H,3,0),IF('General Information'!$C$6="Español",VLOOKUP(E17,'BASE_FUNCOES (hide)'!A:H,4,0)))) -> Cadastro Médico | G17: =IF(AND('General Information'!$D$16=1,VLOOKUP(B17,Modules!$B$5:$E$496,4,0)=1)=TRUE,VLOOKUP('Hours Detail'!E17,'BASE_FUNCOES (hide)'!$A:$V,10,0),IF(AND('General Information'!$D$16=2,VLOOKUP(B17,Modules!$B$5:$E$496,4,0)=1)=TRUE,VLOOKUP('Hours Detail'!E17,'BASE_FUNCOES (hide)'!$A:$V,11,0),IF(AND('General Information'!$D$16=3,VLOOKUP(B17,Modules!$B$5:$E$496,4,0)=1)=TRUE,VLOOKUP('Hours Detail'!E17,'BASE_FUNCOES (hide)'!$A:$V,12,0),IF(AND('General Information'!$D$16=4,VLOOKUP(B17,Modules!$B$5:$E$496,4,0)=1)=TRUE,VLOOKUP('Hours Detail'!E17,'BASE_FUNCOES (hide)'!$A:$V,13,0),IF(AND('General Information'!$D$16=5,VLOOKUP(B17,Modules!$B$5:$E$496,4,0)=1)=TRUE,VLOOKUP('Hours Detail'!E17,'BASE_FUNCOES (hide)'!$A:$V,14,0), IF(AND('General Information'!$D$16=6,VLOOKUP(B17,Modules!$B$5:$E$496,4,0)=1)=TRUE,VLOOKUP('Hours Detail'!E17,'BASE_FUNCOES (hide)'!$A:$V,15,0),"No")))))) -> No | H17: =G17 -> No | I17: =IF('General Information'!$C$4="Mexico",(ROUNDUP(VLOOKUP(E17,'BASE_FUNCOES (hide)'!A:X,21,0),0)),(ROUNDUP(VLOOKUP(E17,'BASE_FUNCOES (hide)'!A:L,9,0),0))) -> 8 | J17: =ROUNDUP(SUMIF(Questions!$E$5:$E$558,'Hours Detail'!E17,Questions!$F$5:$F$558),0) -> 0 | K17: =IF(H17="Yes",ROUNDUP(IF(VLOOKUP(E17,'BASE_FUNCOES (hide)'!A:T,16,FALSE)<>"No",IF('General Information'!$C$19="HTML5",(I17+J17)*'BASE_FUNCOES (hide)'!$T$2,I17+J17),I17+J17),I17+J17),I17+J17) -> 8 | L17: =IF(OR(E17=121,E17=88,E17=2682,E17=2703,E17=2687,E17=2689,E17=2681,E17=2685)=FALSE,"",IF('General Information'!$C$19="HTML5","FUNÇÃO DISPONÍVEL APENAS PARA BRASIL",IF(J18<>0,VLOOKUP(E18,Questions!$E$5:$L$568,5,0),""))) | M17: Fase: Aderência, Parametrização e Treinamentos | N17: 1ª Onda
B18: =VLOOKUP('Hours Detail'!E18,'BASE_FUNCOES (hide)'!A:W,5,FALSE) -> 3 | C18: Prestador | D18: =IF('General Information'!$C$6="Português",VLOOKUP(B18,'ESTRUTURA_MODULO(hide)'!A:D,2,0),IF('General Information'!$C$6="English",VLOOKUP(B18,'ESTRUTURA_MODULO(hide)'!A:D,3,0),IF('General Information'!$C$6="Español",VLOOKUP(B18,'ESTRUTURA_MODULO(hide)'!A:D,4,0)))) -> Cadastros e Funções Gerais | E18: 53 | F18: =IF('General Information'!$C$6="Português",VLOOKUP(E18,'BASE_FUNCOES (hide)'!A:H,2,0),IF('General Information'!$C$6="English",VLOOKUP(E18,'BASE_FUNCOES (hide)'!A:H,3,0),IF('General Information'!$C$6="Español",VLOOKUP(E18,'BASE_FUNCOES (hide)'!A:H,4,0)))) -> Cadastro de CEP | G18: =IF(AND('General Information'!$D$16=1,VLOOKUP(B18,Modules!$B$5:$E$496,4,0)=1)=TRUE,VLOOKUP('Hours Detail'!E18,'BASE_FUNCOES (hide)'!$A:$V,10,0),IF(AND('General Information'!$D$16=2,VLOOKUP(B18,Modules!$B$5:$E$496,4,0)=1)=TRUE,VLOOKUP('Hours Detail'!E18,'BASE_FUNCOES (hide)'!$A:$V,11,0),IF(AND('General Information'!$D$16=3,VLOOKUP(B18,Modules!$B$5:$E$496,4,0)=1)=TRUE,VLOOKUP('Hours Detail'!E18,'BASE_FUNCOES (hide)'!$A:$V,12,0),IF(AND('General Information'!$D$16=4,VLOOKUP(B18,Modules!$B$5:$E$496,4,0)=1)=TRUE,VLOOKUP('Hours Detail'!E18,'BASE_FUNCOES (hide)'!$A:$V,13,0),IF(AND('General Information'!$D$16=5,VLOOKUP(B18,Modules!$B$5:$E$496,4,0)=1)=TRUE,VLOOKUP('Hours Detail'!E18,'BASE_FUNCOES (hide)'!$A:$V,14,0), IF(AND('General Information'!$D$16=6,VLOOKUP(B18,Modules!$B$5:$E$496,4,0)=1)=TRUE,VLOOKUP('Hours Detail'!E18,'BASE_FUNCOES (hide)'!$A:$V,15,0),"No")))))) -> No | H18: =G18 -> No | I18: =IF('General Information'!$C$4="Mexico",(ROUNDUP(VLOOKUP(E18,'BASE_FUNCOES (hide)'!A:X,21,0),0)),(ROUNDUP(VLOOKUP(E18,'BASE_FUNCOES (hide)'!A:L,9,0),0))) -> 4 | J18: =ROUNDUP(SUMIF(Questions!$E$5:$E$558,'Hours Detail'!E18,Questions!$F$5:$F$558),0) -> 0 | K18: =IF(H18="Yes",ROUNDUP(IF(VLOOKUP(E18,'BASE_FUNCOES (hide)'!A:T,16,FALSE)<>"No",IF('General Information'!$C$19="HTML5",(I18+J18)*'BASE_FUNCOES (hide)'!$T$2,I18+J18),I18+J18),I18+J18),I18+J18) -> 4 | L18: =IF(OR(E18=121,E18=88,E18=2682,E18=2703,E18=2687,E18=2689,E18=2681,E18=2685)=FALSE,"",IF('General Information'!$C$19="HTML5","FUNÇÃO DISPONÍVEL APENAS PARA BRASIL",IF(J19<>0,VLOOKUP(E19,Questions!$E$5:$L$568,5,0),""))) | M18: Fase: Aderência, Parametrização e Treinamentos | N18: 1ª Onda
B19: =VLOOKUP('Hours Detail'!E19,'BASE_FUNCOES (hide)'!A:W,5,FALSE) -> 3 | C19: Prestador | D19: =IF('General Information'!$C$6="Português",VLOOKUP(B19,'ESTRUTURA_MODULO(hide)'!A:D,2,0),IF('General Information'!$C$6="English",VLOOKUP(B19,'ESTRUTURA_MODULO(hide)'!A:D,3,0),IF('General Information'!$C$6="Español",VLOOKUP(B19,'ESTRUTURA_MODULO(hide)'!A:D,4,0)))) -> Cadastros e Funções Gerais | E19: 132 | F19: =IF('General Information'!$C$6="Português",VLOOKUP(E19,'BASE_FUNCOES (hide)'!A:H,2,0),IF('General Information'!$C$6="English",VLOOKUP(E19,'BASE_FUNCOES (hide)'!A:H,3,0),IF('General Information'!$C$6="Español",VLOOKUP(E19,'BASE_FUNCOES (hide)'!A:H,4,0)))) -> Cadastro de Materiais | G19: =IF(AND('General Information'!$D$16=1,VLOOKUP(B19,Modules!$B$5:$E$496,4,0)=1)=TRUE,VLOOKUP('Hours Detail'!E19,'BASE_FUNCOES (hide)'!$A:$V,10,0),IF(AND('General Information'!$D$16=2,VLOOKUP(B19,Modules!$B$5:$E$496,4,0)=1)=TRUE,VLOOKUP('Hours Detail'!E19,'BASE_FUNCOES (hide)'!$A:$V,11,0),IF(AND('General Information'!$D$16=3,VLOOKUP(B19,Modules!$B$5:$E$496,4,0)=1)=TRUE,VLOOKUP('Hours Detail'!E19,'BASE_FUNCOES (hide)'!$A:$V,12,0),IF(AND('General Information'!$D$16=4,VLOOKUP(B19,Modules!$B$5:$E$496,4,0)=1)=TRUE,VLOOKUP('Hours Detail'!E19,'BASE_FUNCOES (hide)'!$A:$V,13,0),IF(AND('General Information'!$D$16=5,VLOOKUP(B19,Modules!$B$5:$E$496,4,0)=1)=TRUE,VLOOKUP('Hours Detail'!E19,'BASE_FUNCOES (hide)'!$A:$V,14,0), IF(AND('General Information'!$D$16=6,VLOOKUP(B19,Modules!$B$5:$E$496,4,0)=1)=TRUE,VLOOKUP('Hours Detail'!E19,'BASE_FUNCOES (hide)'!$A:$V,15,0),"No")))))) -> No | H19: =G19 -> No | I19: =IF('General Information'!$C$4="Mexico",(ROUNDUP(VLOOKUP(E19,'BASE_FUNCOES (hide)'!A:X,21,0),0)),(ROUNDUP(VLOOKUP(E19,'BASE_FUNCOES (hide)'!A:L,9,0),0))) -> 32 | J19: =ROUNDUP(SUMIF(Questions!$E$5:$E$558,'Hours Detail'!E19,Questions!$F$5:$F$558),0) -> 0 | K19: =IF(H19="Yes",ROUNDUP(IF(VLOOKUP(E19,'BASE_FUNCOES (hide)'!A:T,16,FALSE)<>"No",IF('General Information'!$C$19="HTML5",(I19+J19)*'BASE_FUNCOES (hide)'!$T$2,I19+J19),I19+J19),I19+J19),I19+J19) -> 32 | L19: =IF(OR(E19=121,E19=88,E19=2682,E19=2703,E19=2687,E19=2689,E19=2681,E19=2685)=FALSE,"",IF('General Information'!$C$19="HTML5","FUNÇÃO DISPONÍVEL APENAS PARA BRASIL",IF(J20<>0,VLOOKUP(E20,Questions!$E$5:$L$568,5,0),""))) | M19: Fase: Aderência, Parametrização e Treinamentos | N19: 1ª Onda
B20: =VLOOKUP('Hours Detail'!E20,'BASE_FUNCOES (hide)'!A:W,5,FALSE) -> 3 | C20: Prestador | D20: =IF('General Information'!$C$6="Português",VLOOKUP(B20,'ESTRUTURA_MODULO(hide)'!A:D,2,0),IF('General Information'!$C$6="English",VLOOKUP(B20,'ESTRUTURA_MODULO(hide)'!A:D,3,0),IF('General Information'!$C$6="Español",VLOOKUP(B20,'ESTRUTURA_MODULO(hide)'!A:D,4,0)))) -> Cadastros e Funções Gerais | E20: 705 | F20: =IF('General Information'!$C$6="Português",VLOOKUP(E20,'BASE_FUNCOES (hide)'!A:H,2,0),IF('General Information'!$C$6="English",VLOOKUP(E20,'BASE_FUNCOES (hide)'!A:H,3,0),IF('General Information'!$C$6="Español",VLOOKUP(E20,'BASE_FUNCOES (hide)'!A:H,4,0)))) -> Cargas | G20: =IF(AND('General Information'!$D$16=1,VLOOKUP(B20,Modules!$B$5:$E$496,4,0)=1)=TRUE,VLOOKUP('Hours Detail'!E20,'BASE_FUNCOES (hide)'!$A:$V,10,0),IF(AND('General Information'!$D$16=2,VLOOKUP(B20,Modules!$B$5:$E$496,4,0)=1)=TRUE,VLOOKUP('Hours Detail'!E20,'BASE_FUNCOES (hide)'!$A:$V,11,0),IF(AND('General Information'!$D$16=3,VLOOKUP(B20,Modules!$B$5:$E$496,4,0)=1)=TRUE,VLOOKUP('Hours Detail'!E20,'BASE_FUNCOES (hide)'!$A:$V,12,0),IF(AND('General Information'!$D$16=4,VLOOKUP(B20,Modules!$B$5:$E$496,4,0)=1)=TRUE,VLOOKUP('Hours Detail'!E20,'BASE_FUNCOES (hide)'!$A:$V,13,0),IF(AND('General Information'!$D$16=5,VLOOKUP(B20,Modules!$B$5:$E$496,4,0)=1)=TRUE,VLOOKUP('Hours Detail'!E20,'BASE_FUNCOES (hide)'!$A:$V,14,0), IF(AND('General Information'!$D$16=6,VLOOKUP(B20,Modules!$B$5:$E$496,4,0)=1)=TRUE,VLOOKUP('Hours Detail'!E20,'BASE_FUNCOES (hide)'!$A:$V,15,0),"No")))))) -> No | H20: =G20 -> No | I20: =IF('General Information'!$C$4="Mexico",(ROUNDUP(VLOOKUP(E20,'BASE_FUNCOES (hide)'!A:X,21,0),0)),(ROUNDUP(VLOOKUP(E20,'BASE_FUNCOES (hide)'!A:L,9,0),0))) -> 12 | J20: =ROUNDUP(SUMIF(Questions!$E$5:$E$558,'Hours Detail'!E20,Questions!$F$5:$F$558),0) -> 0 | K20: =IF(H20="Yes",ROUNDUP(IF(VLOOKUP(E20,'BASE_FUNCOES (hide)'!A:T,16,FALSE)<>"No",IF('General Information'!$C$19="HTML5",(I20+J20)*'BASE_FUNCOES (hide)'!$T$2,I20+J20),I20+J20),I20+J20),I20+J20) -> 12 | L20: =IF(OR(E20=121,E20=88,E20=2682,E20=2703,E20=2687,E20=2689,E20=2681,E20=2685)=FALSE,"",IF('General Information'!$C$19="HTML5","FUNÇÃO DISPONÍVEL APENAS PARA BRASIL",IF(J21<>0,VLOOKUP(E21,Questions!$E$5:$L$568,5,0),""))) | M20: Fase: Aderência, Parametrização e Treinamentos | N20: 1ª Onda
B21: =VLOOKUP('Hours Detail'!E21,'BASE_FUNCOES (hide)'!A:W,5,FALSE) -> 3 | C21: Prestador | D21: =IF('General Information'!$C$6="Português",VLOOKUP(B21,'ESTRUTURA_MODULO(hide)'!A:D,2,0),IF('General Information'!$C$6="English",VLOOKUP(B21,'ESTRUTURA_MODULO(hide)'!A:D,3,0),IF('General Information'!$C$6="Español",VLOOKUP(B21,'ESTRUTURA_MODULO(hide)'!A:D,4,0)))) -> Cadastros e Funções Gerais | E21: 911 | F21: =IF('General Information'!$C$6="Português",VLOOKUP(E21,'BASE_FUNCOES (hide)'!A:H,2,0),IF('General Information'!$C$6="English",VLOOKUP(E21,'BASE_FUNCOES (hide)'!A:H,3,0),IF('General Information'!$C$6="Español",VLOOKUP(E21,'BASE_FUNCOES (hide)'!A:H,4,0)))) -> Empresa/Estabelecimento/Contas/CC | G21: =IF(AND('General Information'!$D$16=1,VLOOKUP(B21,Modules!$B$5:$E$496,4,0)=1)=TRUE,VLOOKUP('Hours Detail'!E21,'BASE_FUNCOES (hide)'!$A:$V,10,0),IF(AND('General Information'!$D$16=2,VLOOKUP(B21,Modules!$B$5:$E$496,4,0)=1)=TRUE,VLOOKUP('Hours Detail'!E21,'BASE_FUNCOES (hide)'!$A:$V,11,0),IF(AND('General Information'!$D$16=3,VLOOKUP(B21,Modules!$B$5:$E$496,4,0)=1)=TRUE,VLOOKUP('Hours Detail'!E21,'BASE_FUNCOES (hide)'!$A:$V,12,0),IF(AND('General Information'!$D$16=4,VLOOKUP(B21,Modules!$B$5:$E$496,4,0)=1)=TRUE,VLOOKUP('Hours Detail'!E21,'BASE_FUNCOES (hide)'!$A:$V,13,0),IF(AND('General Information'!$D$16=5,VLOOKUP(B21,Modules!$B$5:$E$496,4,0)=1)=TRUE,VLOOKUP('Hours Detail'!E21,'BASE_FUNCOES (hide)'!$A:$V,14,0), IF(AND('General Information'!$D$16=6,VLOOKUP(B21,Modules!$B$5:$E$496,4,0)=1)=TRUE,VLOOKUP('Hours Detail'!E21,'BASE_FUNCOES (hide)'!$A:$V,15,0),"No")))))) -> No | H21: =G21 -> No | I21: =IF('General Information'!$C$4="Mexico",(ROUNDUP(VLOOKUP(E21,'BASE_FUNCOES (hide)'!A:X,21,0),0)),(ROUNDUP(VLOOKUP(E21,'BASE_FUNCOES (hide)'!A:L,9,0),0))) -> 24 | J21: =ROUNDUP(SUMIF(Questions!$E$5:$E$558,'Hours Detail'!E21,Questions!$F$5:$F$558),0) -> 0 | K21: =IF(H21="Yes",ROUNDUP(IF(VLOOKUP(E21,'BASE_FUNCOES (hide)'!A:T,16,FALSE)<>"No",IF('General Information'!$C$19="HTML5",(I21+J21)*'BASE_FUNCOES (hide)'!$T$2,I21+J21),I21+J21),I21+J21),I21+J21) -> 24 | L21: =IF(OR(E21=121,E21=88,E21=2682,E21=2703,E21=2687,E21=2689,E21=2681,E21=2685)=FALSE,"",IF('General Information'!$C$19="HTML5","FUNÇÃO DISPONÍVEL APENAS PARA BRASIL",IF(J22<>0,VLOOKUP(E22,Questions!$E$5:$L$568,5,0),""))) | M21: Fase: Aderência, Parametrização e Treinamentos | N21: 1ª Onda
B22: =VLOOKUP('Hours Detail'!E22,'BASE_FUNCOES (hide)'!A:W,5,FALSE) -> 3 | C22: Prestador | D22: =IF('General Information'!$C$6="Português",VLOOKUP(B22,'ESTRUTURA_MODULO(hide)'!A:D,2,0),IF('General Information'!$C$6="English",VLOOKUP(B22,'ESTRUTURA_MODULO(hide)'!A:D,3,0),IF('General Information'!$C$6="Español",VLOOKUP(B22,'ESTRUTURA_MODULO(hide)'!A:D,4,0)))) -> Cadastros e Funções Gerais | E22: 1 | F22: =IF('General Information'!$C$6="Português",VLOOKUP(E22,'BASE_FUNCOES (hide)'!A:H,2,0),IF('General Information'!$C$6="English",VLOOKUP(E22,'BASE_FUNCOES (hide)'!A:H,3,0),IF('General Information'!$C$6="Español",VLOOKUP(E22,'BASE_FUNCOES (hide)'!A:H,4,0)))) -> Estrutura Atendimento | G22: =IF(AND('General Information'!$D$16=1,VLOOKUP(B22,Modules!$B$5:$E$496,4,0)=1)=TRUE,VLOOKUP('Hours Detail'!E22,'BASE_FUNCOES (hide)'!$A:$V,10,0),IF(AND('General Information'!$D$16=2,VLOOKUP(B22,Modules!$B$5:$E$496,4,0)=1)=TRUE,VLOOKUP('Hours Detail'!E22,'BASE_FUNCOES (hide)'!$A:$V,11,0),IF(AND('General Information'!$D$16=3,VLOOKUP(B22,Modules!$B$5:$E$496,4,0)=1)=TRUE,VLOOKUP('Hours Detail'!E22,'BASE_FUNCOES (hide)'!$A:$V,12,0),IF(AND('General Information'!$D$16=4,VLOOKUP(B22,Modules!$B$5:$E$496,4,0)=1)=TRUE,VLOOKUP('Hours Detail'!E22,'BASE_FUNCOES (hide)'!$A:$V,13,0),IF(AND('General Information'!$D$16=5,VLOOKUP(B22,Modules!$B$5:$E$496,4,0)=1)=TRUE,VLOOKUP('Hours Detail'!E22,'BASE_FUNCOES (hide)'!$A:$V,14,0), IF(AND('General Information'!$D$16=6,VLOOKUP(B22,Modules!$B$5:$E$496,4,0)=1)=TRUE,VLOOKUP('Hours Detail'!E22,'BASE_FUNCOES (hide)'!$A:$V,15,0),"No")))))) -> No | H22: =G22 -> No | I22: =IF('General Information'!$C$4="Mexico",(ROUNDUP(VLOOKUP(E22,'BASE_FUNCOES (hide)'!A:X,21,0),0)),(ROUNDUP(VLOOKUP(E22,'BASE_FUNCOES (hide)'!A:L,9,0),0))) -> 8 | J22: =ROUNDUP(SUMIF(Questions!$E$5:$E$558,'Hours Detail'!E22,Questions!$F$5:$F$558),0) -> 0 | K22: =IF(H22="Yes",ROUNDUP(IF(VLOOKUP(E22,'BASE_FUNCOES (hide)'!A:T,16,FALSE)<>"No",IF('General Information'!$C$19="HTML5",(I22+J22)*'BASE_FUNCOES (hide)'!$T$2,I22+J22),I22+J22),I22+J22),I22+J22) -> 8 | L22: =IF(OR(E22=121,E22=88,E22=2682,E22=2703,E22=2687,E22=2689,E22=2681,E22=2685)=FALSE,"",IF('General Information'!$C$19="HTML5","FUNÇÃO DISPONÍVEL APENAS PARA BRASIL",IF(J23<>0,VLOOKUP(E23,Questions!$E$5:$L$568,5,0),""))) | M22: Fase: Aderência, Parametrização e Treinamentos | N22: 1ª Onda
B23: =VLOOKUP('Hours Detail'!E23,'BASE_FUNCOES (hide)'!A:W,5,FALSE) -> 3 | C23: Prestador | D23: =IF('General Information'!$C$6="Português",VLOOKUP(B23,'ESTRUTURA_MODULO(hide)'!A:D,2,0),IF('General Information'!$C$6="English",VLOOKUP(B23,'ESTRUTURA_MODULO(hide)'!A:D,3,0),IF('General Information'!$C$6="Español",VLOOKUP(B23,'ESTRUTURA_MODULO(hide)'!A:D,4,0)))) -> Cadastros e Funções Gerais | E23: 947 | F23: =IF('General Information'!$C$6="Português",VLOOKUP(E23,'BASE_FUNCOES (hide)'!A:H,2,0),IF('General Information'!$C$6="English",VLOOKUP(E23,'BASE_FUNCOES (hide)'!A:H,3,0),IF('General Information'!$C$6="Español",VLOOKUP(E23,'BASE_FUNCOES (hide)'!A:H,4,0)))) -> Exames e Procedimentos Internos | G23: =IF(AND('General Information'!$D$16=1,VLOOKUP(B23,Modules!$B$5:$E$496,4,0)=1)=TRUE,VLOOKUP('Hours Detail'!E23,'BASE_FUNCOES (hide)'!$A:$V,10,0),IF(AND('General Information'!$D$16=2,VLOOKUP(B23,Modules!$B$5:$E$496,4,0)=1)=TRUE,VLOOKUP('Hours Detail'!E23,'BASE_FUNCOES (hide)'!$A:$V,11,0),IF(AND('General Information'!$D$16=3,VLOOKUP(B23,Modules!$B$5:$E$496,4,0)=1)=TRUE,VLOOKUP('Hours Detail'!E23,'BASE_FUNCOES (hide)'!$A:$V,12,0),IF(AND('General Information'!$D$16=4,VLOOKUP(B23,Modules!$B$5:$E$496,4,0)=1)=TRUE,VLOOKUP('Hours Detail'!E23,'BASE_FUNCOES (hide)'!$A:$V,13,0),IF(AND('General Information'!$D$16=5,VLOOKUP(B23,Modules!$B$5:$E$496,4,0)=1)=TRUE,VLOOKUP('Hours Detail'!E23,'BASE_FUNCOES (hide)'!$A:$V,14,0), IF(AND('General Information'!$D$16=6,VLOOKUP(B23,Modules!$B$5:$E$496,4,0)=1)=TRUE,VLOOKUP('Hours Detail'!E23,'BASE_FUNCOES (hide)'!$A:$V,15,0),"No")))))) -> No | H23: =G23 -> No | I23: =IF('General Information'!$C$4="Mexico",(ROUNDUP(VLOOKUP(E23,'BASE_FUNCOES (hide)'!A:X,21,0),0)),(ROUNDUP(VLOOKUP(E23,'BASE_FUNCOES (hide)'!A:L,9,0),0))) -> 16 | J23: =ROUNDUP(SUMIF(Questions!$E$5:$E$558,'Hours Detail'!E23,Questions!$F$5:$F$558),0) -> 0 | K23: =IF(H23="Yes",ROUNDUP(IF(VLOOKUP(E23,'BASE_FUNCOES (hide)'!A:T,16,FALSE)<>"No",IF('General Information'!$C$19="HTML5",(I23+J23)*'BASE_FUNCOES (hide)'!$T$2,I23+J23),I23+J23),I23+J23),I23+J23) -> 16 | L23: =IF(OR(E23=121,E23=88,E23=2682,E23=2703,E23=2687,E23=2689,E23=2681,E23=2685)=FALSE,"",IF('General Information'!$C$19="HTML5","FUNÇÃO DISPONÍVEL APENAS PARA BRASIL",IF(J24<>0,VLOOKUP(E24,Questions!$E$5:$L$568,5,0),""))) | M23: Fase: Aderência, Parametrização e Treinamentos | N23: 1ª Onda
B24: =VLOOKUP('Hours Detail'!E24,'BASE_FUNCOES (hide)'!A:W,5,FALSE) -> 3 | C24: Prestador | D24: =IF('General Information'!$C$6="Português",VLOOKUP(B24,'ESTRUTURA_MODULO(hide)'!A:D,2,0),IF('General Information'!$C$6="English",VLOOKUP(B24,'ESTRUTURA_MODULO(hide)'!A:D,3,0),IF('General Information'!$C$6="Español",VLOOKUP(B24,'ESTRUTURA_MODULO(hide)'!A:D,4,0)))) -> Cadastros e Funções Gerais | E24: 6 | F24: =IF('General Information'!$C$6="Português",VLOOKUP(E24,'BASE_FUNCOES (hide)'!A:H,2,0),IF('General Information'!$C$6="English",VLOOKUP(E24,'BASE_FUNCOES (hide)'!A:H,3,0),IF('General Information'!$C$6="Español",VLOOKUP(E24,'BASE_FUNCOES (hide)'!A:H,4,0)))) -> Pessoa Jurídica | G24: =IF(AND('General Information'!$D$16=1,VLOOKUP(B24,Modules!$B$5:$E$496,4,0)=1)=TRUE,VLOOKUP('Hours Detail'!E24,'BASE_FUNCOES (hide)'!$A:$V,10,0),IF(AND('General Information'!$D$16=2,VLOOKUP(B24,Modules!$B$5:$E$496,4,0)=1)=TRUE,VLOOKUP('Hours Detail'!E24,'BASE_FUNCOES (hide)'!$A:$V,11,0),IF(AND('General Information'!$D$16=3,VLOOKUP(B24,Modules!$B$5:$E$496,4,0)=1)=TRUE,VLOOKUP('Hours Detail'!E24,'BASE_FUNCOES (hide)'!$A:$V,12,0),IF(AND('General Information'!$D$16=4,VLOOKUP(B24,Modules!$B$5:$E$496,4,0)=1)=TRUE,VLOOKUP('Hours Detail'!E24,'BASE_FUNCOES (hide)'!$A:$V,13,0),IF(AND('General Information'!$D$16=5,VLOOKUP(B24,Modules!$B$5:$E$496,4,0)=1)=TRUE,VLOOKUP('Hours Detail'!E24,'BASE_FUNCOES (hide)'!$A:$V,14,0), IF(AND('General Information'!$D$16=6,VLOOKUP(B24,Modules!$B$5:$E$496,4,0)=1)=TRUE,VLOOKUP('Hours Detail'!E24,'BASE_FUNCOES (hide)'!$A:$V,15,0),"No")))))) -> No | H24: =G24 -> No | I24: =IF('General Information'!$C$4="Mexico",(ROUNDUP(VLOOKUP(E24,'BASE_FUNCOES (hide)'!A:X,21,0),0)),(ROUNDUP(VLOOKUP(E24,'BASE_FUNCOES (hide)'!A:L,9,0),0))) -> 12 | J24: =ROUNDUP(SUMIF(Questions!$E$5:$E$558,'Hours Detail'!E24,Questions!$F$5:$F$558),0) -> 0 | K24: =IF(H24="Yes",ROUNDUP(IF(VLOOKUP(E24,'BASE_FUNCOES (hide)'!A:T,16,FALSE)<>"No",IF('General Information'!$C$19="HTML5",(I24+J24)*'BASE_FUNCOES (hide)'!$T$2,I24+J24),I24+J24),I24+J24),I24+J24) -> 12 | L24: =IF(OR(E24=121,E24=88,E24=2682,E24=2703,E24=2687,E24=2689,E24=2681,E24=2685)=FALSE,"",IF('General Information'!$C$19="HTML5","FUNÇÃO DISPONÍVEL APENAS PARA BRASIL",IF(J25<>0,VLOOKUP(E25,Questions!$E$5:$L$568,5,0),""))) | M24: Fase: Aderência, Parametrização e Treinamentos | N24: 1ª Onda
B25: =VLOOKUP('Hours Detail'!E25,'BASE_FUNCOES (hide)'!A:W,5,FALSE) -> 3 | C25: Prestador | D25: =IF('General Information'!$C$6="Português",VLOOKUP(B25,'ESTRUTURA_MODULO(hide)'!A:D,2,0),IF('General Information'!$C$6="English",VLOOKUP(B25,'ESTRUTURA_MODULO(hide)'!A:D,3,0),IF('General Information'!$C$6="Español",VLOOKUP(B25,'ESTRUTURA_MODULO(hide)'!A:D,4,0)))) -> Cadastros e Funções Gerais | E25: 25 | F25: =IF('General Information'!$C$6="Português",VLOOKUP(E25,'BASE_FUNCOES (hide)'!A:H,2,0),IF('General Information'!$C$6="English",VLOOKUP(E25,'BASE_FUNCOES (hide)'!A:H,3,0),IF('General Information'!$C$6="Español",VLOOKUP(E25,'BASE_FUNCOES (hide)'!A:H,4,0)))) -> Procedimentos | G25: =IF(AND('General Information'!$D$16=1,VLOOKUP(B25,Modules!$B$5:$E$496,4,0)=1)=TRUE,VLOOKUP('Hours Detail'!E25,'BASE_FUNCOES (hide)'!$A:$V,10,0),IF(AND('General Information'!$D$16=2,VLOOKUP(B25,Modules!$B$5:$E$496,4,0)=1)=TRUE,VLOOKUP('Hours Detail'!E25,'BASE_FUNCOES (hide)'!$A:$V,11,0),IF(AND('General Information'!$D$16=3,VLOOKUP(B25,Modules!$B$5:$E$496,4,0)=1)=TRUE,VLOOKUP('Hours Detail'!E25,'BASE_FUNCOES (hide)'!$A:$V,12,0),IF(AND('General Information'!$D$16=4,VLOOKUP(B25,Modules!$B$5:$E$496,4,0)=1)=TRUE,VLOOKUP('Hours Detail'!E25,'BASE_FUNCOES (hide)'!$A:$V,13,0),IF(AND('General Information'!$D$16=5,VLOOKUP(B25,Modules!$B$5:$E$496,4,0)=1)=TRUE,VLOOKUP('Hours Detail'!E25,'BASE_FUNCOES (hide)'!$A:$V,14,0), IF(AND('General Information'!$D$16=6,VLOOKUP(B25,Modules!$B$5:$E$496,4,0)=1)=TRUE,VLOOKUP('Hours Detail'!E25,'BASE_FUNCOES (hide)'!$A:$V,15,0),"No")))))) -> No | H25: =G25 -> No | I25: =IF('General Information'!$C$4="Mexico",(ROUNDUP(VLOOKUP(E25,'BASE_FUNCOES (hide)'!A:X,21,0),0)),(ROUNDUP(VLOOKUP(E25,'BASE_FUNCOES (hide)'!A:L,9,0),0))) -> 10 | J25: =ROUNDUP(SUMIF(Questions!$E$5:$E$558,'Hours Detail'!E25,Questions!$F$5:$F$558),0) -> 0 | K25: =IF(H25="Yes",ROUNDUP(IF(VLOOKUP(E25,'BASE_FUNCOES (hide)'!A:T,16,FALSE)<>"No",IF('General Information'!$C$19="HTML5",(I25+J25)*'BASE_FUNCOES (hide)'!$T$2,I25+J25),I25+J25),I25+J25),I25+J25) -> 10 | L25: =IF(OR(E25=121,E25=88,E25=2682,E25=2703,E25=2687,E25=2689,E25=2681,E25=2685)=FALSE,"",IF('General Information'!$C$19="HTML5","FUNÇÃO DISPONÍVEL APENAS PARA BRASIL",IF(J26<>0,VLOOKUP(E26,Questions!$E$5:$L$568,5,0),""))) | M25: Fase: Aderência, Parametrização e Treinamentos | N25: 1ª Onda
B26: =VLOOKUP('Hours Detail'!E26,'BASE_FUNCOES (hide)'!A:W,5,FALSE) -> 3 | C26: Prestador | D26: =IF('General Information'!$C$6="Português",VLOOKUP(B26,'ESTRUTURA_MODULO(hide)'!A:D,2,0),IF('General Information'!$C$6="English",VLOOKUP(B26,'ESTRUTURA_MODULO(hide)'!A:D,3,0),IF('General Information'!$C$6="Español",VLOOKUP(B26,'ESTRUTURA_MODULO(hide)'!A:D,4,0)))) -> Cadastros e Funções Gerais | E26: 15 | F26: =IF('General Information'!$C$6="Português",VLOOKUP(E26,'BASE_FUNCOES (hide)'!A:H,2,0),IF('General Information'!$C$6="English",VLOOKUP(E26,'BASE_FUNCOES (hide)'!A:H,3,0),IF('General Information'!$C$6="Español",VLOOKUP(E26,'BASE_FUNCOES (hide)'!A:H,4,0)))) -> Tipos de Acomodação | G26: =IF(AND('General Information'!$D$16=1,VLOOKUP(B26,Modules!$B$5:$E$496,4,0)=1)=TRUE,VLOOKUP('Hours Detail'!E26,'BASE_FUNCOES (hide)'!$A:$V,10,0),IF(AND('General Information'!$D$16=2,VLOOKUP(B26,Modules!$B$5:$E$496,4,0)=1)=TRUE,VLOOKUP('Hours Detail'!E26,'BASE_FUNCOES (hide)'!$A:$V,11,0),IF(AND('General Information'!$D$16=3,VLOOKUP(B26,Modules!$B$5:$E$496,4,0)=1)=TRUE,VLOOKUP('Hours Detail'!E26,'BASE_FUNCOES (hide)'!$A:$V,12,0),IF(AND('General Information'!$D$16=4,VLOOKUP(B26,Modules!$B$5:$E$496,4,0)=1)=TRUE,VLOOKUP('Hours Detail'!E26,'BASE_FUNCOES (hide)'!$A:$V,13,0),IF(AND('General Information'!$D$16=5,VLOOKUP(B26,Modules!$B$5:$E$496,4,0)=1)=TRUE,VLOOKUP('Hours Detail'!E26,'BASE_FUNCOES (hide)'!$A:$V,14,0), IF(AND('General Information'!$D$16=6,VLOOKUP(B26,Modules!$B$5:$E$496,4,0)=1)=TRUE,VLOOKUP('Hours Detail'!E26,'BASE_FUNCOES (hide)'!$A:$V,15,0),"No")))))) -> No | H26: =G26 -> No | I26: =IF('General Information'!$C$4="Mexico",(ROUNDUP(VLOOKUP(E26,'BASE_FUNCOES (hide)'!A:X,21,0),0)),(ROUNDUP(VLOOKUP(E26,'BASE_FUNCOES (hide)'!A:L,9,0),0))) -> 2 | J26: =ROUNDUP(SUMIF(Questions!$E$5:$E$558,'Hours Detail'!E26,Questions!$F$5:$F$558),0) -> 0 | K26: =IF(H26="Yes",ROUNDUP(IF(VLOOKUP(E26,'BASE_FUNCOES (hide)'!A:T,16,FALSE)<>"No",IF('General Information'!$C$19="HTML5",(I26+J26)*'BASE_FUNCOES (hide)'!$T$2,I26+J26),I26+J26),I26+J26),I26+J26) -> 2 | L26: =IF(OR(E26=121,E26=88,E26=2682,E26=2703,E26=2687,E26=2689,E26=2681,E26=2685)=FALSE,"",IF('General Information'!$C$19="HTML5","FUNÇÃO DISPONÍVEL APENAS PARA BRASIL",IF(J27<>0,VLOOKUP(E27,Questions!$E$5:$L$568,5,0),""))) | M26: Fase: Aderência, Parametrização e Treinamentos | N26: 1ª Onda
B27: =VLOOKUP('Hours Detail'!E27,'BASE_FUNCOES (hide)'!A:W,5,FALSE) -> 3 | C27: Prestador | D27: =IF('General Information'!$C$6="Português",VLOOKUP(B27,'ESTRUTURA_MODULO(hide)'!A:D,2,0),IF('General Information'!$C$6="English",VLOOKUP(B27,'ESTRUTURA_MODULO(hide)'!A:D,3,0),IF('General Information'!$C$6="Español",VLOOKUP(B27,'ESTRUTURA_MODULO(hide)'!A:D,4,0)))) -> Cadastros e Funções Gerais | E27: 230 | F27: =IF('General Information'!$C$6="Português",VLOOKUP(E27,'BASE_FUNCOES (hide)'!A:H,2,0),IF('General Information'!$C$6="English",VLOOKUP(E27,'BASE_FUNCOES (hide)'!A:H,3,0),IF('General Information'!$C$6="Español",VLOOKUP(E27,'BASE_FUNCOES (hide)'!A:H,4,0)))) -> Cadastro de Funcionários | G27: =IF(AND('General Information'!$D$16=1,VLOOKUP(B27,Modules!$B$5:$E$496,4,0)=1)=TRUE,VLOOKUP('Hours Detail'!E27,'BASE_FUNCOES (hide)'!$A:$V,10,0),IF(AND('General Information'!$D$16=2,VLOOKUP(B27,Modules!$B$5:$E$496,4,0)=1)=TRUE,VLOOKUP('Hours Detail'!E27,'BASE_FUNCOES (hide)'!$A:$V,11,0),IF(AND('General Information'!$D$16=3,VLOOKUP(B27,Modules!$B$5:$E$496,4,0)=1)=TRUE,VLOOKUP('Hours Detail'!E27,'BASE_FUNCOES (hide)'!$A:$V,12,0),IF(AND('General Information'!$D$16=4,VLOOKUP(B27,Modules!$B$5:$E$496,4,0)=1)=TRUE,VLOOKUP('Hours Detail'!E27,'BASE_FUNCOES (hide)'!$A:$V,13,0),IF(AND('General Information'!$D$16=5,VLOOKUP(B27,Modules!$B$5:$E$496,4,0)=1)=TRUE,VLOOKUP('Hours Detail'!E27,'BASE_FUNCOES (hide)'!$A:$V,14,0), IF(AND('General Information'!$D$16=6,VLOOKUP(B27,Modules!$B$5:$E$496,4,0)=1)=TRUE,VLOOKUP('Hours Detail'!E27,'BASE_FUNCOES (hide)'!$A:$V,15,0),"No")))))) -> No | H27: No | I27: =IF('General Information'!$C$4="Mexico",(ROUNDUP(VLOOKUP(E27,'BASE_FUNCOES (hide)'!A:X,21,0),0)),(ROUNDUP(VLOOKUP(E27,'BASE_FUNCOES (hide)'!A:L,9,0),0))) -> 4 | J27: =ROUNDUP(SUMIF(Questions!$E$5:$E$558,'Hours Detail'!E27,Questions!$F$5:$F$558),0) -> 0 | K27: =IF(H27="Yes",ROUNDUP(IF(VLOOKUP(E27,'BASE_FUNCOES (hide)'!A:T,16,FALSE)<>"No",IF('General Information'!$C$19="HTML5",(I27+J27)*'BASE_FUNCOES (hide)'!$T$2,I27+J27),I27+J27),I27+J27),I27+J27) -> 4 | L27: =IF(OR(E27=121,E27=88,E27=2682,E27=2703,E27=2687,E27=2689,E27=2681,E27=2685)=FALSE,"",IF('General Information'!$C$19="HTML5","FUNÇÃO DISPONÍVEL APENAS PARA BRASIL",IF(J28<>0,VLOOKUP(E28,Questions!$E$5:$L$568,5,0),""))) | M27: Fase: Aderência, Parametrização e Treinamentos | N27: 1ª Onda
B28: =VLOOKUP('Hours Detail'!E28,'BASE_FUNCOES (hide)'!A:W,5,FALSE) -> 3 | C28: Prestador | D28: =IF('General Information'!$C$6="Português",VLOOKUP(B28,'ESTRUTURA_MODULO(hide)'!A:D,2,0),IF('General Information'!$C$6="English",VLOOKUP(B28,'ESTRUTURA_MODULO(hide)'!A:D,3,0),IF('General Information'!$C$6="Español",VLOOKUP(B28,'ESTRUTURA_MODULO(hide)'!A:D,4,0)))) -> Cadastros e Funções Gerais | E28: 100 | F28: =IF('General Information'!$C$6="Português",VLOOKUP(E28,'BASE_FUNCOES (hide)'!A:H,2,0),IF('General Information'!$C$6="English",VLOOKUP(E28,'BASE_FUNCOES (hide)'!A:H,3,0),IF('General Information'!$C$6="Español",VLOOKUP(E28,'BASE_FUNCOES (hide)'!A:H,4,0)))) -> Questionário | G28: =IF(AND('General Information'!$D$16=1,VLOOKUP(B28,Modules!$B$5:$E$496,4,0)=1)=TRUE,VLOOKUP('Hours Detail'!E28,'BASE_FUNCOES (hide)'!$A:$V,10,0),IF(AND('General Information'!$D$16=2,VLOOKUP(B28,Modules!$B$5:$E$496,4,0)=1)=TRUE,VLOOKUP('Hours Detail'!E28,'BASE_FUNCOES (hide)'!$A:$V,11,0),IF(AND('General Information'!$D$16=3,VLOOKUP(B28,Modules!$B$5:$E$496,4,0)=1)=TRUE,VLOOKUP('Hours Detail'!E28,'BASE_FUNCOES (hide)'!$A:$V,12,0),IF(AND('General Information'!$D$16=4,VLOOKUP(B28,Modules!$B$5:$E$496,4,0)=1)=TRUE,VLOOKUP('Hours Detail'!E28,'BASE_FUNCOES (hide)'!$A:$V,13,0),IF(AND('General Information'!$D$16=5,VLOOKUP(B28,Modules!$B$5:$E$496,4,0)=1)=TRUE,VLOOKUP('Hours Detail'!E28,'BASE_FUNCOES (hide)'!$A:$V,14,0), IF(AND('General Information'!$D$16=6,VLOOKUP(B28,Modules!$B$5:$E$496,4,0)=1)=TRUE,VLOOKUP('Hours Detail'!E28,'BASE_FUNCOES (hide)'!$A:$V,15,0),"No")))))) -> No | H28: No | I28: =IF('General Information'!$C$4="Mexico",(ROUNDUP(VLOOKUP(E28,'BASE_FUNCOES (hide)'!A:X,21,0),0)),(ROUNDUP(VLOOKUP(E28,'BASE_FUNCOES (hide)'!A:L,9,0),0))) -> 4 | J28: =ROUNDUP(SUMIF(Questions!$E$5:$E$558,'Hours Detail'!E28,Questions!$F$5:$F$558),0) -> 0 | K28: =IF(H28="Yes",ROUNDUP(IF(VLOOKUP(E28,'BASE_FUNCOES (hide)'!A:T,16,FALSE)<>"No",IF('General Information'!$C$19="HTML5",(I28+J28)*'BASE_FUNCOES (hide)'!$T$2,I28+J28),I28+J28),I28+J28),I28+J28) -> 4 | L28: =IF(OR(E28=121,E28=88,E28=2682,E28=2703,E28=2687,E28=2689,E28=2681,E28=2685)=FALSE,"",IF('General Information'!$C$19="HTML5","FUNÇÃO DISPONÍVEL APENAS PARA BRASIL",IF(J29<>0,VLOOKUP(E29,Questions!$E$5:$L$568,5,0),""))) | M28: Fase: Aderência, Parametrização e Treinamentos | N28: 1ª Onda
B29: =VLOOKUP('Hours Detail'!E29,'BASE_FUNCOES (hide)'!A:W,5,FALSE) -> 3 | C29: Prestador | D29: =IF('General Information'!$C$6="Português",VLOOKUP(B29,'ESTRUTURA_MODULO(hide)'!A:D,2,0),IF('General Information'!$C$6="English",VLOOKUP(B29,'ESTRUTURA_MODULO(hide)'!A:D,3,0),IF('General Information'!$C$6="Español",VLOOKUP(B29,'ESTRUTURA_MODULO(hide)'!A:D,4,0)))) -> Cadastros e Funções Gerais | E29: 944 | F29: =IF('General Information'!$C$6="Português",VLOOKUP(E29,'BASE_FUNCOES (hide)'!A:H,2,0),IF('General Information'!$C$6="English",VLOOKUP(E29,'BASE_FUNCOES (hide)'!A:H,3,0),IF('General Information'!$C$6="Español",VLOOKUP(E29,'BASE_FUNCOES (hide)'!A:H,4,0)))) -> Avaliações | G29: =IF(AND('General Information'!$D$16=1,VLOOKUP(B29,Modules!$B$5:$E$496,4,0)=1)=TRUE,VLOOKUP('Hours Detail'!E29,'BASE_FUNCOES (hide)'!$A:$V,10,0),IF(AND('General Information'!$D$16=2,VLOOKUP(B29,Modules!$B$5:$E$496,4,0)=1)=TRUE,VLOOKUP('Hours Detail'!E29,'BASE_FUNCOES (hide)'!$A:$V,11,0),IF(AND('General Information'!$D$16=3,VLOOKUP(B29,Modules!$B$5:$E$496,4,0)=1)=TRUE,VLOOKUP('Hours Detail'!E29,'BASE_FUNCOES (hide)'!$A:$V,12,0),IF(AND('General Information'!$D$16=4,VLOOKUP(B29,Modules!$B$5:$E$496,4,0)=1)=TRUE,VLOOKUP('Hours Detail'!E29,'BASE_FUNCOES (hide)'!$A:$V,13,0),IF(AND('General Information'!$D$16=5,VLOOKUP(B29,Modules!$B$5:$E$496,4,0)=1)=TRUE,VLOOKUP('Hours Detail'!E29,'BASE_FUNCOES (hide)'!$A:$V,14,0), IF(AND('General Information'!$D$16=6,VLOOKUP(B29,Modules!$B$5:$E$496,4,0)=1)=TRUE,VLOOKUP('Hours Detail'!E29,'BASE_FUNCOES (hide)'!$A:$V,15,0),"No")))))) -> No | H29: No | I29: =IF('General Information'!$C$4="Mexico",(ROUNDUP(VLOOKUP(E29,'BASE_FUNCOES (hide)'!A:X,21,0),0)),(ROUNDUP(VLOOKUP(E29,'BASE_FUNCOES (hide)'!A:L,9,0),0))) -> 2 | J29: =ROUNDUP(SUMIF(Questions!$E$5:$E$558,'Hours Detail'!E29,Questions!$F$5:$F$558),0) -> 0 | K29: =IF(H29="Yes",ROUNDUP(IF(VLOOKUP(E29,'BASE_FUNCOES (hide)'!A:T,16,FALSE)<>"No",IF('General Information'!$C$19="HTML5",(I29+J29)*'BASE_FUNCOES (hide)'!$T$2,I29+J29),I29+J29),I29+J29),I29+J29) -> 2 | L29: =IF(OR(E29=121,E29=88,E29=2682,E29=2703,E29=2687,E29=2689,E29=2681,E29=2685)=FALSE,"",IF('General Information'!$C$19="HTML5","FUNÇÃO DISPONÍVEL APENAS PARA BRASIL",IF(J30<>0,VLOOKUP(E30,Questions!$E$5:$L$568,5,0),""))) | M29: Fase: Aderência, Parametrização e Treinamentos | N29: 1ª Onda
B30: =VLOOKUP('Hours Detail'!E30,'BASE_FUNCOES (hide)'!A:W,5,FALSE) -> 3 | C30: Prestador | D30: =IF('General Information'!$C$6="Português",VLOOKUP(B30,'ESTRUTURA_MODULO(hide)'!A:D,2,0),IF('General Information'!$C$6="English",VLOOKUP(B30,'ESTRUTURA_MODULO(hide)'!A:D,3,0),IF('General Information'!$C$6="Español",VLOOKUP(B30,'ESTRUTURA_MODULO(hide)'!A:D,4,0)))) -> Cadastros e Funções Gerais | E30: 909 | F30: =IF('General Information'!$C$6="Português",VLOOKUP(E30,'BASE_FUNCOES (hide)'!A:H,2,0),IF('General Information'!$C$6="English",VLOOKUP(E30,'BASE_FUNCOES (hide)'!A:H,3,0),IF('General Information'!$C$6="Español",VLOOKUP(E30,'BASE_FUNCOES (hide)'!A:H,4,0)))) -> Cadastro Avaliações | G30: =IF(AND('General Information'!$D$16=1,VLOOKUP(B30,Modules!$B$5:$E$496,4,0)=1)=TRUE,VLOOKUP('Hours Detail'!E30,'BASE_FUNCOES (hide)'!$A:$V,10,0),IF(AND('General Information'!$D$16=2,VLOOKUP(B30,Modules!$B$5:$E$496,4,0)=1)=TRUE,VLOOKUP('Hours Detail'!E30,'BASE_FUNCOES (hide)'!$A:$V,11,0),IF(AND('General Information'!$D$16=3,VLOOKUP(B30,Modules!$B$5:$E$496,4,0)=1)=TRUE,VLOOKUP('Hours Detail'!E30,'BASE_FUNCOES (hide)'!$A:$V,12,0),IF(AND('General Information'!$D$16=4,VLOOKUP(B30,Modules!$B$5:$E$496,4,0)=1)=TRUE,VLOOKUP('Hours Detail'!E30,'BASE_FUNCOES (hide)'!$A:$V,13,0),IF(AND('General Information'!$D$16=5,VLOOKUP(B30,Modules!$B$5:$E$496,4,0)=1)=TRUE,VLOOKUP('Hours Detail'!E30,'BASE_FUNCOES (hide)'!$A:$V,14,0), IF(AND('General Information'!$D$16=6,VLOOKUP(B30,Modules!$B$5:$E$496,4,0)=1)=TRUE,VLOOKUP('Hours Detail'!E30,'BASE_FUNCOES (hide)'!$A:$V,15,0),"No")))))) -> No | H30: =G30 -> No | I30: =IF('General Information'!$C$4="Mexico",(ROUNDUP(VLOOKUP(E30,'BASE_FUNCOES (hide)'!A:X,21,0),0)),(ROUNDUP(VLOOKUP(E30,'BASE_FUNCOES (hide)'!A:L,9,0),0))) -> 8 | J30: =ROUNDUP(SUMIF(Questions!$E$5:$E$558,'Hours Detail'!E30,Questions!$F$5:$F$558),0) -> 0 | K30: =IF(H30="Yes",ROUNDUP(IF(VLOOKUP(E30,'BASE_FUNCOES (hide)'!A:T,16,FALSE)<>"No",IF('General Information'!$C$19="HTML5",(I30+J30)*'BASE_FUNCOES (hide)'!$T$2,I30+J30),I30+J30),I30+J30),I30+J30) -> 8 | L30: =IF(OR(E30=121,E30=88,E30=2682,E30=2703,E30=2687,E30=2689,E30=2681,E30=2685)=FALSE,"",IF('General Information'!$C$19="HTML5","FUNÇÃO DISPONÍVEL APENAS PARA BRASIL",IF(J31<>0,VLOOKUP(E31,Questions!$E$5:$L$568,5,0),""))) | M30: Fase: Aderência, Parametrização e Treinamentos | N30: 1ª Onda
B31: =VLOOKUP('Hours Detail'!E31,'BASE_FUNCOES (hide)'!A:W,5,FALSE) -> 3 | C31: Prestador | D31: =IF('General Information'!$C$6="Português",VLOOKUP(B31,'ESTRUTURA_MODULO(hide)'!A:D,2,0),IF('General Information'!$C$6="English",VLOOKUP(B31,'ESTRUTURA_MODULO(hide)'!A:D,3,0),IF('General Information'!$C$6="Español",VLOOKUP(B31,'ESTRUTURA_MODULO(hide)'!A:D,4,0)))) -> Cadastros e Funções Gerais | E31: 18 | F31: =IF('General Information'!$C$6="Português",VLOOKUP(E31,'BASE_FUNCOES (hide)'!A:H,2,0),IF('General Information'!$C$6="English",VLOOKUP(E31,'BASE_FUNCOES (hide)'!A:H,3,0),IF('General Information'!$C$6="Español",VLOOKUP(E31,'BASE_FUNCOES (hide)'!A:H,4,0)))) -> Cadastro de Estrutura da Conta Paciente | G31: =IF(AND('General Information'!$D$16=1,VLOOKUP(B31,Modules!$B$5:$E$496,4,0)=1)=TRUE,VLOOKUP('Hours Detail'!E31,'BASE_FUNCOES (hide)'!$A:$V,10,0),IF(AND('General Information'!$D$16=2,VLOOKUP(B31,Modules!$B$5:$E$496,4,0)=1)=TRUE,VLOOKUP('Hours Detail'!E31,'BASE_FUNCOES (hide)'!$A:$V,11,0),IF(AND('General Information'!$D$16=3,VLOOKUP(B31,Modules!$B$5:$E$496,4,0)=1)=TRUE,VLOOKUP('Hours Detail'!E31,'BASE_FUNCOES (hide)'!$A:$V,12,0),IF(AND('General Information'!$D$16=4,VLOOKUP(B31,Modules!$B$5:$E$496,4,0)=1)=TRUE,VLOOKUP('Hours Detail'!E31,'BASE_FUNCOES (hide)'!$A:$V,13,0),IF(AND('General Information'!$D$16=5,VLOOKUP(B31,Modules!$B$5:$E$496,4,0)=1)=TRUE,VLOOKUP('Hours Detail'!E31,'BASE_FUNCOES (hide)'!$A:$V,14,0), IF(AND('General Information'!$D$16=6,VLOOKUP(B31,Modules!$B$5:$E$496,4,0)=1)=TRUE,VLOOKUP('Hours Detail'!E31,'BASE_FUNCOES (hide)'!$A:$V,15,0),"No")))))) -> No | H31: =G31 -> No | I31: =IF('General Information'!$C$4="Mexico",(ROUNDUP(VLOOKUP(E31,'BASE_FUNCOES (hide)'!A:X,21,0),0)),(ROUNDUP(VLOOKUP(E31,'BASE_FUNCOES (hide)'!A:L,9,0),0))) -> 8 | J31: =ROUNDUP(SUMIF(Questions!$E$5:$E$558,'Hours Detail'!E31,Questions!$F$5:$F$558),0) -> 0 | K31: =IF(H31="Yes",ROUNDUP(IF(VLOOKUP(E31,'BASE_FUNCOES (hide)'!A:T,16,FALSE)<>"No",IF('General Information'!$C$19="HTML5",(I31+J31)*'BASE_FUNCOES (hide)'!$T$2,I31+J31),I31+J31),I31+J31),I31+J31) -> 8 | L31: =IF(OR(E31=121,E31=88,E31=2682,E31=2703,E31=2687,E31=2689,E31=2681,E31=2685)=FALSE,"",IF('General Information'!$C$19="HTML5","FUNÇÃO DISPONÍVEL APENAS PARA BRASIL",IF(J32<>0,VLOOKUP(E32,Questions!$E$5:$L$568,5,0),""))) | M31: Fase: Aderência, Parametrização e Treinamentos | N31: 1ª Onda
